Workbook
Name OLE_LINK1: Основные!$A$97
Name OLE_LINK2: Основные!$A$97

Sheet театры, музеи
A1: 7.1. ЧИСЛЕННОСТЬ ЗРИТЕЛЕЙ ТЕАТРОВ И ЧИСЛО ПОСЕЩЕНИЙ МУЗЕЕВ на 1 000 человек населения1);2)
B2: Численность зрителей театров, человек | I2: Число посещений музеев, человек
B3: 2010 | C3: 2015 | D3: 2020 | E3: 2021 | F3: 2022 | G3: 2023 | H3: Место, | I3: 2010 | J3: 2015 | K3: 2020 | L3: 2021 | M3: 2022 | N3: 2023 | O3: Место,
A4: Российская Федерация | B4: 217 | C4: 260 | D4: 109 | E4: 173 | F4: 245 | G4: 284 | I4: 567 | J4: 533 | K4: 400 | L4: 648 | M4: 827 | N4: 904
A5: Центральный | B5: 262 | C5: 315 | D5: 131 | E5: 169 | F5: 255 | G5: 303 | H5: 2 | I5: 647 | J5: 831 | K5: 505 | L5: 683 | M5: 932 | N5: 1023 | O5: 2
A6: федеральный округ
A7: Белгородская область | B7: 118 | C7: 134 | D7: 72 | E7: 111 | F7: 141 | G7: 152 | H7: 72 | I7: 436 | J7: 220 | K7: 361 | L7: 689 | M7: 782 | N7: 732 | O7: 29
A8: Брянская область | B8: 139 | C8: 182 | D8: 81 | E8: 94 | F8: 148 | G8: 173 | H8: 66 | I8: 786 | J8: 450 | K8: 437 | L8: 449 | M8: 845 | N8: 677 | O8: 33
A9: Владимирская область | B9: 115 | C9: 135 | D9: 63 | E9: 66 | F9: 66 | G9: 78 | H9: 82 | I9: 1 376 | J9: 1103 | K9: 585 | L9: 1133 | M9: 1 187 | N9: 1292 | O9: 12
A10: Воронежская область | B10: 159 | C10: 177 | D10: 65 | E10: 87 | F10: 158 | G10: 228 | H10: 49 | I10: 220 | J10: 133 | K10: 175 | L10: 320 | M10: 386 | N10: 401 | O10: 58
A11: Ивановская область | B11: 233 | C11: 248 | D11: 86 | E11: 187 | F11: 324 | G11: 350 | H11: 10 | I11: 409 | J11: 205 | K11: 186 | L11: 411 | M11: 514 | N11: 619 | O11: 34
A12: Калужская область | B12: 185 | C12: 203 | D12: 91 | E12: 173 | F12: 184 | G12: 205 | H12: 58 | I12: 464 | J12: 401 | K12: 391 | L12: 889 | M12: 1 080 | N12: 1108 | O12: 19
A13: Костромская область | B13: 245 | C13: 335 | D13: 147 | E13: 161 | F13: 264 | G13: 257 | H13: 37 | J13: 489 | K13: 598 | L13: 753 | M13: 1 125 | N13: 1124 | O13: 18
A14: Курская область | B14: 164 | C14: 187 | D14: 84 | E14: 75 | F14: 157 | G14: 234 | H14: 47 | I14: 309 | J14: 157 | K14: 243 | L14: 378 | M14: 496 | N14: 559 | O14: 39
A15: Липецкая область | B15: 138 | C15: 169 | D15: 60 | E15: 81 | F15: 160 | G15: 200 | H15: 61 | I15: 186 | J15: 174 | K15: 140 | L15: 156 | M15: 171 | N15: 198 | O15: 78
A16: Московская область | B16: 91 | C16: 140 | D16: 61 | E16: 81 | F16: 102 | G16: 104 | H16: 79 | I16: 378 | J16: 314 | K16: 368 | L16: 527 | M16: 646 | N16: 851 | O16: 23
A17: Орловская область | B17: 238 | C17: 212 | D17: 92 | E17: 125 | F17: 256 | G17: 327 | H17: 16 | I17: 314 | J17: 265 | K17: 194 | L17: 312 | M17: 366 | N17: 405 | O17: 57
A18: Рязанская область | B18: 198 | C18: 232 | D18: 120 | E18: 128 | F18: 197 | G18: 264 | H18: 33 | I18: 494 | J18: 496 | K18: 462 | L18: 783 | M18: 905 | N18: 1142 | O18: 17
A19: Смоленская область | B19: 113 | C19: 115 | D19: 56 | E19: 72 | F19: 125 | G19: 169 | H19: 69 | I19: 441 | J19: 376 | K19: 276 | L19: 598 | M19: 850 | N19: 813 | O19: 25
A20: Тамбовская область | B20: 138 | C20: 191 | D20: 94 | E20: 143 | F20: 209 | G20: 255 | H20: 39 | I20: 290 | J20: 162 | K20: 311 | L20: 430 | M20: 445 | N20: 619 | O20: 34
A21: Тверская область | B21: 181 | C21: 227 | D21: 95 | E21: 171 | F21: 281 | G21: 350 | H21: 10 | I21: 334 | J21: 236 | K21: 402 | L21: 601 | M21: 672 | N21: 746 | O21: 27
A22: Тульская область | B22: 209 | C22: 238 | D22: 82 | E22: 125 | F22: 187 | G22: 237 | H22: 45 | I22: 608 | J22: 613 | K22: 720 | L22: 1003 | M22: 1 269 | N22: 1506 | O22: 9
A23: Ярославская область | B23: 226 | C23: 269 | D23: 150 | E23: 202 | F23: 261 | G23: 287 | H23: 24 | I23: 1 402 | J23: 971 | K23: 1469 | L23: 2328 | M23: 2 863 | N23: 3070 | O23: 3
A24: г. Москва | B24: 527 | C24: 611 | D24: 240 | E24: 294 | F24: 452 | G24: 538 | H24: 3 | I24: 993 | J24: 1839 | K24: 697 | L24: 748 | M24: 1 208 | N24: 1256 | O24: 13
A25: Северо-Западный | B25: 279 | C25: 395 | D25: 179 | E25: 286 | F25: 390 | G25: 459 | H25: 1 | I25: 1 779 | J25: 1506 | K25: 1100 | L25: 1933 | M25: 2 502 | N25: 2822 | O25: 1
A26: федеральный округ
A27: Республика Карелия | B27: 166 | C27: 241 | D27: 142 | E27: 228 | F27: 269 | G27: 375 | H27: 8 | I27: 683 | J27: 278 | K27: 556 | L27: 899 | M27: 1 354 | N27: 1311 | O27: 11
A28: Республика Коми | B28: 163 | C28: 188 | D28: 101 | E28: 165 | F28: 232 | G28: 279 | H28: 26 | I28: 388 | J28: 204 | K28: 220 | L28: 330 | M28: 455 | N28: 446 | O28: 50
A29: Архангельская область | B29: 136 | C29: 190 | D29: 106 | E29: 176 | F29: 203 | G29: 256 | I29: 550 | J29: 546 | K29: 429 | L29: 941 | M29: 1 279 | N29: 1201
A30: в том числе:
A31: Ненецкий автономный округ | B31: – | C31: – | D31: – | E31: – | F31: – | G31: – | I31: 522 | J31: 439 | K31: 149 | L31: 378 | M31: 452 | N31: 438 | O31: 51
A32: Архангельская область без автономного округа | B32: 141 | C32: 198 | D32: 110 | E32: 184 | F32: 211 | G32: 267 | H32: 31 | I32: 551 | J32: 550 | K32: 440 | L32: 964 | M32: 1 314 | N32: 1234 | O32: 14
A33: Вологодская область | B33: 154 | C33: 164 | D33: 79 | E33: 148 | F33: 218 | G33: 264 | H33: 33 | I33: 895 | J33: 600 | K33: 595 | L33: 979 | M33: 1 095 | N33: 1196 | O33: 15
A34: Калинингpадская область | B34: 154 | C34: 209 | D34: 80 | E34: 111 | F34: 183 | G34: 211 | H34: 56 | I34: 981 | J34: 854 | K34: 965 | L34: 1957 | M34: 1 828 | N34: 2318 | O34: 4
A35: Ленинградская область | B35: 145 | C35: 119 | D35: 54 | E35: 95 | F35: 122 | G35: 126 | H35: 75 | I35: 731 | J35: 261 | K35: 448 | L35: 575 | M35: 696 | N35: 848 | O35: 24
A36: Мурманская область | B36: 139 | C36: 138 | D36: 65 | E36: 141 | F36: 205 | G36: 214 | H36: 54 | I36: 389 | J36: 359 | K36: 182 | L36: 356 | M36: 455 | N36: 540 | O36: 44
A37: Новгородская область | B37: 106 | C37: 130 | D37: 50 | E37: 60 | F37: 127 | G37: 115 | H37: 78 | I37: 1 095 | J37: 1129 | K37: 862 | L37: 1438 | M37: 1 910 | N37: 2200 | O37: 6
A38: Псковская область | B38: 151 | C38: 145 | D38: 61 | E38: 80 | F38: 172 | G38: 204 | H38: 59 | I38: 954 | J38: 1027 | K38: 1645 | L38: 2329 | M38: 2 581 | N38: 3211 | O38: 2
A39: г. Санкт-Петербург | B39: 517 | C39: 766 | D39: 444 | E39: 520 | F39: 695 | G39: 822 | H39: 1 | I39: 3 669 | J39: 3066 | K39: 1834 | L39: 3298 | M39: 4 450 | N39: 4987 | O39: 1
A40: Южный | B40: 124 | C40: 158 | D40: 67 | E40: 105 | F40: 153 | G40: 183 | H40: 7 | I40: 519 | J40: 388 | K40: 450 | L40: 672 | M40: 661 | N40: 671 | O40: 4
A41: федеральный округ
A42: Республика Адыгея | B42: 96 | C42: 105 | D42: 33 | E42: 104 | F42: 151 | G42: 181 | H42: 63 | I42: 141 | J42: 82 | K42: 102 | L42: 162 | M42: 277 | N42: 287 | O42: 70
A43: Республика Калмыкия | B43: 113 | C43: 103 | D43: 31 | E43: 62 | F43: 201 | G43: 245 | H43: 43 | I43: 126 | J43: 39 | K43: 42 | L43: 129 | M43: 131 | N43: 190 | O43: 80
A44: Республика Крым | C44: 177 | D44: 63 | E44: 131 | F44: 180 | G44: 228 | H44: 49 | J44: 604 | K44: 1224 | L44: 1650 | M44: 1 159 | N44: 944 | O44: 21
A45: Краснодарский край | B45: 86 | C45: 103 | D45: 25 | E45: 38 | F45: 74 | G45: 103 | H45: 80 | I45: 397 | J45: 226 | K45: 159 | L45: 308 | M45: 337 | N45: 368 | O45: 21
A46: Астраханская область | B46: 214 | C46: 339 | D46: 154 | E46: 201 | F46: 298 | G46: 283 | H46: 25 | I46: 359 | J46: 184 | K46: 164 | L46: 185 | M46: 424 | N46: 417 | O46: 54
A47: Волгоградская область | B47: 153 | C47: 185 | D47: 67 | E47: 150 | F47: 181 | G47: 214 | H47: 54 | I47: 1 205 | J47: 919 | K47: 771 | L47: 1121 | M47: 1 387 | N47: 1641 | O47: 7
A48: Ростовская область | B48: 133 | C48: 151 | D48: 97 | E48: 126 | F48: 179 | G48: 204 | H48: 59 | I48: 351 | J48: 197 | K48: 206 | L48: 367 | M48: 402 | N48: 413 | O48: 56
A49: г. Севастополь | C49: 354 | D49: 176 | E49: 209 | F49: 306 | G49: 358 | H49: 9 | J49: 1288 | K49: 2302 | L49: 2997 | M49: 2 037 | N49: 1536 | O49: 8
A50: Северо-Кавказский | B50: 91 | C50: 119 | D50: 42 | E50: 104 | F50: 125 | G50: 150 | H50: 8 | I50: 174 | J50: 125 | K50: 116 | L50: 222 | M50: 285 | N50: 304 | O50: 8
A51: федеральный округ
A52: Республика Дагестан | B52: 108 | C52: 108 | D52: 35 | E52: 78 | F52: 113 | G52: 122 | H52: 76 | I52: 171 | J52: 106 | K52: 63 | L52: 97 | M52: 170 | N52: 183 | O52: 81
A53: Республика Ингушетия | B53: 65 | C53: 190 | D53: 49 | E53: 14 | F53: 136 | G53: 218 | H53: 53 | I53: 654 | J53: 459 | K53: 207 | L53: 414 | M53: 658 | N53: 693 | O53: 31
A54: Кабардино-Балкарская Республика | B54: 92 | C54: 107 | D54: 37 | E54: 143 | F54: 151 | G54: 210 | H54: 57 | I54: 101 | J54: 96 | K54: 116 | L54: 306 | M54: 344 | N54: 375 | O54: 61
A55: Карачаево-Черкесская Республика | B55: 73 | C55: 75 | D55: 19 | E55: 44 | F55: 102 | G55: 99 | H55: 81 | I55: 47 | J55: 25 | K55: 11 | L55: 55 | M55: 77 | N55: 129 | O55: 85
A56: Республика Северная Осетия | B56: 192 | C56: 242 | D56: 76 | E56: 182 | F56: 269 | G56: 317 | H56: 20 | I56: 54 | J56: 36 | K56: 71 | L56: 152 | M56: 140 | N56: 180 | O56: 82
A57: Чеченская Республика | B57: 28 | C57: 154 | D57: 67 | E57: 205 | F57: 92 | G57: 154 | H57: 71 | I57: 13 | J57: 141 | K57: 141 | L57: 217 | M57: 289 | N57: 268 | O57: 72
A58: Ставропольский край | B58: 84 | C58: 84 | D58: 33 | E58: 76 | F58: 117 | G58: 117 | H58: 77 | I58: 253 | J58: 131 | K58: 173 | L58: 345 | M58: 392 | N58: 425 | O58: 52
A59: Приволжский | B59: 210 | C59: 243 | D59: 100 | E59: 179 | F59: 256 | G59: 294 | H59: 4 | I59: 332 | J59: 283 | K59: 258 | L59: 471 | M59: 637 | N59: 710 | O59: 3
A60: федеральный округ
A61: Республика Башкортостан | B61: 199 | C61: 210 | D61: 78 | E61: 198 | F61: 245 | G61: 257 | H61: 37 | I61: 136 | J61: 97 | K61: 100 | L61: 254 | M61: 297 | N61: 295 | O61: 69
A62: Республика Марий Эл | B62: 302 | C62: 373 | D62: 182 | E62: 296 | F62: 462 | G62: 561 | H62: 2 | I62: 553 | J62: 338 | K62: 387 | L62: 784 | M62: 784 | N62: 868 | O62: 22
A63: Республика Мордовия | B63: 181 | C63: 254 | D63: 87 | E63: 178 | F63: 279 | G63: 324 | H63: 18 | I63: 266 | J63: 161 | K63: 127 | L63: 277 | M63: 318 | N63: 334 | O63: 66
A64: Республика Татарстан | B64: 219 | C64: 285 | D64: 139 | E64: 217 | F64: 282 | G64: 341 | H64: 15 | I64: 455 | J64: 733 | K64: 731 | L64: 1284 | M64: 1806 | N64: 2230 | O64: 5
A65: Удмуртская Республика | B65: 250 | C65: 279 | D65: 113 | E65: 184 | F65: 278 | G65: 312 | H65: 22 | I65: 472 | J65: 236 | K65: 296 | L65: 449 | M65: 539 | N65: 572 | O65: 37
A66: Чувашская Республика | B66: 278 | C66: 319 | D66: 126 | E66: 307 | F66: 379 | G66: 388 | H66: 6 | I66: 229 | J66: 179 | K66: 63 | L66: 233 | M66: 307 | N66: 347 | O66: 64
A67: Пермский край | B67: 262 | C67: 336 | D67: 122 | E67: 255 | F67: 325 | G67: 349 | H67: 13 | I67: 403 | J67: 255 | K67: 201 | L67: 336 | M67: 443 | N67: 396 | O67: 60
A68: Кировская область | B68: 181 | C68: 161 | D68: 65 | E68: 144 | F68: 202 | G68: 236 | H68: 46 | I68: 530 | J68: 426 | K68: 235 | L68: 373 | M68: 595 | N68: 558 | O68: 40
A69: Нижегородская область | B69: 192 | C69: 229 | D69: 82 | E69: 140 | F69: 261 | G69: 317 | H69: 20 | I69: 348 | J69: 328 | K69: 242 | L69: 437 | M69: 783 | N69: 752 | O69: 26
A70: Оренбургская область | B70: 150 | C70: 158 | D70: 70 | E70: 121 | F70: 185 | G70: 220 | H70: 52 | I70: 100 | J70: 80 | K70: 76 | L70: 194 | M70: 237 | N70: 255 | O70: 74
A71: Пензенская область | B71: 144 | C71: 135 | D71: 67 | E71: 58 | F71: 139 | G71: 175 | H71: 65 | I71: 376 | J71: 190 | K71: 222 | L71: 339 | M71: 505 | N71: 521 | O71: 45
A72: Самарская область | B72: 186 | C72: 255 | D72: 135 | E72: 177 | F72: 244 | G72: 277 | H72: 28 | I72: 260 | J72: 206 | K72: 198 | L72: 334 | M72: 397 | N72: 415 | O72: 55
... A75: Уральский | B75: 209 | C75: 231 | D75: 94 | E75: 174 | F75: 223 | G75: 248 | H75: 6 | I75: 287 | J75: 191 | K75: 187 | L75: 449 | M75: 548 | N75: 546 | O75: 5
A76: федеральный округ
A77: Курганская область | B77: 148 | C77: 152 | D77: 56 | E77: 81 | F77: 139 | G77: 171 | H77: 68 | I77: 307 | J77: 254 | K77: 150 | L77: 360 | M77: 379 | N77: 425 | O77: 52
A78: Свердловская область | B78: 253 | C78: 301 | D78: 127 | E78: 215 | F78: 283 | G78: 325 | H78: 17 | I78: 377 | J78: 210 | K78: 230 | L78: 425 | M78: 554 | N78: 589 | O78: 36
A79: Тюменская область | B79: 160 | C79: 168 | D79: 60 | E79: 150 | F79: 170 | G79: 200 | I79: 279 | J79: 243 | K79: 245 | L79: 742 | M79: 892 | N79: 809
A80: в том числе:
A81: Ханты-Мансийский автономный округ | B81: 136 | C81: 158 | D81: 31 | E81: 72 | F81: 135 | G81: 162 | H81: 70 | I81: 291 | J81: 182 | K81: 76 | L81: 225 | M81: 307 | N81: 278 | O81: 71
A82: Ямало-Ненецкий автономный округ | B82: – | C82: – | D82: – | E82: – | F82: – | G82: – | I82: 281 | J82: 216 | K82: 284 | L82: 444 | M82: 459 | N82: 490 | O82: 48
A83: Тюменская область без автономных округов | B83: 250 | C83: 238 | D83: 111 | E83: 283 | F83: 262 | G83: 304 | H83: 23 | I83: 263 | J83: 319 | K83: 413 | L83: 1389 | M83: 1658 | N83: 1485 | O83: 10
A84: Челябинская область | B84: 217 | C84: 229 | D84: 99 | E84: 170 | F84: 226 | G84: 225 | H84: 51 | I84: 178 | J84: 98 | K84: 80 | L84: 173 | M84: 191 | N84: 221 | O84: 77
A85: Сибирский | B85: 243 | C85: 263 | D85: 108 | E85: 186 | F85: 271 | G85: 299 | H85: 3 | I85: 381 | J85: 247 | K85: 190 | L85: 342 | M85: 432 | N85: 459 | O85: 6
A86: федеральный округ
A87: Республика Алтай | B87: 39 | C87: 86 | D87: 30 | E87: 65 | F87: 76 | G87: 135 | H87: 74 | I87: 25 | J87: 156 | K87: 51 | L87: 244 | M87: 312 | N87: 345 | O87: 65
A88: Республика Тыва | B88: 48 | C88: 97 | D88: 77 | E88: 236 | F88: 315 | G88: 420 | H88: 4 | I88: 148 | J88: 81 | K88: 54 | L88: 146 | M88: 143 | N88: 158 | O88: 84
A89: Республика Хакасия | B89: 181 | C89: 248 | D89: 90 | E89: 203 | F89: 210 | G89: 258 | H89: 36 | I89: 439 | J89: 390 | K89: 317 | L89: 600 | M89: 677 | N89: 695 | O89: 30
A90: Алтайский край | B90: 157 | C90: 167 | D90: 80 | E90: 150 | F90: 220 | G90: 234 | H90: 47 | I90: 244 | J90: 101 | K90: 97 | L90: 202 | M90: 222 | N90: 228 | O90: 76
A91: Красноярский край | B91: 291 | C91: 318 | D91: 124 | E91: 209 | F91: 357 | G91: 385 | H91: 7 | I91: 610 | J91: 395 | K91: 237 | L91: 497 | M91: 695 | N91: 736 | O91: 28
A92: Иркутская область | B92: 200 | C92: 239 | D92: 66 | E92: 118 | F92: 217 | G92: 251 | H92: 40 | I92: 403 | J92: 265 | K92: 148 | L92: 239 | M92: 354 | N92: 357 | O92: 63
A93: Кемеровская область | B93: 149 | C93: 193 | D93: 67 | E93: 148 | F93: 173 | G93: 178 | H93: 64 | I93: 465 | J93: 278 | K93: 320 | L93: 448 | M93: 475 | N93: 496 | O93: 47
A94: Новосибирская область | B94: 352 | C94: 327 | D94: 173 | E94: 273 | F94: 335 | G94: 394 | H94: 5 | I94: 207 | J94: 141 | K94: 108 | L94: 178 | M94: 201 | N94: 261 | O94: 73
A95: Омская область | B95: 360 | C95: 354 | D95: 156 | E95: 227 | F95: 323 | G95: 342 | H95: 14 | I95: 423 | J95: 268 | K95: 231 | L95: 485 | M95: 608 | N95: 549 | O95: 41
A96: Томская область | B96: 284 | C96: 320 | D96: 99 | E96: 149 | F96: 299 | G96: 278 | H96: 27 | I96: 285 | J96: 274 | K96: 181 | L96: 307 | M96: 521 | N96: 683 | O96: 32
A97: Дальневосточный | B97: 190 | C97: 233 | D97: 101 | E97: 176 | F97: 236 | G97: 260 | H97: 5 | I97: 377 | J97: 249 | K97: 192 | L97: 321 | M97: 366 | N97: 405 | O97: 7
A98: федеральный округ
A99: Республика Бурятия | B99: 182 | C99: 236 | D99: 73 | E99: 158 | F99: 250 | G99: 263 | H99: 35 | I99: 436 | J99: 354 | K99: 198 | L99: 343 | M99: 378 | N99: 401 | O99: 58
A100: Республика Саха (Якутия) | B100: 183 | C100: 209 | D100: 68 | E100: 142 | F100: 194 | G100: 242 | H100: 44 | I100: 433 | J100: 284 | K100: 213 | L100: 413 | M100: 503 | N100: 500 | O100: 46
A101: Забайкальский край | B101: 229 | C101: 265 | D101: 112 | E101: 211 | F101: 222 | G101: 276 | H101: 29 | I101: 195 | J101: 98 | K101: 113 | L101: 246 | M101: 301 | N101: 324 | O101: 67
A102: Камчатский край | B102: 186 | C102: 232 | D102: 118 | E102: 145 | F102: 263 | G102: 271 | H102: 30 | I102: 250 | J102: 186 | K102: 514 | L102: 553 | M102: 592 | N102: 548 | O102: 42
...

Sheet спортивные сооружния
A1: 7.2. ЧИСЛО СПОРТИВНЫХ СООРУЖЕНИЙ
B2: Стадионы с трибунами | H2: Плоскостные спортивные сооружения
B3: на 1500 мест и более | H3: (площадки и поля) | N3: Спортивные залы | T3: Плавательные бассейны
B4: 2010 | C4: 2015 | D4: 2020 | E4: 2021 | F4: 2022 | G4: 2023 | H4: 2010 | I4: 2015 | J4: 2020 | K4: 2021 | L4: 2022 | M4: 2023 | N4: 2010 | O4: 2015 | P4: 2020 | Q4: 2021 | R4: 2022 | S4: 2023 | T4: 2010 | U4: 2015 | V4: 2020 | W4: 2021 | X4: 2022 | Y4: 2023
A5: Российская Федерация | B5: 1 903 | C5: 1 877 | D5: 1 770 | E5: 1676 | F5: 1632 | G5: 1623 | H5: 129 637 | I5: 148 194 | J5: 154 000 | K5: 157206 | L5: 158944 | M5: 161662 | N5: 72 381 | O5: 72 016 | P5: 75 281 | Q5: 76105 | R5: 76873 | S5: 77777 | T5: 4 237 | U5: 5 196 | V5: 6 229 | W5: 6442 | X5: 6575 | Y5: 6765 | Z5: Российская Федерация
A6: Центральный | B6: 531 | C6: 465 | D6: 414 | E6: 410 | F6: 397 | G6: 395 | H6: 32 516 | I6: 40 280 | J6: 44 824 | K6: 46416 | L6: 47 322 | M6: 48554 | N6: 15 586 | O6: 16 859 | P6: 18 037 | Q6: 18354 | R6: 18562 | S6: 18795 | T6: 1 216 | U6: 1 401 | V6: 1 741 | W6: 1774 | X6: 1808 | Y6: 1880 | Z6: Центральный
A7: федеральный округ | Z7: федеральный округ
A8: Белгородская область | B8: 19 | C8: 25 | D8: 24 | E8: 24 | F8: 22 | G8: 23 | H8: 3 088 | I8: 3 300 | J8: 3 283 | K8: 3321 | L8: 3 272 | M8: 3268 | N8: 800 | O8: 819 | P8: 875 | Q8: 887 | R8: 899 | S8: 909 | T8: 129 | U8: 142 | V8: 159 | W8: 154 | X8: 156 | Y8: 149 | Z8: Белгородская область
A9: Брянская область | B9: 19 | C9: 30 | D9: 21 | E9: 17 | F9: 16 | G9: 18 | H9: 1 571 | I9: 1 517 | J9: 1 426 | K9: 1394 | L9: 1 374 | M9: 1437 | N9: 682 | O9: 675 | P9: 646 | Q9: 667 | R9: 686 | S9: 688 | T9: 38 | U9: 50 | V9: 49 | W9: 53 | X9: 56 | Y9: 57 | Z9: Брянская область
A10: Владимирская область | B10: 33 | C10: 33 | D10: 33 | E10: 33 | F10: 30 | G10: 28 | H10: 1 381 | I10: 1 554 | J10: 1 716 | K10: 1778 | L10: 1 776 | M10: 1758 | N10: 673 | O10: 716 | P10: 811 | Q10: 821 | R10: 847 | S10: 857 | T10: 43 | U10: 57 | V10: 68 | W10: 69 | X10: 71 | Y10: 71 | Z10: Владимирская область
A11: Воронежская область | B11: 29 | C11: 25 | D11: 10 | E11: 10 | F11: 10 | G11: 10 | H11: 3 471 | I11: 4 171 | J11: 4 569 | K11: 4509 | L11: 4 296 | M11: 4331 | N11: 1 285 | O11: 1 428 | P11: 1 308 | Q11: 1337 | R11: 1 338 | S11: 1350 | T11: 52 | U11: 83 | V11: 66 | W11: 63 | X11: 72 | Y11: 72 | Z11: Воронежская область
A12: Ивановская область | B12: 25 | C12: 21 | D12: 16 | E12: 16 | F12: 14 | G12: 14 | H12: 667 | I12: 1 030 | J12: 1 064 | K12: 1066 | L12: 1 043 | M12: 1023 | N12: 407 | O12: 518 | P12: 529 | Q12: 537 | R12: 542 | S12: 553 | T12: 24 | U12: 30 | V12: 35 | W12: 37 | X12: 38 | Y12: 38 | Z12: Ивановская область
A13: Калужская область | B13: 25 | C13: 18 | D13: 15 | E13: 15 | F13: 15 | G13: 15 | H13: 1 032 | I13: 1 066 | J13: 918 | K13: 929 | L13: 930 | M13: 935 | N13: 530 | O13: 592 | P13: 618 | Q13: 626 | R13: 625 | S13: 625 | T13: 28 | U13: 49 | V13: 71 | W13: 74 | X13: 76 | Y13: 79 | Z13: Калужская область
A14: Костромская область | B14: 17 | C14: 6 | D14: 6 | E14: 7 | F14: 6 | G14: 6 | H14: 684 | I14: 653 | J14: 685 | K14: 708 | L14: 718 | M14: 720 | N14: 358 | O14: 380 | P14: 397 | Q14: 408 | R14: 411 | S14: 413 | T14: 31 | U14: 32 | V14: 33 | W14: 34 | X14: 33 | Y14: 33 | Z14: Костромская область
A15: Курская область | B15: 15 | C15: 13 | D15: 11 | E15: 9 | F15: 9 | G15: 9 | H15: 1 189 | I15: 1 159 | J15: 1 081 | K15: 1094 | L15: 1 095 | M15: 1099 | N15: 657 | O15: 659 | P15: 673 | Q15: 680 | R15: 683 | S15: 679 | T15: 36 | U15: 35 | V15: 47 | W15: 49 | X15: 49 | Y15: 54 | Z15: Курская область
A16: Липецкая область | B16: 21 | C16: 21 | D16: 22 | E16: 22 | F16: 22 | G16: 22 | H16: 1 734 | I16: 1 941 | J16: 2 074 | K16: 2112 | L16: 2 175 | M16: 2189 | N16: 569 | O16: 602 | P16: 626 | Q16: 645 | R16: 654 | S16: 660 | T16: 33 | U16: 42 | V16: 52 | W16: 57 | X16: 58 | Y16: 59 | Z16: Липецкая область
A17: Московская область | B17: 129 | C17: 126 | D17: 123 | E17: 122 | F17: 119 | G17: 118 | H17: 3 079 | I17: 4 901 | J17: 2 427 | K17: 2874 | L17: 3 001 | M17: 3381 | N17: 1 886 | O17: 2 207 | P17: 2 382 | Q17: 2505 | R17: 2 528 | S17: 2594 | T17: 196 | U17: 271 | V17: 332 | W17: 349 | X17: 348 | Y17: 381 | Z17: Московская область
A18: Орловская область | B18: 14 | C18: 14 | D18: 3 | E18: 3 | F18: 3 | G18: 3 | H18: 1 026 | I18: 1 071 | J18: 579 | K18: 576 | L18: 581 | M18: 585 | N18: 441 | O18: 586 | P18: 562 | Q18: 571 | R18: 598 | S18: 518 | T18: 30 | U18: 32 | V18: 34 | W18: 34 | X18: 34 | Y18: 33 | Z18: Орловская область
A19: Рязанская область | B19: 13 | C19: 15 | D19: 13 | E19: 13 | F19: 13 | G19: 13 | H19: 1 333 | I19: 1 359 | J19: 1 310 | K19: 1327 | L19: 1 329 | M19: 1334 | N19: 499 | O19: 516 | P19: 604 | Q19: 617 | R19: 612 | S19: 621 | T19: 31 | U19: 41 | V19: 58 | W19: 59 | X19: 59 | Y19: 63 | Z19: Рязанская область
A20: Смоленская область | B20: 24 | C20: 24 | D20: 24 | E20: 24 | F20: 24 | G20: 24 | H20: 1 173 | I20: 1 207 | J20: 1 303 | K20: 1315 | L20: 1 320 | M20: 1322 | N20: 934 | O20: 924 | P20: 913 | Q20: 907 | R20: 925 | S20: 914 | T20: 33 | U20: 55 | V20: 63 | W20: 66 | X20: 67 | Y20: 66 | Z20: Смоленская область
A21: Тамбовская область | B21: 19 | C21: 21 | D21: 21 | E21: 21 | F21: 21 | G21: 21 | H21: 2 223 | I21: 2 803 | J21: 2 874 | K21: 2876 | L21: 2 878 | M21: 2879 | N21: 533 | O21: 632 | P21: 653 | Q21: 654 | R21: 656 | S21: 656 | T21: 25 | U21: 40 | V21: 41 | W21: 41 | X21: 41 | Y21: 42 | Z21: Тамбовская область
A22: Тверская область | B22: 19 | C22: 18 | D22: 17 | E22: 17 | F22: 17 | G22: 17 | H22: 1 669 | I22: 1 947 | J22: 2 308 | K22: 2540 | L22: 2 578 | M22: 2672 | N22: 1 275 | O22: 819 | P22: 859 | Q22: 873 | R22: 880 | S22: 889 | T22: 62 | U22: 57 | V22: 63 | W22: 65 | X22: 68 | Y22: 69 | Z22: Тверская область
A23: Тульская область | B23: 29 | C23: 20 | D23: 17 | E23: 17 | F23: 17 | G23: 17 | H23: 1 064 | I23: 1 234 | J23: 1 313 | K23: 1331 | L23: 1 344 | M23: 1351 | N23: 557 | O23: 610 | P23: 623 | Q23: 633 | R23: 638 | S23: 643 | T23: 30 | U23: 46 | V23: 50 | W23: 49 | X23: 50 | Y23: 49 | Z23: Тульская область
A24: Ярославская область | B24: 18 | C24: 13 | D24: 13 | E24: 13 | F24: 12 | G24: 8 | H24: 1 048 | I24: 1 128 | J24: 1 263 | K24: 1270 | L24: 1 299 | M24: 1311 | N24: 577 | O24: 559 | P24: 566 | Q24: 569 | R24: 569 | S24: 572 | T24: 30 | U24: 24 | V24: 29 | W24: 30 | X24: 33 | Y24: 33 | Z24: Ярославская область
A25: г. Москва | B25: 63 | C25: 22 | D25: 25 | E25: 27 | F25: 27 | G25: 29 | H25: 5 084 | I25: 8 239 | J25: 14 631 | K25: 15396 | L25: 16 313 | M25: 16959 | N25: 2 923 | O25: 3 617 | P25: 4 392 | Q25: 4417 | R25: 4 471 | S25: 4654 | T25: 365 | U25: 315 | V25: 491 | W25: 491 | X25: 499 | Y25: 532 | Z25: г. Москва
A26: Северо-Западный | B26: 104 | C26: 91 | D26: 83 | E26: 82 | F26: 80 | G26: 78 | H26: 8 318 | I26: 9 622 | J26: 11 251 | K26: 11419 | L26: 11 470 | M26: 11688 | N26: 6 549 | O26: 6 258 | P26: 6 647 | Q26: 6749 | R26: 6784 | S26: 6932 | T26: 409 | U26: 638 | V26: 789 | W26: 826 | X26: 847 | Y26: 868 | Z26: Северо-Западный
A27: федеральный округ | Z27: федеральный округ
A28: Республика Карелия | B28: 4 | C28: 4 | D28: 4 | E28: 4 | F28: 4 | G28: 3 | H28: 547 | I28: 624 | J28: 616 | K28: 623 | L28: 622 | M28: 612 | N28: 748 | O28: 384 | P28: 416 | Q28: 421 | R28: 422 | S28: 416 | T28: 26 | U28: 30 | V28: 39 | W28: 38 | X28: 38 | Y28: 32 | Z28: Республика Карелия
A29: Республика Коми | B29: 8 | C29: 7 | D29: 7 | E29: 7 | F29: 7 | G29: 7 | H29: 755 | I29: 800 | J29: 890 | K29: 933 | L29: 772 | M29: 781 | N29: 719 | O29: 585 | P29: 537 | Q29: 537 | R29: 503 | S29: 501 | T29: 37 | U29: 41 | V29: 43 | W29: 44 | X29: 43 | Y29: 43 | Z29: Республика Коми
A30: Архангельская область | B30: 13 | C30: 9 | D30: 8 | E30: 8 | F30: 8 | G30: 7 | H30: 696 | I30: 880 | J30: 1 106 | K30: 1128 | L30: 1 154 | M30: 1161 | N30: 657 | O30: 697 | P30: 791 | Q30: 799 | R30: 805 | S30: 801 | T30: 35 | U30: 49 | V30: 57 | W30: 57 | X30: 58 | Y30: 58 | Z30: Архангельская область
A31: в том числе: | Z31: в том числе:
A32: Ненецкий автономный округ | B32: – | C32: – | D32: – | E32: – | F32: – | G32: – | H32: – | I32: 35 | J32: 35 | K32: 38 | L32: 39 | M32: 40 | N32: – | O32: 50 | P32: 87 | Q32: 93 | R32: 96 | S32: 92 | T32: – | U32: 1 | V32: 2 | W32: 2 | X32: 2 | Y32: 2 | Z32: Ненецкий автономный округ
A33: Архангельская область без автономного округа | B33: 13 | C33: 9 | D33: 8 | E33: 8 | F33: 8 | G33: 7 | H33: 696 | I33: 845 | J33: 1 071 | K33: 1090 | L33: 1 115 | M33: 1121 | N33: 657 | O33: 647 | P33: 704 | Q33: 706 | R33: 709 | S33: 709 | T33: 35 | U33: 48 | V33: 55 | W33: 55 | X33: 56 | Y33: 56 | Z33: Архангельская область
A34: Вологодская область | B34: 15 | C34: 13 | D34: 10 | E34: 9 | F34: 9 | G34: 11 | H34: 707 | I34: 806 | J34: 928 | K34: 908 | L34: 918 | M34: 924 | N34: 658 | O34: 648 | P34: 627 | Q34: 632 | R34: 635 | S34: 717 | T34: 39 | U34: 48 | V34: 62 | W34: 65 | X34: 59 | Y34: 62 | Z34: Вологодская область
A35: Калинингpадская область | B35: 5 | C35: 6 | D35: 7 | E35: 7 | F35: 7 | G35: 6 | H35: 1 015 | I35: 1 058 | J35: 1 113 | K35: 1125 | L35: 1 134 | M35: 1139 | N35: 399 | O35: 463 | P35: 463 | Q35: 468 | R35: 470 | S35: 474 | T35: 23 | U35: 42 | V35: 46 | W35: 51 | X35: 51 | Y35: 51 | Z35: Калининградская область
A36: Ленинградская область | B36: 25 | C36: 26 | D36: 22 | E36: 23 | F36: 21 | G36: 20 | H36: 827 | I36: 1 279 | J36: 1 828 | K36: 1882 | L36: 1 947 | M36: 2004 | N36: 638 | O36: 701 | P36: 815 | Q36: 847 | R36: 864 | S36: 882 | T36: 33 | U36: 64 | V36: 92 | W36: 93 | X36: 103 | Y36: 102 | Z36: Ленинградская область
A37: Мурманская область | B37: 7 | C37: 7 | D37: 7 | E37: 7 | F37: 7 | G37: 6 | H37: 212 | I37: 299 | J37: 351 | K37: 384 | L37: 395 | M37: 385 | N37: 537 | O37: 366 | P37: 388 | Q37: 406 | R37: 404 | S37: 411 | T37: 36 | U37: 33 | V37: 42 | W37: 45 | X37: 46 | Y37: 45 | Z37: Мурманская область
A38: Новгородская область | B38: 4 | C38: 3 | D38: 2 | E38: 2 | F38: 2 | G38: 2 | H38: 700 | I38: 786 | J38: 905 | K38: 923 | L38: 917 | M38: 920 | N38: 281 | O38: 300 | P38: 329 | Q38: 331 | R38: 332 | S38: 337 | T38: 28 | U38: 33 | V38: 35 | W38: 35 | X38: 35 | Y38: 35 | Z38: Новгородская область
A39: Псковская область | B39: 10 | C39: 9 | D39: 8 | E39: 7 | F39: 7 | G39: 7 | H39: 589 | I39: 551 | J39: 577 | K39: 627 | L39: 639 | M39: 657 | N39: 339 | O39: 341 | P39: 345 | Q39: 337 | R39: 339 | S39: 348 | T39: 12 | U39: 14 | V39: 17 | W39: 18 | X39: 19 | Y39: 19 | Z39: Псковская область
A40: г. Санкт-Петербург | B40: 13 | C40: 7 | D40: 8 | E40: 8 | F40: 8 | G40: 9 | H40: 2 270 | I40: 2 539 | J40: 2 937 | K40: 2886 | L40: 2 972 | M40: 3105 | N40: 1 573 | O40: 1 773 | P40: 1 936 | Q40: 1971 | R40: 2 010 | S40: 2045 | T40: 140 | U40: 284 | V40: 356 | W40: 380 | X40: 395 | Y40: 421 | Z40: г. Санкт-Петербург
A41: Южный | B41: 174 | C41: 231 | D41: 238 | E41: 233 | F41: 224 | G41: 217 | H41: 14 180 | I41: 17 459 | J41: 17 489 | K41: 17680 | L41: 17 937 | M41: 18019 | N41: 5 567 | O41: 6 840 | P41: 7 386 | Q41: 7452 | R41: 7576 | S41: 7726 | T41: 299 | U41: 411 | V41: 507 | W41: 507 | X41: 508 | Y41: 539 | Z41: Южный
A42: федеральный округ | Z42: федеральный округ
A43: Республика Адыгея | B43: 3 | C43: 3 | D43: 3 | E43: 3 | F43: 3 | G43: 3 | H43: 383 | I43: 603 | J43: 671 | K43: 674 | L43: 678 | M43: 676 | N43: 203 | O43: 185 | P43: 209 | Q43: 215 | R43: 223 | S43: 220 | T43: 7 | U43: 12 | V43: 12 | W43: 12 | X43: 12 | Y43: 12 | Z43: Республика Адыгея
A44: Республика Калмыкия | B44: 2 | C44: 2 | D44: 2 | E44: 2 | F44: 2 | G44: – | H44: 360 | I44: 288 | J44: 297 | K44: 302 | L44: 305 | M44: 250 | N44: 190 | O44: 185 | P44: 184 | Q44: 184 | R44: 185 | S44: 144 | T44: 2 | U44: 2 | V44: 3 | W44: 3 | X44: 4 | Y44: 1 | Z44: Республика Калмыкия
A45: Республика Крым | C45: 37 | D45: 34 | E45: 31 | F45: 30 | G45: 30 | I45: 1 577 | J45: 1 434 | K45: 1497 | L45: 1 546 | M45: 1516 | O45: 668 | P45: 756 | Q45: 761 | R45: 754 | S45: 772 | U45: 17 | V45: 27 | W45: 27 | X45: 27 | Y45: 28 | Z45: Республика Крым
A46: Краснодарский край | B46: 74 | C46: 80 | D46: 84 | E46: 85 | F46: 87 | G46: 82 | H46: 5 016 | I46: 5 414 | J46: 5 466 | K46: 5578 | L46: 5 672 | M46: 5717 | N46: 2 000 | O46: 2 150 | P46: 2 437 | Q46: 2477 | R46: 2 537 | S46: 2681 | T46: 131 | U46: 164 | V46: 201 | W46: 202 | X46: 201 | Y46: 228 | Z46: Краснодарский край
A47: Астраханская область | B47: 6 | C47: 8 | D47: 17 | E47: 17 | F47: 8 | G47: 8 | H47: 918 | I47: 916 | J47: 738 | K47: 746 | L47: 739 | M47: 746 | N47: 389 | O47: 476 | P47: 541 | Q47: 550 | R47: 577 | S47: 579 | T47: 10 | U47: 16 | V47: 26 | W47: 24 | X47: 23 | Y47: 23 | Z47: Астраханская область
A48: Волгоградская область | B48: 35 | C48: 41 | D48: 38 | E48: 35 | F48: 35 | G48: 35 | H48: 2 085 | I48: 2 503 | J48: 2 570 | K48: 2505 | L48: 2 518 | M48: 2535 | N48: 1 069 | O48: 1 149 | P48: 1 227 | Q48: 1225 | R48: 1 242 | S48: 1244 | T48: 42 | U48: 55 | V48: 64 | W48: 64 | X48: 65 | Y48: 66 | Z48: Волгоградская область
A49: Ростовская область | B49: 54 | C49: 54 | D49: 56 | E49: 56 | F49: 56 | G49: 56 | H49: 5 418 | I49: 5 844 | J49: 6 117 | K49: 6183 | L49: 6 269 | M49: 6363 | N49: 1 716 | O49: 1 765 | P49: 1 896 | Q49: 1911 | R49: 1 924 | S49: 1952 | T49: 107 | U49: 139 | V49: 164 | W49: 165 | X49: 166 | Y49: 171 | Z49: Ростовская область
A50: г. Севастополь | C50: 6 | D50: 4 | E50: 4 | F50: 3 | G50: 3 | I50: 314 | J50: 196 | K50: 195 | L50: 210 | M50: 216 | O50: 262 | P50: 136 | Q50: 129 | R50: 134 | S50: 134 | U50: 6 | V50: 10 | W50: 10 | X50: 10 | Y50: 10 | Z50: г. Севастополь
A51: Северо-Кавказский | B51: 89 | C51: 100 | D51: 107 | E51: 102 | F51: 92 | G51: 97 | H51: 6 807 | I51: 7 406 | J51: 8 174 | K51: 8406 | L51: 8 559 | M51: 9035 | N51: 3 410 | O51: 3 725 | P51: 4 245 | Q51: 4250 | R51: 4326 | S51: 4504 | T51: 101 | U51: 147 | V51: 205 | W51: 231 | X51: 229 | Y51: 251 | Z51: Северо-Кавказский
A52: федеральный округ | Z52: федеральный округ
A53: Республика Дагестан | B53: 12 | C53: 12 | D53: 13 | E53: 13 | F53: 12 | G53: 13 | H53: 1 844 | I53: 2 048 | J53: 2 127 | K53: 2112 | L53: 2 191 | M53: 2579 | N53: 760 | O53: 868 | P53: 1 035 | Q53: 1050 | R53: 1 065 | S53: 1094 | T53: 6 | U53: 21 | V53: 30 | W53: 32 | X53: 32 | Y53: 37 | Z53: Республика Дагестан
A54: Республика Ингушетия | B54: 4 | C54: 4 | D54: 4 | E54: 4 | F54: 4 | G54: 4 | H54: 138 | I54: 159 | J54: 189 | K54: 208 | L54: 209 | M54: 211 | N54: 91 | O54: 125 | P54: 165 | Q54: 163 | R54: 163 | S54: 170 | T54: – | U54: 5 | V54: 8 | W54: 8 | X54: 10 | Y54: 10 | Z54: Республика Ингушетия
A55: Кабардино-Балкарская Республика | B55: 12 | C55: 12 | D55: 12 | E55: 11 | F55: 11 | G55: 11 | H55: 686 | I55: 935 | J55: 983 | K55: 990 | L55: 994 | M55: 975 | N55: 454 | O55: 491 | P55: 511 | Q55: 514 | R55: 515 | S55: 518 | T55: 15 | U55: 15 | V55: 20 | W55: 16 | X55: 16 | Y55: 17 | Z55: Кабардино-Балкарская
A56: Карачаево-Черкесская Республика | B56: 4 | C56: 4 | D56: 4 | E56: 4 | F56: 4 | G56: 4 | H56: 264 | I56: 303 | J56: 311 | K56: 314 | L56: 315 | M56: 320 | N56: 210 | O56: 223 | P56: 272 | Q56: 275 | R56: 275 | S56: 279 | T56: 9 | U56: 10 | V56: 15 | W56: 15 | X56: 15 | Y56: 15 | Z56: Карачаево-Черкесская
A57: Республика Северная Осетия | B57: 13 | C57: 15 | D57: 15 | E57: 12 | F57: 12 | G57: 12 | H57: 482 | I57: 571 | J57: 535 | K57: 706 | L57: 734 | M57: 742 | N57: 386 | O57: 430 | P57: 453 | Q57: 430 | R57: 441 | S57: 444 | T57: 14 | U57: 18 | V57: 25 | W57: 26 | X57: 26 | Y57: 26 | Z57: Республика Северная
A58: Чеченская Республика | B58: 3 | C58: 13 | D58: 17 | E58: 17 | F58: 9 | G58: 13 | H58: 694 | I58: 695 | J58: 1 139 | K58: 1128 | L58: 1 167 | M58: 1291 | N58: 471 | O58: 489 | P58: 582 | Q58: 634 | R58: 671 | S58: 785 | T58: 1 | U58: 7 | V58: 13 | W58: 24 | X58: 14 | Y58: 26 | Z58: Чеченская Республика
A59: Ставропольский край | B59: 41 | C59: 40 | D59: 42 | E59: 41 | F59: 40 | G59: 40 | H59: 2 699 | I59: 2 695 | J59: 2 890 | K59: 2948 | L59: 2 949 | M59: 2917 | N59: 1 038 | O59: 1 099 | P59: 1 227 | Q59: 1184 | R59: 1 196 | S59: 1214 | T59: 56 | U59: 71 | V59: 94 | W59: 110 | X59: 116 | Y59: 120 | Z59: Ставропольский край
A60: Приволжский | B60: 414 | C60: 380 | D60: 364 | E60: 360 | F60: 360 | G60: 353 | H60: 30 955 | I60: 33 659 | J60: 33 152 | K60: 33575 | L60: 33639 | M60: 33749 | N60: 17 884 | O60: 16 339 | P60: 16 928 | Q60: 16949 | R60: 17027 | S60: 17047 | T60: 913 | U60: 1 160 | V60: 1 428 | W60: 1478 | X60: 1519 | Y60: 1533 | Z60: Приволжский
A61: федеральный округ | Z61: федеральный округ
A62: Республика Башкортостан | B62: 36 | C62: 30 | D62: 27 | E62: 27 | F62: 27 | G62: 25 | H62: 5 579 | I62: 6 345 | J62: 6 854 | K62: 6952 | L62: 7 064 | M62: 7023 | N62: 3 367 | O62: 2 507 | P62: 2 612 | Q62: 2635 | R62: 2675 | S62: 2687 | T62: 138 | U62: 190 | V62: 218 | W62: 215 | X62: 215 | Y62: 218 | Z62: Республика Башкортостан
A63: Республика Марий Эл | B63: 10 | C63: 6 | D63: 7 | E63: 7 | F63: 7 | G63: 8 | H63: 954 | I63: 1 003 | J63: 995 | K63: 1001 | L63: 1 000 | M63: 1002 | N63: 400 | O63: 387 | P63: 386 | Q63: 388 | R63: 391 | S63: 391 | T63: 30 | U63: 34 | V63: 37 | W63: 41 | X63: 42 | Y63: 42 | Z63: Республика Марий Эл
A64: Республика Мордовия | B64: 22 | C64: 7 | D64: 6 | E64: 6 | F64: 6 | G64: 6 | H64: 1 234 | I64: 1 268 | J64: 1 143 | K64: 1141 | L64: 1 137 | M64: 1110 | N64: 560 | O64: 547 | P64: 514 | Q64: 512 | R64: 511 | S64: 492 | T64: 23 | U64: 26 | V64: 30 | W64: 34 | X64: 35 | Y64: 36 | Z64: Республика Мордовия
A65: Республика Татарстан | B65: 40 | C65: 44 | D65: 45 | E65: 45 | F65: 46 | G65: 46 | H65: 4 661 | I65: 5 172 | J65: 3 592 | K65: 3623 | L65: 3 630 | M65: 3664 | N65: 1 935 | O65: 1 993 | P65: 2 012 | Q65: 2036 | R65: 2061 | S65: 2083 | T65: 143 | U65: 184 | V65: 249 | W65: 263 | X65: 281 | Y65: 293 | Z65: Республика Татарстан
A66: Удмуртская Республика | B66: 35 | C66: 31 | D66: 27 | E66: 27 | F66: 26 | G66: 25 | H66: 1 260 | I66: 1 369 | J66: 1 346 | K66: 1371 | L66: 1 319 | M66: 1310 | N66: 1 020 | O66: 809 | P66: 995 | Q66: 1009 | R66: 1021 | S66: 1018 | T66: 55 | U66: 70 | V66: 104 | W66: 106 | X66: 106 | Y66: 104 | Z66: Удмуртская Республика
A67: Чувашская Республика | B67: 11 | C67: 11 | D67: 11 | E67: 11 | F67: 12 | G67: 12 | H67: 2 210 | I67: 2 253 | J67: 2 418 | K67: 2442 | L67: 2 451 | M67: 2365 | N67: 714 | O67: 745 | P67: 775 | Q67: 775 | R67: 770 | S67: 762 | T67: 60 | U67: 70 | V67: 84 | W67: 86 | X67: 86 | Y67: 86 | Z67: Чувашская Республика
A68: Пермский край | B68: 34 | C68: 29 | D68: 25 | E68: 27 | F68: 26 | G68: 25 | H68: 2 204 | I68: 2 329 | J68: 2 484 | K68: 2622 | L68: 2 663 | M68: 2689 | N68: 1 528 | O68: 1 250 | P68: 1 227 | Q68: 1222 | R68: 1234 | S68: 1249 | T68: 68 | U68: 64 | V68: 74 | W68: 74 | X68: 76 | Y68: 76 | Z68: Пермский край
A69: Кировская область | B69: 28 | C69: 28 | D69: 26 | E69: 27 | F69: 25 | G69: 24 | H69: 1 003 | I69: 1 087 | J69: 1 028 | K69: 1071 | L69: 938 | M69: 951 | N69: 1 287 | O69: 849 | P69: 823 | Q69: 816 | R69: 838 | S69: 823 | T69: 24 | U69: 30 | V69: 32 | W69: 40 | X69: 41 | Y69: 42 | Z69: Кировская область
A70: Нижегородская область | B70: 60 | C70: 53 | D70: 47 | E70: 43 | F70: 43 | G70: 42 | H70: 2 530 | I70: 2 830 | J70: 2 928 | K70: 2979 | L70: 2 924 | M70: 2973 | N70: 1 497 | O70: 1 673 | P70: 1 879 | Q70: 1834 | R70: 1822 | S70: 1810 | T70: 105 | U70: 164 | V70: 223 | W70: 220 | X70: 230 | Y70: 228 | Z70: Нижегородская область
A71: Оренбургская область | B71: 28 | C71: 34 | D71: 34 | E71: 34 | F71: 36 | G71: 35 | H71: 2 490 | I71: 2 535 | J71: 2 621 | K71: 2639 | L71: 2 626 | M71: 2611 | N71: 1 173 | O71: 1 183 | P71: 1 195 | Q71: 1201 | R71: 1202 | S71: 1206 | T71: 60 | U71: 57 | V71: 59 | W71: 60 | X71: 60 | Y71: 63 | Z71: Оренбургская область
A72: Пензенская область | B72: 25 | C72: 26 | D72: 26 | E72: 26 | F72: 26 | G72: 25 | H72: 2 060 | I72: 2 235 | J72: 2 364 | K72: 2368 | L72: 2 366 | M72: 2399 | N72: 822 | O72: 879 | P72: 887 | Q72: 887 | R72: 885 | S72: 884 | T72: 65 | U72: 71 | V72: 72 | W72: 72 | X72: 71 | Y72: 72 | Z72: Пензенская область
A73: Самарская область | B73: 40 | C73: 41 | D73: 40 | E73: 39 | F73: 39 | G73: 39 | H73: 1 971 | I73: 2 313 | J73: 2 625 | K73: 2644 | L73: 2 659 | M73: 2692 | N73: 1 356 | O73: 1 451 | P73: 1 502 | Q73: 1526 | R73: 1529 | S73: 1536 | T73: 59 | U73: 95 | V73: 120 | W73: 132 | X73: 136 | Y73: 137 | Z73: Самарская область
A74: Саратовская область | B74: 27 | C74: 26 | D74: 26 | E74: 24 | F74: 24 | G74: 24 | H74: 1 614 | I74: 1 622 | J74: 1 718 | K74: 1731 | L74: 1 886 | M74: 1977 | N74: 1 457 | O74: 1 348 | P74: 1 381 | Q74: 1374 | R74: 1364 | S74: 1379 | T74: 50 | U74: 64 | V74: 80 | W74: 88 | X74: 91 | Y74: 85 | Z74: Саратовская область
A75: Ульяновская область | B75: 18 | C75: 14 | D75: 17 | E75: 17 | F75: 17 | G75: 17 | H75: 1 185 | I75: 1 298 | J75: 1 036 | K75: 991 | L75: 976 | M75: 983 | N75: 768 | O75: 718 | P75: 740 | Q75: 734 | R75: 724 | S75: 727 | T75: 33 | U75: 41 | V75: 46 | W75: 47 | X75: 49 | Y75: 51 | Z75: Ульяновская область
A76: Уральский | B76: 159 | C76: 204 | D76: 126 | E76: 130 | F76: 125 | G76: 124 | H76: 10 717 | I76: 11 845 | J76: 12 435 | K76: 12571 | L76: 12809 | M76: 13060 | N76: 7 314 | O76: 7 280 | P76: 7 534 | Q76: 7646 | R76: 7728 | S76: 7710 | T76: 571 | U76: 587 | V76: 622 | W76: 645 | X76: 663 | Y76: 679 | Z76: Уральский
A77: федеральный округ | Z77: федеральный округ
A78: Курганская область | B78: 21 | C78: 19 | D78: 19 | E78: 21 | F78: 21 | G78: 20 | H78: 1 042 | I78: 1 289 | J78: 1 391 | K78: 1360 | L78: 1 375 | M78: 1318 | N78: 746 | O78: 744 | P78: 747 | Q78: 759 | R78: 727 | S78: 713 | T78: 5 | U78: 10 | V78: 12 | W78: 13 | X78: 13 | Y78: 15 | Z78: Курганская область
A79: Свердловская область | B79: 58 | C79: 111 | D79: 46 | E79: 48 | F79: 44 | G79: 45 | H79: 4 062 | I79: 4 151 | J79: 4 052 | K79: 4046 | L79: 4 135 | M79: 4156 | N79: 2 308 | O79: 2 355 | P79: 2 642 | Q79: 2694 | R79: 2770 | S79: 2710 | T79: 262 | U79: 268 | V79: 247 | W79: 254 | X79: 265 | Y79: 275 | Z79: Свердловская область
A80: Тюменская область | B80: 24 | C80: 24 | D80: 24 | E80: 24 | F80: 23 | G80: 22 | H80: 2 313 | I80: 2 830 | J80: 3645 | K80: 3781 | L80: 3 888 | M80: 4119 | N80: 2 454 | O80: 2 417 | P80: 2 287 | Q80: 2323 | R80: 2346 | S80: 2371 | T80: 191 | U80: 226 | V80: 261 | W80: 275 | X80: 285 | Y80: 288 | Z80: Тюменская область
A81: в том числе: | Z81: в том числе:
A82: Ханты-Мансийский автономный округ | B82: 7 | C82: 6 | D82: 4 | E82: 4 | F82: 4 | G82: 4 | H82: 632 | I82: 881 | J82: 1 159 | K82: 1233 | L82: 1 277 | M82: 1413 | N82: 1 036 | O82: 915 | P82: 960 | Q82: 972 | R82: 998 | S82: 1002 | T82: 100 | U82: 117 | V82: 134 | W82: 141 | X82: 148 | Y82: 149 | Z82: Ханты-Мансийский
A83: Ямало-Ненецкий автономный округ | B83: – | C83: – | D83: – | E83: – | F83: – | G83: – | H83: 174 | I83: 237 | J83: 295 | K83: 320 | L83: 337 | M83: 342 | N83: 386 | O83: 418 | P83: 464 | Q83: 475 | R83: 475 | S83: 475 | T83: 32 | U83: 43 | V83: 63 | W83: 68 | X83: 69 | Y83: 71 | Z83: Ямало-Ненецкий автономный округ
A84: Тюменская область без автономных округов | B84: 17 | C84: 18 | D84: 20 | E84: 20 | F84: 19 | G84: 18 | H84: 1 507 | I84: 1 712 | J84: 2191 | K84: 2228 | L84: 2 274 | M84: 2364 | N84: 1 032 | O84: 1 084 | P84: 863 | Q84: 876 | R84: 873 | S84: 894 | T84: 59 | U84: 66 | V84: 64 | W84: 66 | X84: 68 | Y84: 68 | Z84: Тюменская область
A85: Челябинская область | B85: 56 | C85: 50 | D85: 37 | E85: 37 | F85: 37 | G85: 37 | H85: 3 300 | I85: 3 575 | J85: 3 347 | K85: 3384 | L85: 3 411 | M85: 3467 | N85: 1 806 | O85: 1 764 | P85: 1 858 | Q85: 1870 | R85: 1885 | S85: 1916 | T85: 113 | U85: 83 | V85: 102 | W85: 103 | X85: 100 | Y85: 101 | Z85: Челябинская область
A86: Сибирский | B86: 283 | C86: 276 | D86: 315 | E86: 231 | F86: 228 | G86: 231 | H86: 17 663 | I86: 18 986 | J86: 18 562 | K86: 19053 | L86: 18952 | M86: 19146 | N86: 11 070 | O86: 9 696 | P86: 9 474 | Q86: 9547 | R86: 9695 | S86: 9759 | T86: 508 | U86: 596 | V86: 640 | W86: 676 | X86: 697 | Y86: 713 | Z86: Сибирский
A87: федеральный округ | Z87: федеральный округ
A88: Республика Алтай | B88: 5 | C88: 7 | D88: 6 | E88: 7 | F88: 8 | G88: 8 | H88: 164 | I88: 175 | J88: 183 | K88: 185 | L88: 181 | M88: 199 | N88: 121 | O88: 131 | P88: 140 | Q88: 141 | R88: 147 | S88: 150 | T88: 1 | U88: 1 | V88: 2 | W88: 2 | X88: 2 | Y88: 2 | Z88: Республика Алтай
A89: Республика Тыва | B89: 13 | C89: 10 | D89: 11 | E89: 10 | F89: 10 | G89: 10 | H89: 365 | I89: 466 | J89: 481 | K89: 507 | L89: 433 | M89: 391 | N89: 199 | O89: 185 | P89: 214 | Q89: 236 | R89: 240 | S89: 259 | T89: 6 | U89: 3 | V89: 4 | W89: 4 | X89: 4 | Y89: 8 | Z89: Республика Тыва
A90: Республика Хакасия | B90: 18 | C90: 22 | D90: 21 | E90: 21 | F90: 21 | G90: 21 | H90: 480 | I90: 571 | J90: 591 | K90: 596 | L90: 588 | M90: 600 | N90: 257 | O90: 270 | P90: 272 | Q90: 274 | R90: 277 | S90: 282 | T90: 27 | U90: 28 | V90: 30 | W90: 30 | X90: 30 | Y90: 30 | Z90: Республика Хакасия
A91: Алтайский край | B91: 81 | C91: 77 | D91: 133 | E91: 48 | F91: 47 | G91: 49 | H91: 3 352 | I91: 2 919 | J91: 2 979 | K91: 3121 | L91: 3 150 | M91: 3162 | N91: 1 564 | O91: 1 584 | P91: 1 674 | Q91: 1686 | R91: 1714 | S91: 1723 | T91: 51 | U91: 64 | V91: 84 | W91: 95 | X91: 96 | Y91: 100 | Z91: Алтайский край
A92: Красноярский край | B92: 30 | C92: 25 | D92: 16 | E92: 16 | F92: 16 | G92: 16 | H92: 2 615 | I92: 2 799 | J92: 2 739 | K92: 2943 | L92: 2 953 | M92: 3024 | N92: 2 019 | O92: 2 134 | P92: 1 578 | Q92: 1569 | R92: 1587 | S92: 1581 | T92: 86 | U92: 104 | V92: 105 | W92: 120 | X92: 126 | Y92: 127 | Z92: Красноярский край
A93: Иркутская область | B93: 25 | C93: 25 | D93: 24 | E93: 24 | F93: 23 | G93: 24 | H93: 1 652 | I93: 1 913 | J93: 1 864 | K93: 1890 | L93: 1 906 | M93: 1937 | N93: 1 230 | O93: 1 320 | P93: 1 329 | Q93: 1340 | R93: 1367 | S93: 1387 | T93: 71 | U93: 81 | V93: 88 | W93: 92 | X93: 94 | Y93: 97 | Z93: Иркутская область
A94: Кемеровская область | B94: 29 | C94: 28 | D94: 27 | E94: 27 | F94: 27 | G94: 26 | H94: 3 829 | I94: 4 457 | J94: 4 121 | K94: 4117 | L94: 4 057 | M94: 4028 | N94: 2 740 | O94: 1 087 | P94: 1 126 | Q94: 1130 | R94: 1156 | S94: 1157 | T94: 111 | U94: 132 | V94: 124 | W94: 122 | X94: 132 | Y94: 132 | Z94: Кемеровская область
A95: Новосибирская область | B95: 24 | C95: 25 | D95: 23 | E95: 24 | F95: 23 | G95: 24 | H95: 2 097 | I95: 2 262 | J95: 2 089 | K95: 2183 | L95: 2 180 | M95: 2235 | N95: 1 232 | O95: 1 300 | P95: 1 357 | Q95: 1372 | R95: 1406 | S95: 1436 | T95: 66 | U95: 84 | V95: 98 | W95: 105 | X95: 107 | Y95: 110 | Z95: Новосибирская область
A96: Омская область | B96: 41 | C96: 40 | D96: 39 | E96: 39 | F96: 39 | G96: 39 | H96: 2 517 | I96: 2 694 | J96: 2 669 | K96: 2638 | L96: 2 626 | M96: 2665 | N96: 1 232 | O96: 1 216 | P96: 1 203 | Q96: 1206 | R96: 1204 | S96: 1186 | T96: 67 | U96: 71 | V96: 72 | W96: 73 | X96: 73 | Y96: 75 | Z96: Омская область
A97: Томская область | B97: 17 | C97: 17 | D97: 15 | E97: 15 | F97: 14 | G97: 14 | H97: 592 | I97: 730 | J97: 846 | K97: 873 | L97: 878 | M97: 905 | N97: 476 | O97: 469 | P97: 581 | Q97: 593 | R97: 597 | S97: 598 | T97: 22 | U97: 28 | V97: 33 | W97: 33 | X97: 33 | Y97: 32 | Z97: Томская область
A98: Дальневосточный | B98: 149 | C98: 130 | D98: 123 | E98: 128 | F98: 126 | G98: 128 | H98: 8 481 | I98: 8 937 | J98: 8 113 | K98: 8086 | L98: 8256 | M98: 8411 | N98: 5 001 | O98: 5 019 | P98: 5 030 | Q98: 5158 | R98: 5175 | S98: 5304 | T98: 220 | U98: 256 | V98: 297 | W98: 305 | X98: 304 | Y98: 302 | Z98: Дальневосточный
A99: федеральный округ | Z99: федеральный округ
A100: Республика Бурятия | B100: 17 | C100: 17 | D100: 17 | E100: 17 | F100: 17 | G100: 19 | H100: 827 | I100: 992 | J100: 1 057 | K100: 1081 | L100: 1 124 | M100: 1141 | N100: 466 | O100: 515 | P100: 537 | Q100: 550 | R100: 563 | S100: 576 | T100: 11 | U100: 15 | V100: 15 | W100: 16 | X100: 17 | Y100: 17 | Z100: Республика Бурятия
...

Sheet библиотеки
A1: 7.3. ОБЩЕДОСТУПНЫЕ БИБЛИОТЕКИ
B2: Библиотечный фонд на 1 000 человек населения1);2) | I2: Численность пользователей3),
B3: (на конец года; экземпляров) | I3: тыс. человек
B4: 2010 | C4: 2015 | D4: 2020 | E4: 2021 | F4: 2022 | G4: 2023 | H4: Место, | I4: 2010 | J4: 2015 | K4: 2020 | L4: 2021 | M4: 2022 | N4: 2023
H5: занимаемое
H6: в Российской
H7: Федерации
H8: 2023
A9: Российская Федерация | B9: 6 459 | C9: 5702 | D9: 5697 | E9: 5643 | F9: 5 591 | G9: 6066 | I9: 55 971 | J9: 51 992 | K9: 44 028 | L9: 49672 | M9: 51 691 | N9: 50831
A10: Центральный | B10: 6 934 | C10: 5941 | D10: 5819 | E10: 5762 | F10: 5 661 | G10: 7500 | H10: 2 | I10: 14 225 | J10: 12 448 | K10: 9 876 | L10: 11064 | M10: 11 025 | N10: 11088
A11: федеральный округ
A12: Белгородская область | B12: 6 973 | C12: 6597 | D12: 6047 | E12: 5994 | F12: 6 044 | G12: 6001 | H12: 47 | I12: 736 | J12: 750 | K12: 706 | L12: 789 | M12: 826 | N12: 746
A13: Брянская область | B13: 7 473 | C13: 7181 | D13: 7012 | E13: 7002 | F13: 6 870 | G13: 6792 | H13: 33 | I13: 617 | J13: 543 | K13: 464 | L13: 485 | M13: 484 | N13: 487
A14: Владимирская область | B14: 6 989 | C14: 6863 | D14: 6666 | E14: 6681 | F14: 6 621 | G14: 6592 | H14: 37 | I14: 580 | J14: 546 | K14: 439 | L14: 490 | M14: 495 | N14: 503
A15: Воронежская область | B15: 6 833 | C15: 4173 | D15: 6031 | E15: 6004 | F15: 5 967 | G15: 5899 | H15: 48 | I15: 884 | J15: 565 | K15: 694 | L15: 774 | M15: 865 | N15: 778
A16: Ивановская область | B16: 8 340 | C16: 6524 | D16: 8458 | E16: 8566 | F16: 8 560 | G16: 8511 | H16: 16 | I16: 475 | J16: 351 | K16: 289 | L16: 361 | M16: 383 | N16: 388
A17: Калужская область | B17: 7 775 | C17: 7027 | D17: 6808 | E17: 6702 | F17: 6 675 | G17: 6642 | H17: 34 | I17: 439 | J17: 418 | K17: 375 | L17: 400 | M17: 409 | N17: 572
A18: Костромская область | B18: 11 982 | C18: 10951 | D18: 10553 | E18: 10513 | F18: 10 356 | G18: 10260 | H18: 6 | I18: 286 | J18: 264 | K18: 252 | L18: 267 | M18: 284 | N18: 432
A19: Курская область | B19: 10 485 | C19: 8911 | D19: 8284 | E19: 8243 | F19: 8 195 | G19: 8072 | H19: 17 | I19: 593 | J19: 511 | K19: 443 | L19: 476 | M19: 492 | N19: 534
A20: Липецкая область | B20: 7 505 | C20: 6237 | D20: 6956 | E20: 6965 | F20: 6 908 | G20: 6891 | H20: 30 | I20: 562 | J20: 440 | K20: 414 | L20: 451 | M20: 456 | N20: 495
A21: Московская область | B21: 3 658 | C21: 2791 | D21: 2181 | E21: 2061 | F21: 1 928 | G21: 1831 | H21: 83 | I21: 1 791 | J21: 1 607 | K21: 1484 | L21: 1712 | M21: 1 756 | N21: 1485
A22: Орловская область | B22: 6 839 | C22: 6626 | D22: 6877 | E22: 6892 | F22: 6 841 | G22: 6796 | H22: 32 | I22: 328 | J22: 288 | K22: 244 | L22: 257 | M22: 259 | N22: 281
A23: Рязанская область | B23: 6 049 | C23: 5678 | D23: 5770 | E23: 5771 | F23: 5 806 | G23: 5850 | H23: 50 | I23: 507 | J23: 478 | K23: 434 | L23: 491 | M23: 492 | N23: 544
A24: Смоленская область | B24: 9 660 | C24: 9270 | D24: 9165 | E24: 9150 | F24: 9 132 | G24: 9143 | H24: 11 | I24: 595 | J24: 548 | K24: 431 | L24: 439 | M24: 442 | N24: 443
A25: Тамбовская область | B25: 9 119 | C25: 8838 | D25: 9180 | E25: 9284 | F25: 9 351 | G25: 9364 | H25: 8 | I25: 579 | J25: 506 | K25: 496 | L25: 515 | M25: 517 | N25: 506
A26: Тверская область | B26: 9 026 | C26: 7898 | D26: 7877 | E26: 7890 | F26: 7 894 | G26: 7809 | H26: 20 | I26: 595 | J26: 538 | K26: 432 | L26: 498 | M26: 511 | N26: 559
A27: Тульская область | B27: 6 143 | C27: 4556 | D27: 4601 | E27: 4492 | F27: 4 444 | G27: 4400 | H27: 70 | I27: 595 | J27: 534 | K27: 457 | L27: 521 | M27: 533 | N27: 452
A28: Ярославская область | B28: 7 502 | C28: 6732 | D28: 6786 | E28: 6735 | F28: 6 663 | G28: 6512 | H28: 39 | I28: 480 | J28: 555 | K28: 431 | L28: 519 | M28: 451 | N28: 451
A29: г. Москва | B29: 7 458 | C29: 6630 | D29: 6438 | E29: 6413 | F29: 6 266 | G29: 12054 | H29: 2 | I29: 3 583 | J29: 3 006 | K29: 1391 | L29: 1617 | M29: 1 371 | N29: 1431
A30: Северо-Западный | B30: 8 486 | C30: 7972 | D30: 7685 | E30: 7621 | F30: 7 435 | G30: 7555 | H30: 1 | I30: 5 029 | J30: 4 859 | K30: 4 180 | L30: 4619 | M30: 4 831 | N30: 4050
A31: федеральный округ
A32: Республика Карелия | B32: 8 320 | C32: 6749 | D32: 7510 | E32: 7550 | F32: 7 563 | G32: 7537 | H32: 22 | I32: 497 | J32: 218 | K32: 143 | L32: 147 | M32: 152 | N32: 167
A33: Республика Коми | B33: 8 141 | C33: 8219 | D33: 6411 | E33: 6405 | F33: 6 388 | G33: 6349 | H33: 41 | I33: 421 | J33: 391 | K33: 297 | L33: 334 | M33: 347 | N33: 346
A34: Архангельская область | B34: 7 527 | C34: 6876 | D34: 7577 | E34: 7609 | F34: 7 435 | G34: 7313 | I34: 446 | J34: 402 | K34: 356 | L34: 372 | M34: 392 | N34: 424
A35: в том числе:
A36: Ненецкий автономный округ | B36: 4 689 | C36: 7423 | D36: 9741 | E36: 9594 | F36: 9 421 | G36: 8902 | H36: 12 | I36: 14 | J36: 18 | K36: 23 | L36: 24 | M36: 24 | N36: 14
A37: Архангельская область без автономного округа | B37: 7 628 | C37: 6855 | D37: 7486 | E37: 7525 | F37: 7 349 | G37: 7243 | H37: 25 | I37: 432 | J37: 384 | K37: 332 | L37: 348 | M37: 368 | N37: 410
A38: Вологодская область | B38: 7 298 | C38: 6448 | D38: 6109 | E38: 6107 | F38: 6 115 | G38: 6058 | H38: 44 | I38: 543 | J38: 643 | K38: 639 | L38: 682 | M38: 738 | N38: 558
A39: Калинингpадская область | B39: 5 158 | C39: 4856 | D39: 4458 | E39: 4326 | F39: 4 284 | G39: 4206 | H39: 72 | I39: 371 | J39: 306 | K39: 257 | L39: 268 | M39: 283 | N39: 269
A40: Ленинградская область | B40: 3 212 | C40: 3944 | D40: 3412 | E40: 3329 | F40: 3 296 | G40: 3229 | H40: 78 | I40: 360 | J40: 454 | K40: 454 | L40: 538 | M40: 579 | N40: 413
A41: Мурманская область | B41: 10 157 | C41: 8168 | D41: 8308 | E41: 7876 | F41: 7 645 | G41: 7443 | H41: 24 | I41: 487 | J41: 466 | K41: 354 | L41: 417 | M41: 416 | N41: 402
A42: Новгородская область | B42: 8 940 | C42: 8251 | D42: 8060 | E42: 8024 | F42: 8 015 | G42: 7900 | H42: 18 | I42: 294 | J42: 373 | K42: 392 | L42: 341 | M42: 350 | N42: 332
A43: Псковская область | B43: 12 327 | C43: 10870 | D43: 10697 | E43: 10737 | F43: 10 766 | G43: 10512 | H43: 4 | I43: 376 | J43: 335 | K43: 266 | L43: 262 | M43: 263 | N43: 188
A44: г. Санкт-Петербург | B44: 10 737 | C44: 10182 | D44: 9878 | E44: 9833 | F44: 9 912 | G44: 9919 | H44: 7 | I44: 1 234 | J44: 1 272 | K44: 1024 | L44: 1257 | M44: 1 311 | N44: 951
A45: Южный | B45: 5 441 | C45: 4677 | D45: 4801 | E45: 4774 | F45: 4 748 | G45: 4696 | H45: 6 | I45: 5 366 | J45: 5 279 | K45: 4 543 | L45: 4829 | M45: 5 556 | N45: 5395
A46: федеральный округ
A47: Республика Адыгея | B47: 6 019 | C47: 5377 | D47: 4950 | E47: 4897 | F47: 4 957 | G47: 4936 | H47: 64 | I47: 202 | J47: 179 | K47: 160 | L47: 170 | M47: 172 | N47: 180
A48: Республика Калмыкия | B48: 10 157 | C48: 9697 | D48: 9425 | E48: 9303 | F48: 9 339 | G48: 9245 | H48: 9 | I48: 149 | J48: 139 | K48: 84 | L48: 88 | M48: 97 | N48: 156
A49: Республика Крым | C49: 5858 | D49: 5614 | E49: 5550 | F49: 5 432 | G49: 5223 | H49: 59 | J49: 573 | K49: 540 | L49: 537 | M49: 537 | N49: 496
A50: Краснодарский край | B50: 4 378 | C50: 3617 | D50: 3922 | E50: 3901 | F50: 3 892 | G50: 3875 | H50: 74 | I50: 1 896 | J50: 1 653 | K50: 1 311 | L50: 1323 | M50: 1 626 | N50: 1539
A51: Астраханская область | B51: 6 310 | C51: 6006 | D51: 6016 | E51: 6019 | F51: 6 065 | G51: 6029 | H51: 45 | I51: 413 | J51: 362 | K51: 300 | L51: 317 | M51: 328 | N51: 405
A52: Волгоградская область | B52: 5 667 | C52: 3735 | D52: 5074 | E52: 5120 | F52: 5 093 | G52: 5061 | H52: 61 | I52: 1 049 | J52: 640 | K52: 561 | L52: 688 | M52: 701 | N52: 739
A53: Ростовская область | B53: 6 019 | C53: 5434 | D53: 5096 | E53: 5080 | F53: 5 077 | G53: 5036 | H53: 62 | I53: 1 658 | J53: 1 618 | K53: 1 499 | L53: 1622 | M53: 1 995 | N53: 1730
A54: г. Севастополь | C54: 4205 | D54: 3139 | E54: 2905 | F54: 2 732 | G54: 2693 | H54: 80 | J54: 116 | K54: 88 | L54: 83 | M54: 100 | N54: 150
A55: Северо-Кавказский | B55: 3 895 | C55: 3712 | D55: 3640 | E55: 3590 | F55: 3 593 | G55: 3578 | H55: 8 | I55: 3 222 | J55: 3 013 | K55: 2 588 | L55: 3120 | M55: 3 251 | N55: 2934
A56: федеральный округ
A57: Республика Дагестан | B57: 2 826 | C57: 2658 | D57: 2534 | E57: 2374 | F57: 2 361 | G57: 2339 | H57: 82 | I57: 994 | J57: 895 | K57: 673 | L57: 770 | M57: 813 | N57: 927
A58: Республика Ингушетия | B58: 2 991 | C58: 1428 | D58: 1330 | E58: 1320 | F58: 1 319 | G58: 1306 | H58: 85 | I58: 192 | J58: 121 | K58: 82 | L58: 96 | M58: 105 | N58: 67
A59: Кабардино-Балкарская Республика | B59: 5 785 | C59: 5689 | D59: 5538 | E59: 5494 | F59: 5 522 | G59: 5527 | H59: 56 | I59: 258 | J59: 277 | K59: 198 | L59: 274 | M59: 285 | N59: 252
A60: Карачаево-Черкесская Республика | B60: 5 852 | C60: 5624 | D60: 5433 | E60: 5398 | F60: 5 399 | G60: 5343 | H60: 57 | I60: 225 | J60: 190 | K60: 118 | L60: 154 | M60: 157 | N60: 206
A61: Республика Северная Осетия | B61: 5 465 | C61: 5135 | D61: 4989 | E61: 4960 | F61: 4 959 | G61: 4936 | H61: 64 | I61: 200 | J61: 195 | K61: 144 | L61: 158 | M61: 161 | N61: 132
A62: Чеченская Республика | B62: 1 158 | C62: 1186 | D62: 1429 | E62: 1470 | F62: 1 489 | G62: 1483 | H62: 84 | I62: 212 | J62: 260 | K62: 410 | L62: 549 | M62: 597 | N62: 354
A63: Ставропольский край | B63: 5 080 | C63: 5163 | D63: 5187 | E63: 5221 | F63: 5 269 | G63: 5289 | H63: 58 | I63: 1 142 | J63: 1 074 | K63: 964 | L63: 1119 | M63: 1 133 | N63: 996
A64: Приволжский | B64: 6 844 | C64: 6245 | D64: 6242 | E64: 6198 | F64: 6 152 | G64: 6108 | H64: 4 | I64: 13 365 | J64: 12 222 | K64: 10 913 | L64: 11784 | M64: 12 001 | N64: 13566
A65: федеральный округ
A66: Республика Башкортостан | B66: 8 204 | C66: 7629 | D66: 7086 | E66: 6800 | F66: 6 578 | G66: 6490 | H66: 40 | I66: 2 033 | J66: 1 955 | K66: 1 789 | L66: 1798 | M66: 1 801 | N66: 2387
A67: Республика Марий Эл | B67: 8 235 | C67: 7727 | D67: 7223 | E67: 7148 | F67: 7 046 | G67: 6956 | H67: 28 | I67: 385 | J67: 373 | K67: 282 | L67: 323 | M67: 330 | N67: 317
A68: Республика Мордовия | B68: 8 494 | C68: 8234 | D68: 7812 | E68: 7808 | F68: 7 890 | G68: 7886 | H68: 19 | I68: 469 | J68: 436 | K68: 294 | L68: 394 | M68: 405 | N68: 407
A69: Республика Татарстан | B69: 6 318 | C69: 5996 | D69: 5837 | E69: 5844 | F69: 5 879 | G69: 5868 | H69: 49 | I69: 1 558 | J69: 1 460 | K69: 1 382 | L69: 1437 | M69: 1 450 | N69: 1781
A70: Удмуртская Республика | B70: 3 826 | C70: 3596 | D70: 3632 | E70: 3646 | F70: 3 670 | G70: 3663 | H70: 75 | I70: 617 | J70: 584 | K70: 526 | L70: 547 | M70: 561 | N70: 636
A71: Чувашская Республика | B71: 7 841 | C71: 7793 | D71: 7849 | E71: 7735 | F71: 7 623 | G71: 7548 | H71: 21 | I71: 692 | J71: 665 | K71: 455 | L71: 590 | M71: 594 | N71: 822
A72: Пермский край | B72: 5 093 | C72: 4238 | D72: 4713 | E72: 4722 | F72: 4 736 | G72: 4738 | H72: 67 | I72: 1 012 | J72: 872 | K72: 992 | L72: 1027 | M72: 1 054 | N72: 1133
A73: Кировская область | B73: 11 042 | C73: 10585 | D73: 10713 | E73: 10747 | F73: 10 596 | G73: 10482 | H73: 5 | I73: 732 | J73: 696 | K73: 627 | L73: 687 | M73: 685 | N73: 830
A74: Нижегородская область | B74: 6 724 | C74: 6258 | D74: 5972 | E74: 5933 | F74: 5 878 | G74: 5806 | H74: 51 | I74: 1 602 | J74: 1 384 | K74: 1 104 | L74: 1191 | M74: 1 236 | N74: 1349
A75: Оренбургская область | B75: 6 862 | C75: 5854 | D75: 6630 | E75: 6658 | F75: 6 615 | G75: 6593 | H75: 36 | I75: 870 | J75: 668 | K75: 585 | L75: 686 | M75: 706 | N75: 870
A76: Пензенская область | B76: 6 814 | C76: 6572 | D76: 6573 | E76: 6608 | F76: 6 635 | G76: 6641 | H76: 35 | I76: 671 | J76: 681 | K76: 624 | L76: 674 | M76: 706 | N76: 608
A77: Самарская область | B77: 6 016 | C77: 4794 | D77: 5319 | E77: 5300 | F77: 5 251 | G77: 5198 | H77: 60 | I77: 1 068 | J77: 919 | K77: 940 | L77: 1013 | M77: 1 037 | N77: 1020
A78: Саратовская область | B78: 6 408 | C78: 5824 | D78: 5653 | E78: 5705 | F78: 5 732 | G78: 5728 | H78: 52 | I78: 1 132 | J78: 1 057 | K78: 877 | L78: 945 | M78: 961 | N78: 916
A79: Ульяновская область | B79: 7 303 | C79: 6683 | D79: 6971 | E79: 6963 | F79: 6 986 | G79: 6888 | H79: 31 | I79: 526 | J79: 473 | K79: 439 | L79: 474 | M79: 475 | N79: 489
A80: Уральский | B80: 4 976 | C80: 4432 | D80: 4543 | E80: 4437 | F80: 4 379 | G80: 4332 | H80: 7 | I80: 4 235 | J80: 4 510 | K80: 3 736 | L80: 4541 | M80: 4 912 | N80: 4264
A81: федеральный округ
A82: Курганская область | B82: 9 984 | C82: 8033 | D82: 9789 | E82: 9788 | F82: 9 320 | G82: 9231 | H82: 10 | I82: 467 | J82: 351 | K82: 403 | L82: 425 | M82: 425 | N82: 457
A83: Свердловская область | B83: 4 302 | C83: 3836 | D83: 3727 | E83: 3708 | F83: 3 679 | G83: 3656 | H83: 76 | I83: 1 255 | J83: 1 443 | K83: 1 187 | L83: 1494 | M83: 1 631 | N83: 1262
A84: Тюменская область | B84: 4 029 | C84: 4041 | D84: 4380 | E84: 4117 | F84: 4 115 | G84: 4066 | I84: 1 088 | J84: 1 222 | K84: 1 069 | L84: 1340 | M84: 1 525 | N84: 1439
A85: в том числе:
A86: Ханты-Мансийский автономный округ | B86: 2 929 | C86: 2826 | D86: 3155 | E86: 3125 | F86: 3 109 | G86: 3069 | H86: 79 | I86: 440 | J86: 412 | K86: 292 | L86: 419 | M86: 460 | N86: 456
A87: Ямало-Ненецкий автономный округ | B87: 2 914 | C87: 3226 | D87: 3111 | E87: 2734 | F87: 2 702 | G87: 2658 | H87: 81 | I87: 141 | J87: 279 | K87: 357 | L87: 446 | M87: 557 | N87: 165
A88: Тюменская область без автономных округов | B88: 5 723 | C88: 5668 | D88: 6094 | E88: 5620 | F88: 5 647 | G88: 5600 | H88: 54 | I88: 507 | J88: 532 | K88: 419 | L88: 475 | M88: 507 | N88: 818
A89: Челябинская область | B89: 5 427 | C89: 4703 | D89: 4538 | E89: 4494 | F89: 4 444 | G89: 4393 | H89: 71 | I89: 1 424 | J89: 1 494 | K89: 1 077 | L89: 1283 | M89: 1 331 | N89: 1106
A90: Сибирский | B90: 6 404 | C90: 5343 | D90: 5606 | E90: 5553 | F90: 5 501 | G90: 5433 | H90: 5 | I90: 7 209 | J90: 6 569 | K90: 5 357 | L90: 6450 | M90: 6 705 | N90: 6527
A91: федеральный округ
A92: Республика Алтай | B92: 8 467 | C92: 7034 | D92: 7076 | E92: 7104 | F92: 6 929 | G92: 6933 | H92: 29 | I92: 125 | J92: 103 | K92: 90 | L92: 104 | M92: 118 | N92: 120
A93: Республика Тыва | B93: 9 343 | C93: 9420 | D93: 9010 | E93: 8838 | F93: 8 758 | G93: 8732 | H93: 15 | I93: 150 | J93: 157 | K93: 116 | L93: 142 | M93: 155 | N93: 139
A94: Республика Хакасия | B94: 6 523 | C94: 6132 | D94: 5878 | E94: 5861 | F94: 5 803 | G94: 5661 | H94: 53 | I94: 298 | J94: 235 | K94: 138 | L94: 203 | M94: 209 | N94: 185
A95: Алтайский край | B95: 6 162 | C95: 5499 | D95: 6047 | E95: 6065 | F95: 6 081 | G95: 6028 | H95: 46 | I95: 1 092 | J95: 872 | K95: 685 | L95: 792 | M95: 815 | N95: 930
A96: Красноярский край | B96: 7 461 | C96: 7222 | D96: 6773 | E96: 6606 | F96: 6 508 | G96: 6333 | H96: 42 | I96: 1 320 | J96: 1 334 | K96: 980 | L96: 1278 | M96: 1 366 | N96: 1329
A97: Иркутская область | B97: 5 503 | C97: 3208 | D97: 4786 | E97: 4699 | F97: 4 640 | G97: 4597 | H97: 69 | I97: 926 | J97: 642 | K97: 569 | L97: 735 | M97: 800 | N97: 727
A98: Кемеровская область | B98: 6 263 | C98: 5410 | D98: 5095 | E98: 5058 | F98: 5 015 | G98: 4961 | H98: 63 | I98: 1 072 | J98: 1 055 | K98: 852 | L98: 970 | M98: 990 | N98: 990
A99: Новосибирская область | B99: 5 675 | C99: 3522 | D99: 4120 | E99: 4062 | F99: 3 969 | G99: 3889 | H99: 73 | I99: 966 | J99: 1 055 | K99: 968 | L99: 1246 | M99: 1 197 | N99: 870
A100: Омская область | B100: 7 470 | C100: 6987 | D100: 6989 | E100: 7027 | F100: 7 014 | G100: 7002 | H100: 27 | I100: 929 | J100: 801 | K100: 709 | L100: 679 | M100: 724 | N100: 802
...

Sheet Газеты
A1: 7.4. ВЫПУСК ГАЗЕТ на 1 000 человек населения1);2)
A2: (разовый тираж; экземпляров)
B3: 2010 | C3: 2015 | D3: 2020 | E3: 2021 | F3: 2022 | G3: 2023 | H3: Место, занимаемое
H4: в Российской
H5: Федерации
H6: 2023
A7: Российская Федерация | B7: 1 446 | C7: 1382 | D7: 936 | E7: 817 | F7: 693 | G7: 579
A8: Центральный | B8: 2 414 | C8: 2014 | D8: 1730 | E8: 1513 | F8: 1 328 | G8: 1053 | H8: 2
A9: федеральный округ
A10: Белгородская область | B10: 1 005 | C10: 4404 | D10: 1896 | E10: 2041 | F10: 2 163 | G10: 852 | H10: 47
A11: Брянская область | B11: 388 | C11: 550 | D11: 359 | E11: 296 | F11: 254 | G11: 234 | H11: 33
A12: Владимирская область | B12: 249 | C12: 795 | D12: 605 | E12: 817 | F12: 562 | G12: 552 | H12: 37
A13: Воронежская область | B13: 1 217 | C13: 1067 | D13: 460 | E13: 753 | F13: 470 | G13: 480 | H13: 48
A14: Ивановская область | B14: 420 | C14: 619 | D14: 549 | E14: 426 | F14: 376 | G14: 321 | H14: 16
A15: Калужская область | B15: 769 | C15: 1020 | D15: 820 | E15: 843 | F15: 676 | G15: 622 | H15: 34
A16: Костромская область | B16: 5 252 | C16: 748 | D16: 772 | E16: 361 | F16: 431 | G16: 386 | H16: 6
A17: Курская область | B17: 1 368 | C17: 1411 | D17: 1004 | E17: 1028 | F17: 1 061 | G17: 394 | H17: 17
A18: Липецкая область | B18: 508 | C18: 792 | D18: 240 | E18: 173 | F18: 140 | G18: 132 | H18: 30
A19: Московская область | B19: 745 | C19: 792 | D19: 287 | E19: 291 | F19: 244 | G19: 198 | H19: 83
A20: Орловская область | B20: 564 | C20: 708 | D20: 359 | E20: 423 | F20: 268 | G20: 188 | H20: 32
A21: Рязанская область | B21: 517 | C21: 551 | D21: 381 | E21: 373 | F21: 608 | G21: 408 | H21: 50
A22: Смоленская область | B22: 3 523 | C22: 5578 | D22: 3796 | E22: 3846 | F22: 3 369 | G22: 2592 | H22: 11
A23: Тамбовская область | B23: 362 | C23: 785 | D23: 179 | E23: 180 | F23: 171 | G23: 154 | H23: 8
A24: Тверская область | B24: 504 | C24: 602 | D24: 300 | E24: 305 | F24: 329 | G24: 307 | H24: 20
A25: Тульская область | B25: 597 | C25: 574 | D25: 333 | E25: 449 | F25: 263 | G25: 191 | H25: 70
A26: Ярославская область | B26: 617 | C26: 1048 | D26: 556 | E26: 961 | F26: 651 | G26: 509 | H26: 39
A27: г. Москва | B27: 5 929 | C27: 3860 | D27: 4095 | E27: 3297 | F27: 2 894 | G27: 2383 | H27: 2
A28: Северо-Западный | B28: 2 651 | C28: 2335 | D28: 1344 | E28: 1179 | F28: 913 | G28: 895 | H28: 1
A29: федеральный округ
A30: Республика Карелия | B30: 1 011 | C30: 2396 | D30: 1151 | E30: 1715 | F30: 1 301 | G30: 564 | H30: 22
A31: Республика Коми | B31: 827 | C31: 1322 | D31: 1018 | E31: 1022 | F31: 807 | G31: 770 | H31: 41
A32: Архангельская область | B32: 2 159 | C32: 2303 | D32: 1759 | E32: 1393 | F32: 1 130 | G32: 1250
A33: в том числе:
A34: Ненецкий автономный округ | B34: 349 | C34: 533 | D34: 1171 | E34: 795 | F34: 493 | G34: 866 | H34: 12
A35: Архангельская область без автономного округа | B35: 2 223 | C35: 2372 | D35: 1784 | E35: 1418 | F35: 1 158 | G35: 1250 | H35: 25
A36: Вологодская область | B36: 1 074 | C36: 1178 | D36: 833 | E36: 1130 | F36: 724 | G36: 1061 | H36: 44
A37: Калинингpадская область | B37: 987 | C37: 1741 | D37: 506 | E37: 469 | F37: 350 | G37: 319 | H37: 72
A38: Ленинградская область | B38: 351 | C38: 445 | D38: 207 | E38: 260 | F38: 153 | G38: 130 | H38: 78
A39: Мурманская область | B39: 819 | C39: 781 | D39: 397 | E39: 729 | F39: 210 | G39: 837 | H39: 24
A40: Новгородская область | B40: 1 485 | C40: 1889 | D40: 1495 | E40: 1288 | F40: 1 079 | G40: 717 | H40: 18
A41: Псковская область | B41: 1 126 | C41: 1075 | D41: 770 | E41: 720 | F41: 376 | G41: 353 | H41: 4
A42: г. Санкт-Петербург | B42: 5 519 | C42: 3928 | D42: 2150 | E42: 1667 | F42: 1 388 | G42: 1313 | H42: 7
A43: Южный федеральный округ | B43: 1 050 | C43: 786 | D43: 381 | E43: 326 | F43: 288 | G43: 217 | H43: 6
A44: Республика Адыгея | B44: 363 | C44: 478 | D44: 218 | E44: 208 | F44: 189 | G44: 186 | H44: 64
A45: Республика Калмыкия | B45: 380 | C45: 305 | D45: 162 | E45: 235 | F45: 142 | G45: 142 | H45: 9
A46: Республика Крым | C46: 684 | D46: 247 | E46: 307 | F46: 182 | G46: 136 | H46: 59
A47: Краснодарский край | B47: 756 | C47: 711 | D47: 305 | E47: 313 | F47: 307 | G47: 230 | H47: 74
A48: Астраханская область | B48: 387 | C48: 525 | D48: 241 | E48: 251 | F48: 262 | G48: 104 | H48: 45
A49: Волгоградская область | B49: 850 | C49: 761 | D49: 397 | E49: 292 | F49: 193 | G49: 156 | H49: 61
A50: Ростовская область | B50: 1 803 | C50: 910 | D50: 525 | E50: 359 | F50: 365 | G50: 310 | H50: 62
A51: г. Севастополь | C51: 2437 | D51: 1012 | E51: 735 | F51: 498 | G51: 195 | H51: 80
A52: Северо-Кавказский | B52: 289 | C52: 280 | D52: 118 | E52: 136 | F52: 95 | G52: 86 | H52: 8
A53: федеральный округ
A54: Республика Дагестан | B54: 109 | C54: 141 | D54: 97 | E54: 85 | F54: 68 | G54: 56 | H54: 82
A55: Республика Ингушетия | B55: 46 | C55: 32 | D55: 14 | E55: 10 | F55: 14 | G55: 10 | H55: 85
A56: Кабардино-Балкарская Республика | B56: 242 | C56: 127 | D56: 57 | E56: 55 | F56: 43 | G56: 49 | H56: 56
A57: Карачаево-Черкесская Республика | B57: 231 | C57: 177 | D57: 124 | E57: 122 | F57: 103 | G57: 95 | H57: 57
A58: Республика Северная Осетия | B58: 314 | C58: 262 | D58: 111 | E58: 110 | F58: 111 | G58: 85 | H58: 64
A59: Чеченская Республика | B59: 50 | C59: 51 | D59: 39 | E59: 36 | F59: 30 | G59: 28 | H59: 84
A60: Ставропольский край | B60: 638 | C60: 647 | D60: 218 | E60: 299 | F60: 186 | G60: 173 | H60: 58
A61: Приволжский | B61: 1 196 | C61: 1519 | D61: 813 | E61: 682 | F61: 567 | G61: 515 | H61: 4
A62: федеральный округ
A63: Республика Башкортостан | B63: 1 163 | C63: 1172 | D63: 633 | E63: 489 | F63: 415 | G63: 278 | H63: 40
A64: Республика Марий Эл | B64: 2 277 | C64: 2831 | D64: 1914 | E64: 1890 | F64: 1 591 | G64: 1618 | H64: 28
A65: Республика Мордовия | B65: 513 | C65: 595 | D65: 267 | E65: 430 | F65: 227 | G65: 225 | H65: 19
A66: Республика Татарстан | B66: 1 421 | C66: 1556 | D66: 603 | E66: 429 | F66: 392 | G66: 349 | H66: 49
A67: Удмуртская Республика | B67: 786 | C67: 1444 | D67: 627 | E67: 561 | F67: 592 | G67: 520 | H67: 75
A68: Чувашская Республика | B68: 1 103 | C68: 1771 | D68: 762 | E68: 651 | F68: 486 | G68: 509 | H68: 21
A69: Пермский край | B69: 1 287 | C69: 1526 | D69: 793 | E69: 631 | F69: 396 | G69: 370 | H69: 67
A70: Кировская область | B70: 1 242 | C70: 1400 | D70: 862 | E70: 708 | F70: 621 | G70: 605 | H70: 5
A71: Нижегородская область | B71: 2 216 | C71: 3205 | D71: 1782 | E71: 1740 | F71: 1 412 | G71: 1201 | H71: 51
A72: Оренбургская область | B72: 510 | C72: 937 | D72: 372 | E72: 409 | F72: 345 | G72: 291 | H72: 36
A73: Пензенская область | B73: 1 025 | C73: 1090 | D73: 631 | E73: 627 | F73: 469 | G73: 455 | H73: 35
A74: Самарская область | B74: 737 | C74: 1126 | D74: 713 | E74: 506 | F74: 404 | G74: 285 | H74: 60
A75: Саратовская область | B75: 1 173 | C75: 1310 | D75: 604 | E75: 452 | F75: 420 | G75: 405 | H75: 52
A76: Ульяновская область | B76: 666 | C76: 803 | D76: 1171 | E76: 594 | F76: 660 | G76: 1143 | H76: 31
A77: Уральский | B77: 749 | C77: 965 | D77: 614 | E77: 514 | F77: 473 | G77: 331 | H77: 7
A78: федеральный округ
A79: Курганская область | B79: 479 | C79: 534 | D79: 356 | E79: 259 | F79: 171 | G79: 196 | H79: 10
A80: Свердловская область | B80: 630 | C80: 712 | D80: 521 | E80: 620 | F80: 471 | G80: 375 | H80: 76
A81: Тюменская область | B81: 797 | C81: 605 | D81: 414 | E81: 277 | F81: 249 | G81: 204
A82: в том числе:
A83: Ханты-Мансийский автономный округ | B83: 586 | C83: 332 | D83: 358 | E83: 333 | F83: 250 | G83: 222 | H83: 79
A84: Ямало-Ненецкий автономный округ | B84: 182 | C84: 151 | D84: 222 | E84: 197 | F84: 185 | G84: 172 | H84: 81
A85: Тюменская область без автономных округов | B85: 1 280 | C85: 1070 | D85: 536 | E85: 243 | F85: 269 | G85: 193 | H85: 54
A86: Челябинская область | B86: 920 | C86: 1753 | D86: 1008 | E86: 703 | F86: 796 | G86: 450 | H86: 71
A87: Сибирский | B87: 680 | C87: 752 | D87: 536 | E87: 459 | F87: 351 | G87: 307 | H87: 5
A88: федеральный округ
A89: Республика Алтай | B89: 146 | C89: 332 | D89: 435 | E89: 418 | F89: 408 | G89: 318 | H89: 29
A90: Республика Тыва | B90: 247 | C90: 222 | D90: 137 | E90: 91 | F90: 78 | G90: 73 | H90: 15
A91: Республика Хакасия | B91: 522 | C91: 557 | D91: 567 | E91: 623 | F91: 626 | G91: 788 | H91: 53
A92: Алтайский край | B92: 654 | C92: 674 | D92: 541 | E92: 542 | F92: 399 | G92: 294 | H92: 46
A93: Красноярский край | B93: 578 | C93: 711 | D93: 472 | E93: 400 | F93: 259 | G93: 314 | H93: 42
A94: Иркутская область | B94: 739 | C94: 747 | D94: 494 | E94: 640 | F94: 375 | G94: 354 | H94: 69
A95: Кемеровская область | B95: 496 | C95: 674 | D95: 390 | E95: 280 | F95: 182 | G95: 122 | H95: 63
A96: Новосибирская область | B96: 906 | C96: 887 | D96: 688 | E96: 478 | F96: 498 | G96: 363 | H96: 73
A97: Омская область | B97: 857 | C97: 840 | D97: 374 | E97: 361 | F97: 315 | G97: 266 | H97: 27
A98: Томская область | B98: 759 | C98: 1062 | D98: 587 | E98: 655 | F98: 505 | G98: 416 | H98: 68
A99: Дальневосточный | B99: 477 | C99: 678 | D99: 291 | E99: 273 | F99: 216 | G99: 201 | H99: 3
A100: федеральный округ
...

Sheet Лагеря
B1: ЧИСЛЕННОСТЬ ОТДОХНУВШИХ ДЕТЕЙ ЗА ЛЕТО В СУБЪЕКТЕ РОССИЙСКОЙ ФЕДЕРАЦИИ (тысяч человек)
B3: 2018 | C3: 20202) | D3: 2021 | E3: 2022 | F3: 2023
A4: Российская Федерация | B4: 4 274,4 | C4: 707.1 | D4: 3 597,5 | E4: 3 925,2 | F4: 4021.6
A5: Центральный | B5: 742 | C5: 168.2 | D5: 676.7 | E5: 720.6 | F5: 704.5
A6: федеральный округ
A7: Белгородская область | B7: 80.2 | C7: 16.2 | D7: 95.5 | E7: 89.6 | F7: 59.5
A8: Брянская область | B8: 36.4 | C8: 17.8 | D8: 32.8 | E8: 32.9 | F8: 33.1
A9: Владимирская область | B9: 46.7 | C9: – | D9: 40.7 | E9: 45.7 | F9: 46.3
A10: Воронежская область | B10: 61.2 | C10: 15.1 | D10: 47.8 | E10: 62.8 | F10: 69.4
A11: Ивановская область | B11: 21.2 | C11: 0.6 | D11: 23.2 | E11: 25.7 | F11: 25.4
A12: Калужская область | B12: 26 | C12: – | D12: 22.8 | E12: 25.8 | F12: 27
A13: Костромская область | B13: 21.6 | C13: 16.3 | D13: 20.9 | E13: 21.5 | F13: 25.1
A14: Курская область | B14: 34 | C14: 21.9 | D14: 38.2 | E14: 32.1 | F14: 29
A15: Липецкая область | B15: 46.3 | C15: 19.2 | D15: 38.1 | E15: 42.1 | F15: 43.8
A16: Московская область | B16: 103.9 | C16: 24 | D16: 86.5 | E16: 108 | F16: 104.8
A17: Орловская область | B17: 25.2 | C17: 0.3 | D17: 21.3 | E17: 22.1 | F17: 23.7
A18: Рязанская область | B18: 25.7 | C18: 8.5 | D18: 18.7 | E18: 21.5 | F18: 20.7
A19: Смоленская область | B19: 16.7 | C19: – | D19: 12.4 | E19: 13.9 | F19: 14
A20: Тамбовская область | B20: 56 | C20: 4.8 | D20: 48.4 | E20: 48.4 | F20: 48.9
A21: Тверская область | B21: 55.1 | C21: 7 | D21: 46.2 | E21: 50.7 | F21: 55.5
A22: Тульская область | B22: 42 | C22: – | D22: 36.1 | E22: 31.3 | F22: 31.3
A23: Ярославская область | B23: 40.3 | C23: 15.7 | D23: 39.5 | E23: 45.1 | F23: 46
A24: г. Москва | B24: 3.7 | C24: 0.9 | D24: 7.6 | E24: 1.3 | F24: 1.1
A25: Северо-Западный | B25: 278 | C25: 62.5 | D25: 234.6 | E25: 258.1 | F25: 275.7
A26: федеральный округ
A27: Республика Карелия | B27: 5.3 | C27: 1.2 | D27: 3.7 | E27: 4.5 | F27: 4.5
A28: Республика Коми | B28: 24.4 | C28: 10.1 | D28: 26.1 | E28: 27.1 | F28: 28.9
A29: Архангельская область | B29: 35.1 | C29: – | D29: 28.4 | E29: 29.9 | F29: 31.7
A30: в том числе:
A31: Ненецкий автономный округ | B31: 1.7 | C31: – | D31: 1.7 | E31: 1.8 | F31: 1.8
A32: Архангельская область без автономного округа | B32: 33.4 | C32: – | D32: 26.7 | E32: 28.1 | F32: 29.9
A33: Вологодская область | B33: 31 | C33: 6.2 | D33: 27.7 | E33: 31.7 | F33: 33.1
A34: Калинингpадская область | B34: 43.8 | C34: 30.5 | D34: 40.8 | E34: 44.3 | F34: 46.1
A35: Ленинградская область | B35: 69.9 | C35: 6.4 | D35: 48.4 | E35: 58.9 | F35: 60.5
A36: Мурманская область | B36: 7.4 | C36: 1.3 | D36: 6.8 | E36: 7.1 | F36: 7.3
A37: Новгородская область | B37: 19.3 | C37: 0.3 | D37: 15.7 | E37: 15.9 | F37: 16.4
A38: Псковская область | B38: 11.4 | C38: 4.2 | D38: 10.7 | E38: 11 | F38: 12
A39: г. Санкт-Петербург | B39: 30.5 | C39: 2.2 | D39: 26.3 | E39: 27.8 | F39: 35.2
A40: Южный | B40: 448.8 | C40: 101.8 | D40: 382 | E40: 392.7 | F40: 427.6
A41: федеральный округ
A42: Республика Адыгея | B42: 4.9 | C42: – | D42: 5 | E42: 4.9 | F42: 4.9
A43: Республика Калмыкия | B43: 6.4 | C43: – | D43: 7.2 | E43: 7.7 | F43: 7.2
A44: Республика Крым | B44: 58.8 | C44: 16.2 | D44: 45.5 | E44: 51.1 | F44: 67.7
A45: Краснодарский край | B45: 209.5 | C45: 23.5 | D45: 175.6 | E45: 181 | F45: 191.4
A46: Астраханская область | B46: 18 | C46: 2.7 | D46: 12.3 | E46: 13.9 | F46: 14
A47: Волгоградская область | B47: 83.2 | C47: 6 | D47: 75.2 | E47: 73.6 | F47: 78.3
A48: Ростовская область | B48: 60.4 | C48: 52 | D48: 56.3 | E48: 56.4 | F48: 59.3
A49: г. Севастополь | B49: 7.5 | C49: 1.4 | D49: 4.9 | E49: 4.1 | F49: 4.8
A50: Северо-Кавказский | B50: 149.8 | C50: 2.8 | D50: 126.8 | E50: 141.6 | F50: 142.9
A51: федеральный округ
A52: Республика Дагестан | B52: 12 | C52: – | D52: 19.2 | E52: 21 | F52: 26.4
A53: Республика Ингушетия | B53: 13.9 | C53: – | D53: 4.3 | E53: 4.9 | F53: 3.7
A54: Кабардино-Балкарская Республика | B54: 5.7 | C54: 0.3 | D54: 3.4 | E54: 2.7 | F54: 2.6
A55: Карачаево-Черкесская Республика | B55: 6.5 | C55: – | D55: 6.6 | E55: 6.3 | F55: 6.6
A56: Республика Северная Осетия | D56: 14.6 | E56: 15 | F56: 16.5
A57: Чеченская Республика | B57: 16.9 | C57: – | D57: 7.5 | E57: 12.1 | F57: 9
A58: Ставропольский край | B58: 13.5 | C58: – | D58: 71.2 | E58: 79.7 | F58: 78.1
A59: Приволжский | B59: 1 065,3 | C59: 113.8 | D59: 905.1 | E59: 964.1 | F59: 986.4
A60: федеральный округ
A61: Республика Башкортостан | B61: 195.8 | C61: – | D61: 138.4 | E61: 162.3 | F61: 174.7
A62: Республика Марий Эл | B62: 19.4 | C62: 1 | D62: 18.9 | E62: 21.9 | F62: 22.1
A63: Республика Мордовия | B63: 23.7 | C63: – | D63: 19.4 | E63: 24.9 | F63: 23.6
A64: Республика Татарстан | B64: 151.8 | C64: 36.6 | D64: 143.2 | E64: 148.6 | F64: 147
A65: Удмуртская Республика | B65: 58.3 | C65: 32.6 | D65: 50.6 | E65: 51.8 | F65: 55.9
A66: Чувашская Республика | B66: 33.8 | C66: – | D66: 28.7 | E66: 29.1 | F66: 31.9
A67: Пермский край | B67: 108.4 | C67: 7.9 | D67: 101.2 | E67: 99.7 | F67: 97.6
A68: Кировская область | B68: 51.3 | C68: 7.2 | D68: 47.7 | E68: 50.3 | F68: 51.1
A69: Нижегородская область | B69: 108 | C69: 1.9 | D69: 84.9 | E69: 96.2 | F69: 97.5
A70: Оренбургская область | B70: 80.5 | C70: 5.2 | D70: 66.8 | E70: 63.1 | F70: 61.5
A71: Пензенская область | B71: 41.6 | C71: 12.3 | D71: 36.5 | E71: 34.9 | F71: 38.5
A72: Самарская область | B72: 90.1 | C72: 9.1 | D72: 85.4 | E72: 95.7 | F72: 93.5
A73: Саратовская область | B73: 59 | C73: – | D73: 44.2 | E73: 51.3 | F73: 50.8
A74: Ульяновская область | B74: 43.7 | C74: – | D74: 39.3 | E74: 34.3 | F74: 40.7
A75: Уральский | B75: 518.4 | C75: 163.1 | D75: 471.1 | E75: 536 | F75: 514.2
A76: федеральный округ
A77: Свердловская область | B77: 183.4 | C77: 22.2 | D77: 161.2 | E77: 181.5 | F77: 36.6
A78: Тюменская область | B78: 153.8 | C78: 76.7 | D78: 145.4 | E78: 159.9 | F78: 180.2
A79: в том числе:
A80: Ханты-Мансийский автономный округ | B80: 50.7 | C80: – | D80: 46.1 | E80: 49.8 | F80: 49
A81: Ямало-Ненецкий автономный округ | B81: 8.8 | C81: – | D81: 6.6 | E81: 7.1 | F81: 7.3
A82: Тюменская область без автономных округов | B82: 94.3 | C82: 76.7 | D82: 92.7 | E82: 103 | F82: 100.9
A83: Челябинская область | B83: 140.1 | C83: 50.9 | D83: 139.4 | E83: 159 | F83: 140.1
A84: Сибирский | B84: 712 | C84: 37.5 | D84: 541.7 | E84: 607.4 | F84: 654.7
A85: федеральный округ
A86: Республика Алтай | B86: 9.6 | C86: – | D86: 9.8 | E86: 9.9 | F86: 10
A87: Республика Тыва | B87: 18.5 | C87: 0.7 | D87: 9.5 | E87: 15.7 | F87: 16.7
A88: Республика Хакасия | B88: 24.8 | C88: – | D88: 21.9 | E88: 17.5 | F88: 21.9
A89: Алтайский край | B89: 165.9 | C89: 0.6 | D89: 83.1 | E89: 89.8 | F89: 97.8
A90: Красноярский край | B90: 102.5 | C90: 3.7 | D90: 93.2 | E90: 101.1 | F90: 107.4
A91: Иркутская область | B91: 93.9 | C91: – | D91: 68.2 | E91: 78.9 | F91: 79.9
A92: Кемеровская область | B92: 81.2 | C92: 2.8 | D92: 73.8 | E92: 86.6 | F92: 103.9
A93: Новосибирская область | B93: 104.5 | C93: – | D93: 91.5 | E93: 101.1 | F93: 107.1
A94: Омская область | B94: 65.4 | C94: 29.7 | D94: 52.3 | E94: 64.6 | F94: 67.2
A95: Томская область | B95: 45.7 | C95: – | D95: 38.4 | E95: 42.3 | F95: 42.8
A96: Дальневосточный | B96: 360 | C96: 60 | D96: 259.6 | E96: 304.8 | F96: 315.7
A97: федеральный округ
A98: Республика Бурятия | B98: 37.3 | C98: – | D98: 26.8 | E98: 32.5 | F98: 31.8
A99: Республика Саха (Якутия) | B99: 45.8 | C99: 2.3 | D99: 20.7 | E99: 37.9 | F99: 34.5
A100: Забайкальский край | B100: 43.6 | C100: 13.8 | D100: 35.5 | E100: 41.6 | F100: 37.2
A101: Камчатский край | B101: 13.4 | C101: – | D101: 10 | E101: 12.8 | F101: 12.9
...

Sheet Культурные факторы (копия)
A1: Регион | B1: Численность зрителей театров, человек | C1: Стадионы с трибунами на 1500 мест и более | D1: Библиотечный фонд на 1 000 человек населения (на конец года; экземпляров) | E1: ВЫПУСК ГАЗЕТ на 1 000 человек населения | F1: Численность детей, отдохнувших в них за лето, тыс. человек | I1: Численность зрителей театров, человек | J1: Число посещений музеев, человек | K1: Стадионы с трибунами на 1500 мест и более | L1: Библиотечный фонд на 1 000 человек населения (на конец года; экземпляров) | M1: ВЫПУСК ГАЗЕТ на 1 000 человек населения | N1: Численность детей, отдохнувших в них за лето, тыс. человек
A2: Белгородская область | B2: =VLOOKUP($A2,'театры, музеи'!$A$2:$H$112,7,FALSE) -> 152 | C2: =VLOOKUP($A2,'спортивные сооружния'!A4:G112,7,FALSE) -> 23 | D2: =VLOOKUP($A2,библиотеки!A4:N116,11,FALSE) -> 706 | E2: =VLOOKUP($A2,Газеты!$A$3:$G$111,7,FALSE) -> 852 | F2: =VLOOKUP($A2,Лагеря!$A$3:$F$113,6,FALSE) -> 59.5
A3: Брянская область | B3: =VLOOKUP($A3,'театры, музеи'!$A$2:$H$112,7,FALSE) -> 173 | C3: =VLOOKUP($A3,'спортивные сооружния'!A5:G113,7,FALSE) -> 18 | D3: =VLOOKUP($A3,библиотеки!A5:H117,7,FALSE) -> 6792 | E3: =VLOOKUP($A3,Газеты!$A$3:$G$111,7,FALSE) -> 234 | F3: =VLOOKUP($A3,Лагеря!$A$3:$F$113,6,FALSE) -> 33.1
A4: Владимирская область | B4: =VLOOKUP($A4,'театры, музеи'!$A$2:$H$112,7,FALSE) -> 78 | C4: =VLOOKUP($A4,'спортивные сооружния'!A6:G114,7,FALSE) -> 28 | D4: =VLOOKUP($A4,библиотеки!A6:H118,7,FALSE) -> 6592 | E4: =VLOOKUP($A4,Газеты!$A$3:$G$111,7,FALSE) -> 552 | F4: =VLOOKUP($A4,Лагеря!$A$3:$F$113,6,FALSE) -> 46.3
A5: Воронежская область | B5: =VLOOKUP($A5,'театры, музеи'!$A$2:$H$112,7,FALSE) -> 228 | C5: =VLOOKUP($A5,'спортивные сооружния'!A7:G115,7,FALSE) -> 10 | D5: =VLOOKUP($A5,библиотеки!A7:H119,7,FALSE) -> 5899 | E5: =VLOOKUP($A5,Газеты!$A$3:$G$111,7,FALSE) -> 480 | F5: =VLOOKUP($A5,Лагеря!$A$3:$F$113,6,FALSE) -> 69.4
A6: Ивановская область | B6: =VLOOKUP($A6,'театры, музеи'!$A$2:$H$112,7,FALSE) -> 350 | C6: =VLOOKUP($A6,'спортивные сооружния'!A8:G116,7,FALSE) -> 14 | D6: =VLOOKUP($A6,библиотеки!A8:H120,7,FALSE) -> 8511 | E6: =VLOOKUP($A6,Газеты!$A$3:$G$111,7,FALSE) -> 321 | F6: =VLOOKUP($A6,Лагеря!$A$3:$F$113,6,FALSE) -> 25.4
A7: Калужская область | B7: =VLOOKUP($A7,'театры, музеи'!$A$2:$H$112,7,FALSE) -> 205 | C7: =VLOOKUP($A7,'спортивные сооружния'!A9:G117,7,FALSE) -> 15 | D7: =VLOOKUP($A7,библиотеки!A9:H121,7,FALSE) -> 6642 | E7: =VLOOKUP($A7,Газеты!$A$3:$G$111,7,FALSE) -> 622 | F7: =VLOOKUP($A7,Лагеря!$A$3:$F$113,6,FALSE) -> 27
A8: Костромская область | B8: =VLOOKUP($A8,'театры, музеи'!$A$2:$H$112,7,FALSE) -> 257 | C8: =VLOOKUP($A8,'спортивные сооружния'!A10:G118,7,FALSE) -> 6 | D8: =VLOOKUP($A8,библиотеки!A10:H122,7,FALSE) -> 10260 | E8: =VLOOKUP($A8,Газеты!$A$3:$G$111,7,FALSE) -> 386 | F8: =VLOOKUP($A8,Лагеря!$A$3:$F$113,6,FALSE) -> 25.1
A9: Курская область | B9: =VLOOKUP($A9,'театры, музеи'!$A$2:$H$112,7,FALSE) -> 234 | C9: =VLOOKUP($A9,'спортивные сооружния'!A11:G119,7,FALSE) -> 9 | D9: =VLOOKUP($A9,библиотеки!A11:H123,7,FALSE) -> 8072 | E9: =VLOOKUP($A9,Газеты!$A$3:$G$111,7,FALSE) -> 394 | F9: =VLOOKUP($A9,Лагеря!$A$3:$F$113,6,FALSE) -> 29
A10: Липецкая область | B10: =VLOOKUP($A10,'театры, музеи'!$A$2:$H$112,7,FALSE) -> 200 | C10: =VLOOKUP($A10,'спортивные сооружния'!A12:G120,7,FALSE) -> 22 | D10: =VLOOKUP($A10,библиотеки!A12:H124,7,FALSE) -> 6891 | E10: =VLOOKUP($A10,Газеты!$A$3:$G$111,7,FALSE) -> 132 | F10: =VLOOKUP($A10,Лагеря!$A$3:$F$113,6,FALSE) -> 43.8
A11: Московская область | B11: =VLOOKUP($A11,'театры, музеи'!$A$2:$H$112,7,FALSE) -> 104 | C11: =VLOOKUP($A11,'спортивные сооружния'!A13:G121,7,FALSE) -> 118 | D11: =VLOOKUP($A11,библиотеки!A13:H125,7,FALSE) -> 1831 | E11: =VLOOKUP($A11,Газеты!$A$3:$G$111,7,FALSE) -> 198 | F11: =VLOOKUP($A11,Лагеря!$A$3:$F$113,6,FALSE) -> 104.8
A12: Орловская область | B12: =VLOOKUP($A12,'театры, музеи'!$A$2:$H$112,7,FALSE) -> 327 | C12: =VLOOKUP($A12,'спортивные сооружния'!A14:G122,7,FALSE) -> 3 | D12: =VLOOKUP($A12,библиотеки!A14:H126,7,FALSE) -> 6796 | E12: =VLOOKUP($A12,Газеты!$A$3:$G$111,7,FALSE) -> 188 | F12: =VLOOKUP($A12,Лагеря!$A$3:$F$113,6,FALSE) -> 23.7
A13: Рязанская область | B13: =VLOOKUP($A13,'театры, музеи'!$A$2:$H$112,7,FALSE) -> 264 | C13: =VLOOKUP($A13,'спортивные сооружния'!A15:G123,7,FALSE) -> 13 | D13: =VLOOKUP($A13,библиотеки!A15:H127,7,FALSE) -> 5850 | E13: =VLOOKUP($A13,Газеты!$A$3:$G$111,7,FALSE) -> 408 | F13: =VLOOKUP($A13,Лагеря!$A$3:$F$113,6,FALSE) -> 20.7
A14: Смоленская область | B14: =VLOOKUP($A14,'театры, музеи'!$A$2:$H$112,7,FALSE) -> 169 | C14: =VLOOKUP($A14,'спортивные сооружния'!A16:G124,7,FALSE) -> 24 | D14: =VLOOKUP($A14,библиотеки!A16:H128,7,FALSE) -> 9143 | E14: =VLOOKUP($A14,Газеты!$A$3:$G$111,7,FALSE) -> 2592 | F14: =VLOOKUP($A14,Лагеря!$A$3:$F$113,6,FALSE) -> 14
... A32: Южный федеральный округ | B32: =VLOOKUP($A32,'театры, музеи'!$A$2:$H$112,7,FALSE) -> #N/A | C32: =VLOOKUP($A32,'спортивные сооружния'!A34:G142,7,FALSE) -> #N/A | D32: =VLOOKUP($A32,библиотеки!A34:H146,7,FALSE) -> #N/A | E32: =VLOOKUP($A32,Газеты!$A$3:$G$111,7,FALSE) -> 217 | F32: =VLOOKUP($A32,Лагеря!$A$3:$F$113,6,FALSE) -> #N/A
A33: Республика Адыгея | B33: =VLOOKUP($A33,'театры, музеи'!$A$2:$H$112,7,FALSE) -> 181 | C33: =VLOOKUP($A33,'спортивные сооружния'!A34:G143,7,FALSE) -> 3 | D33: =VLOOKUP($A33,библиотеки!A35:H147,7,FALSE) -> 4936 | E33: =VLOOKUP($A33,Газеты!$A$3:$G$111,7,FALSE) -> 186 | F33: =VLOOKUP($A33,Лагеря!$A$3:$F$113,6,FALSE) -> 4.9
A34: Республика Калмыкия | B34: =VLOOKUP($A34,'театры, музеи'!$A$2:$H$112,7,FALSE) -> 245 | C34: =VLOOKUP($A34,'спортивные сооружния'!A35:G144,7,FALSE) -> – | D34: =VLOOKUP($A34,библиотеки!A36:H148,7,FALSE) -> 9245 | E34: =VLOOKUP($A34,Газеты!$A$3:$G$111,7,FALSE) -> 142 | F34: =VLOOKUP($A34,Лагеря!$A$3:$F$113,6,FALSE) -> 7.2
A35: Республика Крым | B35: =VLOOKUP($A35,'театры, музеи'!$A$2:$H$112,7,FALSE) -> 228 | C35: =VLOOKUP($A35,'спортивные сооружния'!A36:G145,7,FALSE) -> 30 | D35: =VLOOKUP($A35,библиотеки!A37:H149,7,FALSE) -> 5223 | E35: =VLOOKUP($A35,Газеты!$A$3:$G$111,7,FALSE) -> 136 | F35: =VLOOKUP($A35,Лагеря!$A$3:$F$113,6,FALSE) -> 67.7
A36: Краснодарский край | B36: =VLOOKUP($A36,'театры, музеи'!$A$2:$H$112,7,FALSE) -> 103 | C36: =VLOOKUP($A36,'спортивные сооружния'!A37:G146,7,FALSE) -> 82 | D36: =VLOOKUP($A36,библиотеки!A38:H150,7,FALSE) -> 3875 | E36: =VLOOKUP($A36,Газеты!$A$3:$G$111,7,FALSE) -> 230 | F36: =VLOOKUP($A36,Лагеря!$A$3:$F$113,6,FALSE) -> 191.4
A37: Астраханская область | B37: =VLOOKUP($A37,'театры, музеи'!$A$2:$H$112,7,FALSE) -> 283 | C37: =VLOOKUP($A37,'спортивные сооружния'!A38:G147,7,FALSE) -> 8 | D37: =VLOOKUP($A37,библиотеки!A38:H151,7,FALSE) -> 6029 | E37: =VLOOKUP($A37,Газеты!$A$3:$G$111,7,FALSE) -> 104 | F37: =VLOOKUP($A37,Лагеря!$A$3:$F$113,6,FALSE) -> 14
A38: Волгоградская область | B38: =VLOOKUP($A38,'театры, музеи'!$A$2:$H$112,7,FALSE) -> 214 | C38: =VLOOKUP($A38,'спортивные сооружния'!A39:G148,7,FALSE) -> 35 | D38: =VLOOKUP($A38,библиотеки!A39:H152,7,FALSE) -> 5061 | E38: =VLOOKUP($A38,Газеты!$A$3:$G$111,7,FALSE) -> 156 | F38: =VLOOKUP($A38,Лагеря!$A$3:$F$113,6,FALSE) -> 78.3
A39: Ростовская область | B39: =VLOOKUP($A39,'театры, музеи'!$A$2:$H$112,7,FALSE) -> 204 | C39: =VLOOKUP($A39,'спортивные сооружния'!A40:G149,7,FALSE) -> 56 | D39: =VLOOKUP($A39,библиотеки!A40:H153,7,FALSE) -> 5036 | E39: =VLOOKUP($A39,Газеты!$A$3:$G$111,7,FALSE) -> 310 | F39: =VLOOKUP($A39,Лагеря!$A$3:$F$113,6,FALSE) -> 59.3
A40: г. Севастополь | B40: =VLOOKUP($A40,'театры, музеи'!$A$2:$H$112,7,FALSE) -> 358 | C40: =VLOOKUP($A40,'спортивные сооружния'!A41:G150,7,FALSE) -> 3 | D40: =VLOOKUP($A40,библиотеки!A41:H154,7,FALSE) -> 2693 | E40: =VLOOKUP($A40,Газеты!$A$3:$G$111,7,FALSE) -> 195 | F40: =VLOOKUP($A40,Лагеря!$A$3:$F$113,6,FALSE) -> 4.8
A41: Северо-Кавказский федеральный округ | B41: =VLOOKUP($A41,'театры, музеи'!$A$2:$H$112,7,FALSE) -> #N/A | C41: =VLOOKUP($A41,'спортивные сооружния'!A42:G151,7,FALSE) -> #N/A | D41: =VLOOKUP($A41,библиотеки!A42:H155,7,FALSE) -> #N/A | E41: =VLOOKUP($A41,Газеты!$A$3:$G$111,7,FALSE) -> #N/A | F41: =VLOOKUP($A41,Лагеря!$A$3:$F$113,6,FALSE) -> #N/A
A42: Республика Дагестан | B42: =VLOOKUP($A42,'театры, музеи'!$A$2:$H$112,7,FALSE) -> 122 | C42: =VLOOKUP($A42,'спортивные сооружния'!A43:G152,7,FALSE) -> 13 | D42: =VLOOKUP($A42,библиотеки!A43:H156,7,FALSE) -> 2339 | E42: =VLOOKUP($A42,Газеты!$A$3:$G$111,7,FALSE) -> 56 | F42: =VLOOKUP($A42,Лагеря!$A$3:$F$113,6,FALSE) -> 26.4
A43: Республика Ингушетия | B43: =VLOOKUP($A43,'театры, музеи'!$A$2:$H$112,7,FALSE) -> #N/A | C43: =VLOOKUP($A43,'спортивные сооружния'!A44:G153,7,FALSE) -> 4 | D43: =VLOOKUP($A43,библиотеки!A44:H157,7,FALSE) -> #N/A | E43: =VLOOKUP($A43,Газеты!$A$3:$G$111,7,FALSE) -> #N/A | F43: =VLOOKUP($A43,Лагеря!$A$3:$F$113,6,FALSE) -> 3.7
A44: Кабардино-Балкарская Республика | B44: =VLOOKUP($A44,'театры, музеи'!$A$2:$H$112,7,FALSE) -> 210 | C44: =VLOOKUP($A44,'спортивные сооружния'!A45:G154,7,FALSE) -> 11 | D44: =VLOOKUP($A44,библиотеки!A45:H158,7,FALSE) -> 5527 | E44: =VLOOKUP($A44,Газеты!$A$3:$G$111,7,FALSE) -> 49 | F44: =VLOOKUP($A44,Лагеря!$A$3:$F$113,6,FALSE) -> 2.6
A45: Карачаево-Черкесская Республика | B45: =VLOOKUP($A45,'театры, музеи'!$A$2:$H$112,7,FALSE) -> 99 | C45: =VLOOKUP($A45,'спортивные сооружния'!A46:G155,7,FALSE) -> 4 | D45: =VLOOKUP($A45,библиотеки!A46:H159,7,FALSE) -> 5343 | E45: =VLOOKUP($A45,Газеты!$A$3:$G$111,7,FALSE) -> 95 | F45: =VLOOKUP($A45,Лагеря!$A$3:$F$113,6,FALSE) -> 6.6
A46: Республика Северная Осетия | B46: =VLOOKUP($A46,'театры, музеи'!$A$2:$H$112,7,FALSE) -> 317 | C46: =VLOOKUP($A46,'спортивные сооружния'!A47:G156,7,FALSE) -> 12 | D46: =VLOOKUP($A46,библиотеки!A47:H160,7,FALSE) -> 4936 | E46: =VLOOKUP($A46,Газеты!$A$3:$G$111,7,FALSE) -> 85 | F46: =VLOOKUP($A46,Лагеря!$A$3:$F$113,6,FALSE) -> 16.5
A47: Чеченская Республика | B47: =VLOOKUP($A47,'театры, музеи'!$A$2:$H$112,7,FALSE) -> 154 | C47: =VLOOKUP($A47,'спортивные сооружния'!A48:G157,7,FALSE) -> 13 | D47: =VLOOKUP($A47,библиотеки!A48:H161,7,FALSE) -> 1483 | E47: =VLOOKUP($A47,Газеты!$A$3:$G$111,7,FALSE) -> 28 | F47: =VLOOKUP($A47,Лагеря!$A$3:$F$113,6,FALSE) -> 9
A48: Ставропольский край | B48: =VLOOKUP($A48,'театры, музеи'!$A$2:$H$112,7,FALSE) -> 117 | C48: =VLOOKUP($A48,'спортивные сооружния'!A49:G158,7,FALSE) -> 40 | D48: =VLOOKUP($A48,библиотеки!A49:H162,7,FALSE) -> 5289 | E48: =VLOOKUP($A48,Газеты!$A$3:$G$111,7,FALSE) -> 173 | F48: =VLOOKUP($A48,Лагеря!$A$3:$F$113,6,FALSE) -> 78.1
... A55: Чувашская Республика | B55: =VLOOKUP($A55,'театры, музеи'!$A$2:$H$112,7,FALSE) -> 388 | C55: =VLOOKUP($A55,'спортивные сооружния'!A56:G165,7,FALSE) -> 12 | D55: =VLOOKUP($A55,библиотеки!A56:H169,7,FALSE) -> 7548 | E55: =VLOOKUP($A55,Газеты!$A$3:$G$111,7,FALSE) -> 509 | F55: =VLOOKUP($A55,Лагеря!$A$3:$F$113,6,FALSE) -> 31.9
A56: Пермский край | B56: =VLOOKUP($A56,'театры, музеи'!$A$2:$H$112,7,FALSE) -> 349 | C56: =VLOOKUP($A56,'спортивные сооружния'!A56:G166,7,FALSE) -> 25 | D56: =VLOOKUP($A56,библиотеки!A57:H170,7,FALSE) -> 4738 | E56: =VLOOKUP($A56,Газеты!$A$3:$G$111,7,FALSE) -> 370 | F56: =VLOOKUP($A56,Лагеря!$A$3:$F$113,6,FALSE) -> 97.6
A57: Кировская область | B57: =VLOOKUP($A57,'театры, музеи'!$A$2:$H$112,7,FALSE) -> 236 | C57: =VLOOKUP($A57,'спортивные сооружния'!A57:G167,7,FALSE) -> 24 | D57: =VLOOKUP($A57,библиотеки!A58:H171,7,FALSE) -> 10482 | E57: =VLOOKUP($A57,Газеты!$A$3:$G$111,7,FALSE) -> 605 | F57: =VLOOKUP($A57,Лагеря!$A$3:$F$113,6,FALSE) -> 51.1
A58: Нижегородская область | B58: =VLOOKUP($A58,'театры, музеи'!$A$2:$H$112,7,FALSE) -> 317 | C58: =VLOOKUP($A58,'спортивные сооружния'!A57:G168,7,FALSE) -> 42 | D58: =VLOOKUP($A58,библиотеки!A59:H172,7,FALSE) -> 5806 | E58: =VLOOKUP($A58,Газеты!$A$3:$G$111,7,FALSE) -> 1201 | F58: =VLOOKUP($A58,Лагеря!$A$3:$F$113,6,FALSE) -> 97.5
A59: Оренбургская область | B59: =VLOOKUP($A59,'театры, музеи'!$A$2:$H$112,7,FALSE) -> 220 | C59: =VLOOKUP($A59,'спортивные сооружния'!A58:G169,7,FALSE) -> 35 | D59: =VLOOKUP($A59,библиотеки!A60:H173,7,FALSE) -> 6593 | E59: =VLOOKUP($A59,Газеты!$A$3:$G$111,7,FALSE) -> 291 | F59: =VLOOKUP($A59,Лагеря!$A$3:$F$113,6,FALSE) -> 61.5
A60: Пензенская область | B60: =VLOOKUP($A60,'театры, музеи'!$A$2:$H$112,7,FALSE) -> 175 | C60: =VLOOKUP($A60,'спортивные сооружния'!A58:G170,7,FALSE) -> 25 | D60: =VLOOKUP($A60,библиотеки!A61:H174,7,FALSE) -> 6641 | E60: =VLOOKUP($A60,Газеты!$A$3:$G$111,7,FALSE) -> 455 | F60: =VLOOKUP($A60,Лагеря!$A$3:$F$113,6,FALSE) -> 38.5
A61: Самарская область | B61: =VLOOKUP($A61,'театры, музеи'!$A$2:$H$112,7,FALSE) -> 277 | C61: =VLOOKUP($A61,'спортивные сооружния'!A59:G171,7,FALSE) -> 39 | D61: =VLOOKUP($A61,библиотеки!A62:H175,7,FALSE) -> 5198 | E61: =VLOOKUP($A61,Газеты!$A$3:$G$111,7,FALSE) -> 285 | F61: =VLOOKUP($A61,Лагеря!$A$3:$F$113,6,FALSE) -> 93.5
A62: Саратовская область | B62: =VLOOKUP($A62,'театры, музеи'!$A$2:$H$112,7,FALSE) -> 266 | C62: =VLOOKUP($A62,'спортивные сооружния'!A60:G172,7,FALSE) -> 24 | D62: =VLOOKUP($A62,библиотеки!A62:H176,7,FALSE) -> 5728 | E62: =VLOOKUP($A62,Газеты!$A$3:$G$111,7,FALSE) -> 405 | F62: =VLOOKUP($A62,Лагеря!$A$3:$F$113,6,FALSE) -> 50.8
A63: Ульяновская область | B63: =VLOOKUP($A63,'театры, музеи'!$A$2:$H$112,7,FALSE) -> 189 | C63: =VLOOKUP($A63,'спортивные сооружния'!A61:G173,7,FALSE) -> 17 | D63: =VLOOKUP($A63,библиотеки!A63:H177,7,FALSE) -> 6888 | E63: =VLOOKUP($A63,Газеты!$A$3:$G$111,7,FALSE) -> 1143 | F63: =VLOOKUP($A63,Лагеря!$A$3:$F$113,6,FALSE) -> 40.7
A64: Уральский федеральный округ | B64: =VLOOKUP($A64,'театры, музеи'!$A$2:$H$112,7,FALSE) -> #N/A | C64: =VLOOKUP($A64,'спортивные сооружния'!A62:G174,7,FALSE) -> #N/A | D64: =VLOOKUP($A64,библиотеки!A64:H178,7,FALSE) -> #N/A | E64: =VLOOKUP($A64,Газеты!$A$3:$G$111,7,FALSE) -> #N/A | F64: =VLOOKUP($A64,Лагеря!$A$3:$F$113,6,FALSE) -> #N/A
A65: Курганская область | B65: =VLOOKUP($A65,'театры, музеи'!$A$2:$H$112,7,FALSE) -> 171 | C65: =VLOOKUP($A65,'спортивные сооружния'!A63:G175,7,FALSE) -> 20 | D65: =VLOOKUP($A65,библиотеки!A65:H179,7,FALSE) -> 9231 | E65: =VLOOKUP($A65,Газеты!$A$3:$G$111,7,FALSE) -> 196 | F65: =VLOOKUP($A65,Лагеря!$A$3:$F$113,6,FALSE) -> #N/A
A66: Свердловская область | B66: =VLOOKUP($A66,'театры, музеи'!$A$2:$H$112,7,FALSE) -> 325 | C66: =VLOOKUP($A66,'спортивные сооружния'!A64:G176,7,FALSE) -> 45 | D66: =VLOOKUP($A66,библиотеки!A66:H180,7,FALSE) -> 3656 | E66: =VLOOKUP($A66,Газеты!$A$3:$G$111,7,FALSE) -> 375 | F66: =VLOOKUP($A66,Лагеря!$A$3:$F$113,6,FALSE) -> 36.6
A67: Тюменская область | B67: =VLOOKUP($A67,'театры, музеи'!$A$2:$H$112,7,FALSE) -> 200 | C67: =VLOOKUP($A67,'спортивные сооружния'!A65:G177,7,FALSE) -> 22 | D67: =VLOOKUP($A67,библиотеки!A67:H181,7,FALSE) -> 4066 | E67: =VLOOKUP($A67,Газеты!$A$3:$G$111,7,FALSE) -> 204 | F67: =VLOOKUP($A67,Лагеря!$A$3:$F$113,6,FALSE) -> 180.2
A68: Ханты-Мансийский автономный округ | B68: =VLOOKUP($A68,'театры, музеи'!$A$2:$H$112,7,FALSE) -> 162 | C68: =VLOOKUP($A68,'спортивные сооружния'!A66:G178,7,FALSE) -> 4 | D68: =VLOOKUP($A68,библиотеки!A68:H182,7,FALSE) -> 3069 | E68: =VLOOKUP($A68,Газеты!$A$3:$G$111,7,FALSE) -> 222 | F68: =VLOOKUP($A68,Лагеря!$A$3:$F$113,6,FALSE) -> 49
A69: Ямало-Ненецкий автономный округ | B69: =VLOOKUP($A69,'театры, музеи'!$A$2:$H$112,7,FALSE) -> – | C69: =VLOOKUP($A69,'спортивные сооружния'!A67:G179,7,FALSE) -> – | D69: =VLOOKUP($A69,библиотеки!A69:H183,7,FALSE) -> 2658 | E69: =VLOOKUP($A69,Газеты!$A$3:$G$111,7,FALSE) -> 172 | F69: =VLOOKUP($A69,Лагеря!$A$3:$F$113,6,FALSE) -> 7.3
A70: Тюменская область без автономных округов | B70: =VLOOKUP($A70,'театры, музеи'!$A$2:$H$112,7,FALSE) -> 304 | C70: =VLOOKUP($A70,'спортивные сооружния'!A68:G180,7,FALSE) -> 18 | D70: =VLOOKUP($A70,библиотеки!A70:H184,7,FALSE) -> 5600 | E70: =VLOOKUP($A70,Газеты!$A$3:$G$111,7,FALSE) -> 193 | F70: =VLOOKUP($A70,Лагеря!$A$3:$F$113,6,FALSE) -> 100.9
A71: Челябинская область | B71: =VLOOKUP($A71,'театры, музеи'!$A$2:$H$112,7,FALSE) -> 225 | C71: =VLOOKUP($A71,'спортивные сооружния'!A69:G181,7,FALSE) -> 37 | D71: =VLOOKUP($A71,библиотеки!A71:H185,7,FALSE) -> 4393 | E71: =VLOOKUP($A71,Газеты!$A$3:$G$111,7,FALSE) -> 450 | F71: =VLOOKUP($A71,Лагеря!$A$3:$F$113,6,FALSE) -> 140.1
A72: Сибирский федеральный округ | B72: =VLOOKUP($A72,'театры, музеи'!$A$2:$H$112,7,FALSE) -> #N/A | C72: =VLOOKUP($A72,'спортивные сооружния'!A70:G182,7,FALSE) -> #N/A | D72: =VLOOKUP($A72,библиотеки!A72:H186,7,FALSE) -> #N/A | E72: =VLOOKUP($A72,Газеты!$A$3:$G$111,7,FALSE) -> #N/A | F72: =VLOOKUP($A72,Лагеря!$A$3:$F$113,6,FALSE) -> #N/A
A73: Республика Алтай | B73: =VLOOKUP($A73,'театры, музеи'!$A$2:$H$112,7,FALSE) -> 135 | C73: =VLOOKUP($A73,'спортивные сооружния'!A71:G183,7,FALSE) -> 8 | D73: =VLOOKUP($A73,библиотеки!A73:H187,7,FALSE) -> 6933 | E73: =VLOOKUP($A73,Газеты!$A$3:$G$111,7,FALSE) -> 318 | F73: =VLOOKUP($A73,Лагеря!$A$3:$F$113,6,FALSE) -> 10
... A85: Республика Саха (Якутия) | B85: =VLOOKUP($A85,'театры, музеи'!$A$2:$H$112,7,FALSE) -> 242 | C85: =VLOOKUP($A85,'спортивные сооружния'!A83:G195,7,FALSE) -> 24 | D85: =VLOOKUP($A85,библиотеки!A85:H199,7,FALSE) -> 8837 | E85: =VLOOKUP($A85,Газеты!$A$3:$G$111,7,FALSE) -> 135 | F85: =VLOOKUP($A85,Лагеря!$A$3:$F$113,6,FALSE) -> 34.5
A86: Забайкальский край | B86: =VLOOKUP($A86,'театры, музеи'!$A$2:$H$112,7,FALSE) -> 276 | C86: =VLOOKUP($A86,'спортивные сооружния'!A83:G196,7,FALSE) -> 12 | D86: =VLOOKUP($A86,библиотеки!A86:H200,7,FALSE) -> 6518 | E86: =VLOOKUP($A86,Газеты!$A$3:$G$111,7,FALSE) -> 163 | F86: =VLOOKUP($A86,Лагеря!$A$3:$F$113,6,FALSE) -> 37.2
A87: Камчатский край | B87: =VLOOKUP($A87,'театры, музеи'!$A$2:$H$112,7,FALSE) -> 271 | C87: =VLOOKUP($A87,'спортивные сооружния'!A84:G197,7,FALSE) -> 1 | D87: =VLOOKUP($A87,библиотеки!A87:H201,7,FALSE) -> 7520 | E87: =VLOOKUP($A87,Газеты!$A$3:$G$111,7,FALSE) -> 487 | F87: =VLOOKUP($A87,Лагеря!$A$3:$F$113,6,FALSE) -> 12.9
A88: Приморский край | B88: =VLOOKUP($A88,'театры, музеи'!$A$2:$H$112,7,FALSE) -> 318 | C88: =VLOOKUP($A88,'спортивные сооружния'!A85:G198,7,FALSE) -> 24 | D88: =VLOOKUP($A88,библиотеки!A88:H202,7,FALSE) -> 3577 | E88: =VLOOKUP($A88,Газеты!$A$3:$G$111,7,FALSE) -> 150 | F88: =VLOOKUP($A88,Лагеря!$A$3:$F$113,6,FALSE) -> 92.2
A89: Хабаровский край | B89: =VLOOKUP($A89,'театры, музеи'!$A$2:$H$112,7,FALSE) -> 246 | C89: =VLOOKUP($A89,'спортивные сооружния'!A85:G199,7,FALSE) -> 16 | D89: =VLOOKUP($A89,библиотеки!A88:H203,7,FALSE) -> 7103 | E89: =VLOOKUP($A89,Газеты!$A$3:$G$111,7,FALSE) -> 193 | F89: =VLOOKUP($A89,Лагеря!$A$3:$F$113,6,FALSE) -> 40.3
A90: Амурская область | B90: =VLOOKUP($A90,'театры, музеи'!$A$2:$H$112,7,FALSE) -> 172 | C90: =VLOOKUP($A90,'спортивные сооружния'!A86:G200,7,FALSE) -> 26 | D90: =VLOOKUP($A90,библиотеки!A89:H204,7,FALSE) -> 4829 | E90: =VLOOKUP($A90,Газеты!$A$3:$G$111,7,FALSE) -> 208 | F90: =VLOOKUP($A90,Лагеря!$A$3:$F$113,6,FALSE) -> 19.7
A91: Магаданская область | B91: =VLOOKUP($A91,'театры, музеи'!$A$2:$H$112,7,FALSE) -> 350 | C91: =VLOOKUP($A91,'спортивные сооружния'!A87:G201,7,FALSE) -> 1 | D91: =VLOOKUP($A91,библиотеки!A89:H205,7,FALSE) -> 10550 | E91: =VLOOKUP($A91,Газеты!$A$3:$G$111,7,FALSE) -> 280 | F91: =VLOOKUP($A91,Лагеря!$A$3:$F$113,6,FALSE) -> 7.3
A92: Сахалинская область | B92: =VLOOKUP($A92,'театры, музеи'!$A$2:$H$112,7,FALSE) -> 246 | C92: =VLOOKUP($A92,'спортивные сооружния'!A88:G202,7,FALSE) -> 3 | D92: =VLOOKUP($A92,библиотеки!A90:H206,7,FALSE) -> 6276 | E92: =VLOOKUP($A92,Газеты!$A$3:$G$111,7,FALSE) -> 160 | F92: =VLOOKUP($A92,Лагеря!$A$3:$F$113,6,FALSE) -> 27.3
A93: Еврейская автономная область | B93: =VLOOKUP($A93,'театры, музеи'!$A$2:$H$112,7,FALSE) -> 138 | C93: =VLOOKUP($A93,'спортивные сооружния'!A89:G203,7,FALSE) -> 2 | D93: =VLOOKUP($A93,библиотеки!A91:H207,7,FALSE) -> 8834 | E93: =VLOOKUP($A93,Газеты!$A$3:$G$111,7,FALSE) -> 173 | F93: =VLOOKUP($A93,Лагеря!$A$3:$F$113,6,FALSE) -> 8.2
A94: Чукотский автономный округ | B94: =VLOOKUP($A94,'театры, музеи'!$A$2:$H$112,7,FALSE) -> – | C94: =VLOOKUP($A94,'спортивные сооружния'!A90:G204,7,FALSE) -> – | D94: =VLOOKUP($A94,библиотеки!A92:H208,7,FALSE) -> 14479 | E94: =VLOOKUP($A94,Газеты!$A$3:$G$111,7,FALSE) -> 108 | F94: =VLOOKUP($A94,Лагеря!$A$3:$F$113,6,FALSE) -> 4.2
B95: =VLOOKUP($A95,'театры, музеи'!$A$2:$H$112,7,FALSE) -> #N/A | C95: =VLOOKUP($A95,'спортивные сооружния'!A91:G205,7,FALSE) -> #N/A | D95: =VLOOKUP($A95,библиотеки!A93:H209,7,FALSE) -> #N/A | E95: =VLOOKUP($A95,Газеты!$A$3:$G$111,7,FALSE) -> #N/A | F95: =VLOOKUP($A95,Лагеря!$A$3:$F$113,6,FALSE) -> #N/A

Sheet Лист2
J10: Стадионы с трибунами на 1500 мест и более | K10: Численность зрителей театров, человек | L10: Число посещений музеев, человек | M10: Библиотечный фонд на 1 000 человек населения (на конец года; экземпляров) | N10: Численность детей, отдохнувших в них за лето, тыс. человек
J11: 1903 | K11: 217 | L11: 567 | M11: 6459 | N11: 4893.9
B12: Стадионы с трибунами на 1500 мест и более | C12: Численность зрителей театров, человек | D12: Число посещений музеев, человек | E12: Библиотечный фонд на 1 000 человек населения (на конец года; экземпляров) | F12: Численность детей, отдохнувших в них за лето, тыс. человек | J12: 1877 | K12: 260 | L12: 533 | M12: 5702 | N12: 4661.2
A13: Стадионы с трибунами на 1500 мест и более | B13: 1 | J13: 1770 | K13: 109 | L13: 400 | M13: 5697 | N13: 707.1
A14: Численность зрителей театров, человек | B14: -0.13419137 | C14: 1 | J14: 1676 | K14: 173 | L14: 648 | M14: 5643 | N14: 3597.5
A15: Число посещений музеев, человек | B15: -0.73726512 | C15: 0.72302448 | D15: 1 | J15: 1632 | K15: 245 | L15: 827 | M15: 5591 | N15: 3925.2
A16: Библиотечный фонд на 1 000 человек населения (на конец года; экземпляров) | B16: 0.43303942 | C16: 0.24468532 | D16: 0.045815782 | E16: 1 | J16: 1623 | K16: 284 | L16: 904 | M16: 6066 | N16: 4021.6
A17: Численность детей, отдохнувших в них за лето, тыс. человек | B17: 0.1978466 | C17: 0.81379144 | D17: 0.45922712 | E17: 0.42158126 | F17: 1
K25: 0.99749431
K26: 0.99499491
K27: 0.97497453
K28: 19.427255
K29: 6
J32: MS | K32: df | L32: SS | M32: F
J33: 18757.354 | K33: 4 | L33: 75029.415 | M33: 49.699117
J34: 377.41825 | K34: 1 | L34: 377.41825
K35: 5 | L35: 75406.833
J37: t-статистика | K37: Коэффициенты | L37: Стандартная ошибка | M37: P-Значение | N37: Верхние 95% | O37: Нижние 95,0% | P37: Верхние 95,0%
J38: 6.6338723 | K38: 1304.2548 | L38: 196.60536 | M38: 0.095247914 | N38: 3802.3628 | O38: -1193.8531 | P38: 3802.3628
J39: 0.4051535 | K39: 0.14607247 | L39: 0.36053612 | M39: 0.75493886 | N39: 4.7271183 | O39: -4.4349733 | P39: 4.7271183
J40: 0.55415539 | K40: 0.15855364 | L40: 0.28611766 | M40: 0.67785261 | N40: 3.7940231 | O40: -3.4769159 | P40: 3.7940231
J41: 3.4323529 | K41: 0.43672626 | L41: 0.12723816 | M41: 0.18048039 | N41: 2.0534403 | O41: -1.1799878 | P41: 2.0534403
J42: -1.4392028 | K42: -0.032277477 | L42: 0.02242733 | M42: 0.38658553 | N42: 0.25268877 | O42: -0.31724373 | P42: 0.25268877
K49: Предсказанное Стадионы с трибунами на 1500 мест и более | L49: Остатки
K50: 1903 | L50: -2.2737368e-13
K51: 1877 | L51: 2.2737368e-13
K52: 1770 | L52: -2.2737368e-13
K53: 1676 | L53: 0
K54: 1632 | L54: 0
K55: 1623 | L55: 0

Sheet занятые
A1: СРЕДНЕГОДОВАЯ ЧИСЛЕННОСТЬ ЗАНЯТЫХ
B2: 2010 | C2: 2015 | D2: 2020 | E2: 2021 | F2: 2022 | G2: 2023
A3: Российская Федерация | B3: 71493.1 | C3: 72424.9 | D3: 69550.3 | E3: 70817.9 | F3: 71216.9 | G3: 72911.8
A4: Центральный | B4: 20 782,3 | C4: 21 178,0 | D4: 20765.6 | E4: 20906.2 | F4: 20 843,9 | G4: 21537.9
A5: федеральный округ
A6: Белгородская область | B6: 749.8 | C6: 754 | D6: 751.9 | E6: 761.5 | F6: 771.2 | G6: 765.3
A7: Брянская область | B7: 580.9 | C7: 547.7 | D7: 498.5 | E7: 511.3 | F7: 506.7 | G7: 504.5
A8: Владимирская область | B8: 670.5 | C8: 664.4 | D8: 618.6 | E8: 616.1 | F8: 647.7 | G8: 639
A9: Воронежская область | B9: 1 158,9 | C9: 1 092,5 | D9: 1088.1 | E9: 1112.9 | F9: 1 135,4 | G9: 1151.6
A10: Ивановская область | B10: 467.8 | C10: 451.5 | D10: 428.6 | E10: 443.5 | F10: 448.5 | G10: 422.2
A11: Калужская область | B11: 516.8 | C11: 508 | D11: 495 | E11: 508.6 | F11: 503.1 | G11: 536.9
A12: Костромская область | B12: 327.5 | C12: 299.4 | D12: 271.9 | E12: 273.7 | F12: 277.9 | G12: 257.3
A13: Курская область | B13: 546.4 | C13: 520.3 | D13: 492.1 | E13: 509.3 | F13: 512.3 | G13: 502.6
A14: Липецкая область | B14: 594.5 | C14: 565.2 | D14: 556 | E14: 559.4 | F14: 549.5 | G14: 565.7
A15: Московская область | B15: 3 341,4 | C15: 3 366,9 | D15: 3422.7 | E15: 3488.4 | F15: 3 452,4 | G15: 3991.8
A16: Орловская область | B16: 342.5 | C16: 335.9 | D16: 293.8 | E16: 299.2 | F16: 297.8 | G16: 301.5
A17: Рязанская область | B17: 529 | C17: 504.8 | D17: 472.7 | E17: 487.2 | F17: 495.3 | G17: 499.7
A18: Смоленская область | B18: 484.6 | C18: 460.8 | D18: 407.2 | E18: 411.6 | F18: 423.4 | G18: 409.6
A19: Тамбовская область | B19: 504 | C19: 499.8 | D19: 449 | E19: 451.8 | F19: 462.3 | G19: 459.9
A20: Тверская область | B20: 676.8 | C20: 630.1 | D20: 576 | E20: 571.3 | F20: 575.2 | G20: 578.2
A21: Тульская область | B21: 770 | C21: 742.6 | D21: 705.1 | E21: 713 | F21: 716 | G21: 736.3
A22: Ярославская область | B22: 649.1 | C22: 635.9 | D22: 597.5 | E22: 611.5 | F22: 603 | G22: 598.7
A23: г. Москва | B23: 7 871,8 | C23: 8 598,0 | D23: 8641 | E23: 8576 | F23: 8 466,1 | G23: 8617.1
A24: Северо-Западный | B24: 7 286,3 | C24: 7 296,8 | D24: 6954.2 | E24: 7047.9 | F24: 7 138,5 | G24: 7221.2
A25: федеральный округ
A26: Республика Карелия | B26: 310.7 | C26: 284 | D26: 260.1 | E26: 264.9 | F26: 264.9 | G26: 235.1
A27: Республика Коми | B27: 472.6 | C27: 437.7 | D27: 383.2 | E27: 377.3 | F27: 368.9 | G27: 335.6
A28: Архангельская область | B28: 575.6 | C28: 558.4 | D28: 497.7 | E28: 509.1 | F28: 510.8 | G28: 460.5
A29: в том числе:
A30: Ненецкий автономный округ | B30: 32.5 | C30: 33.3 | D30: 31.2 | E30: 30 | F30: 31.4 | G30: 30.7
A31: Архангельская область без автономного округа | B31: 543.1 | C31: 525.1 | D31: 466.5 | E31: 479.1 | F31: 479.5 | G31: 429.8
A32: Вологодская область | B32: 608.6 | C32: 554.1 | D32: 517.6 | E32: 515.1 | F32: 517.7 | G32: 503.2
A33: Калининградская область | B33: 484.5 | C33: 478.2 | D33: 472.8 | E33: 489.7 | F33: 506.7 | G33: 519.3
A34: Ленинградская область | B34: 837.2 | C34: 842.1 | D34: 782.6 | E34: 800.7 | F34: 871.1 | G34: 901.5
A35: Мурманская область | B35: 417.9 | C35: 383.2 | D35: 348.3 | E35: 356.5 | F35: 340.9 | G35: 313.2
A36: Новгородская область | B36: 315 | C36: 298.7 | D36: 258.8 | E36: 264.5 | F36: 268.1 | G36: 273.8
A37: Псковская область | B37: 310.5 | C37: 295.6 | D37: 272 | E37: 274.5 | F37: 275.9 | G37: 285.2
A38: г. Санкт-Петербург | B38: 2 953,7 | C38: 3 164,8 | D38: 3161.1 | E38: 3195.6 | F38: 3 213,6 | G38: 3393.9
A39: Южный | B39: 6 478,6 | C39: 7 442,5 | D39: 7328.9 | E39: 7563.7 | F39: 7 695,5 | G39: 8057.6
A40: федеральный округ
A41: Республика Адыгея | B41: 156.5 | C41: 155.1 | D41: 152.2 | E41: 152.4 | F41: 152.5 | G41: 156.7
A42: Республика Калмыкия | B42: 115.1 | C42: 111.8 | D42: 104 | E42: 105.1 | F42: 112 | G42: 111.9
A43: Республика Крым | C43: 852.7 | D43: 843 | E43: 850.2 | F43: 839 | G43: 890.6
A44: Краснодарский край | B44: 2 512,5 | C44: 2 546,1 | D44: 2609.1 | E44: 2703.1 | F44: 2 739,0 | G44: 2908
A45: Астраханская область | B45: 493.6 | C45: 479.8 | D45: 444.2 | E45: 457.8 | F45: 472.9 | G45: 466.8
A46: Волгоградская область | B46: 1 243,0 | C46: 1 176,0 | D46: 1072.6 | E46: 1105.7 | F46: 1 129,8 | G46: 1180.1
A47: Ростовская область | B47: 1 957,9 | C47: 1 948,8 | D47: 1909.4 | E47: 1984.6 | F47: 2 017,2 | G47: 2092.1
A48: г. Севастополь | C48: 172.2 | D48: 194.3 | E48: 205 | F48: 233 | G48: 251.4
A49: Северо-Кавказский | B49: 3 650,4 | C49: 3 745,8 | D49: 3739.1 | E49: 3842 | F49: 4 044,1 | G49: 4190.5
A50: федеральный округ
A51: Республика Дагестан | B51: 1 028,1 | C51: 1 063,4 | D51: 1022.9 | E51: 1060 | F51: 1 153,0 | G51: 1230.2
A52: Республика Ингушетия | B52: 134.1 | C52: 153.2 | D52: 182.2 | E52: 184.1 | F52: 199.8 | G52: 198.6
A53: Кабардино-Балкарская Республика | B53: 362.6 | C53: 357 | D53: 360.6 | E53: 363.7 | F53: 377.5 | G53: 386
A54: Карачаево-Черкесская Республика | B54: 179.1 | C54: 173.3 | D54: 161.8 | E54: 168.8 | F54: 179 | G54: 188
A55: Республика Северная Осетия | B55: 301.7 | C55: 294.7 | D55: 248.7 | E55: 255.4 | F55: 266.7 | G55: 274.2
A56: Чеченская Республика | B56: 408.5 | C56: 488.7 | D56: 515.1 | E56: 538.8 | F56: 573.9 | G56: 569.2
A57: Ставропольский край | B57: 1 236,4 | C57: 1 215,5 | D57: 1247.9 | E57: 1271.1 | F57: 1 294,1 | G57: 1344.4
A58: Приволжский | B58: 14 579,5 | C58: 14 221,0 | D58: 13114.1 | E58: 13436.9 | F58: 13 496,4 | G58: 13695.9
A59: федеральный округ
A60: Республика Башкортостан | B60: 1 825,1 | C60: 1 778,8 | D60: 1588.9 | E60: 1650.9 | F60: 1 684,9 | G60: 1730
A61: Республика Марий Эл | B61: 319.4 | C61: 307.5 | D61: 264.5 | E61: 270.9 | F61: 268.3 | G61: 280.7
A62: Республика Мордовия | B62: 426.3 | C62: 393.6 | D62: 365.4 | E62: 374 | F62: 386.1 | G62: 369.3
A63: Республика Татарстан | B63: 1 949,3 | C63: 1 950,3 | D63: 1938.8 | E63: 1985.8 | F63: 1 993,6 | G63: 2036.5
A64: Удмуртская Республика | B64: 761.7 | C64: 741.6 | D64: 678.4 | E64: 693.7 | F64: 685.4 | G64: 681.5
A65: Чувашская Республика | B65: 597.9 | C65: 564.3 | D65: 478.9 | E65: 494.1 | F65: 495 | G65: 508.7
A66: Пермский край | B66: 1 248,5 | C66: 1 201,0 | D66: 1108.5 | E66: 1153.5 | F66: 1 142,5 | G66: 1145.6
A67: Кировская область | B67: 624.9 | C67: 596.6 | D67: 552.2 | E67: 557.4 | F67: 555.5 | G67: 530
A68: Нижегородская область | B68: 1 728,1 | C68: 1 653,6 | D68: 1603.6 | E68: 1637.9 | F68: 1 639,9 | G68: 1660.5
A69: Оренбургская область | B69: 960.4 | C69: 930.2 | D69: 832.3 | E69: 853 | F69: 845.9 | G69: 848.3
A70: Пензенская область | B70: 638.9 | C70: 632.6 | D70: 555.9 | E70: 579.3 | F70: 561.6 | G70: 580.5
A71: Самарская область | B71: 1 740,5 | C71: 1 739,1 | D71: 1597.4 | E71: 1620.9 | F71: 1 616,3 | G71: 1646.3
A72: Саратовская область | B72: 1 155,7 | C72: 1 149,4 | D72: 1009.4 | E72: 1024.4 | F72: 1 059,3 | G72: 1120.4
A73: Ульяновская область | B73: 602.6 | C73: 582.3 | D73: 539.8 | E73: 541.1 | F73: 562.1 | G73: 557.7
A74: Уральский | B74: 6 458,3 | C74: 6 425,9 | D74: 6177.7 | E74: 6310.9 | F74: 6 256,7 | G74: 6448.6
A75: федеральный округ
A76: Курганская область | B76: 383.1 | C76: 359.8 | D76: 309.8 | E76: 302.8 | F76: 306.1 | G76: 308.6
A77: Свердловская область | B77: 2 174,7 | C77: 2 137,9 | D77: 1954.9 | E77: 2024 | F77: 2 017,4 | G77: 2095.2
A78: Тюменская область | B78: 2 170,0 | C78: 2 209,8 | D78: 2196 | E78: 2237.5 | F78: 2 212,3 | G78: 2258.6
A79: в том числе:
A80: Ханты-Мансийский автономный округ | B80: 1 023,5 | C80: 1 037,4 | D80: 1066.1 | E80: 1086.9 | F80: 1 070,6 | G80: 1101.9
A81: Ямало-Ненецкий автономный округ | B81: 387.7 | C81: 393.8 | D81: 417.2 | E81: 424.1 | F81: 416.2 | G81: 409.2
A82: Тюменская область без автономных округов | B82: 758.8 | C82: 778.6 | D82: 712.7 | E82: 726.5 | F82: 725.5 | G82: 747.4
A83: Челябинская область | B83: 1 730,5 | C83: 1 718,3 | D83: 1717 | E83: 1746.6 | F83: 1 720,9 | G83: 1786.3
A84: Сибирский | B84: 8 121,2 | C84: 8 061,3 | D84: 7572 | E84: 7764.8 | F84: 7 815,8 | G84: 7795.2
A85: федеральный округ
A86: Республика Алтай | B86: 88 | C86: 85.6 | D86: 80.6 | E86: 82.4 | F86: 83 | G86: 80.5
A87: Республика Тыва | B87: 101.7 | C87: 99 | D87: 101.9 | E87: 103.7 | F87: 111.2 | G87: 112.3
A88: Республика Хакасия | B88: 253.2 | C88: 237.2 | D88: 207.6 | E88: 228.4 | F88: 233.3 | G88: 248.2
A89: Алтайский край | B89: 1 093,4 | C89: 1 055,9 | D89: 976 | E89: 1006.3 | F89: 1 077,2 | G89: 1057.8
A90: Красноярский край | B90: 1 437,9 | C90: 1 424,4 | D90: 1363.9 | E90: 1408.7 | F90: 1 380,8 | G90: 1409.4
A91: Иркутская область | B91: 1 155,1 | C91: 1 158,8 | D91: 1051.5 | E91: 1073.1 | F91: 1 098,4 | G91: 1093.7
A92: Кемеровская область | B92: 1 284,3 | C92: 1 229,1 | D92: 1146.5 | E92: 1156.6 | F92: 1 157,8 | G92: 1148.1
A93: Новосибирская область | B93: 1 287,9 | C93: 1 363,5 | D93: 1288.2 | E93: 1328.3 | F93: 1 307,5 | G93: 1314.9
A94: Омская область | B94: 938.5 | C94: 932.7 | D94: 876.6 | E94: 877.8 | F94: 868.1 | G94: 835.8
A95: Томская область | B95: 481.2 | C95: 475.2 | D95: 479.1 | E95: 499.5 | F95: 498.5 | G95: 494.5
A96: Дальневосточный | B96: 4 136,5 | C96: 4 053,7 | D96: 3898.6 | E96: 3945.5 | F96: 3 926,1 | G96: 3965
A97: федеральный округ
A98: Республика Бурятия | B98: 401 | C98: 398 | D98: 352.8 | E98: 370.9 | F98: 366.2 | G98: 376.8
A99: Республика Саха (Якутия) | B99: 482.2 | C99: 482.7 | D99: 492.4 | E99: 495.7 | F99: 509.2 | G99: 526.7
A100: Забайкальский край | B100: 488.2 | C100: 475.4 | D100: 452.5 | E100: 456.8 | F100: 446.3 | G100: 427.4
...

Sheet Доход
A1: РЕАЛЬНЫЕ ДЕНЕЖНЫЕ ДОХОДЫ НАСЕЛЕНИЯ (в процентах к предыдущему году)
B2: 2010 | C2: 2015 | D2: 2020 | E2: 2021 | F2: 2022 | G2: 2023 | H2: Место, занима-емоев Российской Федерации 2023
A3: Российская Федерация | B3: 18 958 | C3: 30140 | D3: 35934 | E3: 39934 | F3: 47 386 | G3: 53579
A4: Центральный | B4: 24 645 | C4: 38351 | D4: 47318 | E4: 53244 | F4: 62 684 | G4: 71 914 | H4: 1
A5: федеральный округ
A6: Белгородская область | B6: 16 993 | C6: 28006 | D6: 32799 | E6: 35511 | F6: 41855 | G6: 47257 | H6: 25
A7: Брянская область | B7: 13 358 | C7: 23479 | D7: 28720 | E7: 31713 | F7: 37428 | G7: 40927 | H7: 49
A8: Владимирская область | B8: 12 956 | C8: 22593 | D8: 25649 | E8: 28148 | F8: 34667 | G8: 38649 | H8: 62
A9: Воронежская область | B9: 13 883 | C9: 29291 | D9: 31925 | E9: 34982 | F9: 41156 | G9: 45087 | H9: 31
A10: Ивановская область | B10: 11 124 | C10: 22783 | D10: 27558 | E10: 30235 | F10: 36509 | G10: 41108 | H10: 48
A11: Калужская область | B11: 15 477 | C11: 26787 | D11: 30943 | E11: 33174 | F11: 39423 | G11: 44564 | H11: 32
A12: Костромская область | B12: 13 315 | C12: 22550 | D12: 27408 | E12: 30567 | F12: 37285 | G12: 43668 | H12: 35
A13: Курская область | B13: 14 685 | C13: 25383 | D13: 29917 | E13: 32871 | F13: 39401 | G13: 43719 | H13: 34
A14: Липецкая область | B14: 15 936 | C14: 26864 | D14: 31932 | E14: 34509 | F14: 41177 | G14: 45458 | H14: 30
A15: Московская область | B15: 22 641 | C15: 36170 | D15: 43332 | E15: 49213 | F15: 55746 | G15: 64870 | H15: 12
A16: Орловская область | B16: 13 115 | C16: 22152 | D16: 27121 | E16: 30008 | F16: 35923 | G16: 43730 | H16: 33
A17: Рязанская область | B17: 13 886 | C17: 23578 | D17: 27044 | E17: 30142 | F17: 36431 | G17: 39905 | H17: 53
... A23: г. Москва | B23: 44 051 | C23: 60465 | D23: 76320 | E23: 86453 | F23: 102143 | G23: 117103 | H23: 4
A24: Северо-Западный | B24: 19 837 | C24: 31256 | D24: 39502 | E24: 44623 | F24: 52 455 | G24: 58 669 | H24: 2
A25: федеральный округ
A26: Республика Карелия | B26: 16 046 | C26: 27118 | D26: 36504 | E26: 39929 | F26: 46019 | G26: 53068 | H26: 20
A27: Республика Коми | B27: 22 260 | C27: 32331 | D27: 39601 | E27: 42603 | F27: 50840 | G27: 56152 | H27: 14
A28: Архангельская область | B28: 19 609 | C28: 32434 | D28: 39788 | E28: 43381 | F28: 52050 | G28: 58967
A29: в том числе:
A30: Ненецкий автономный округ | B30: 52 270 | C30: 74218 | D30: 89570 | E30: 92620 | F30: 115336 | G30: 128204 | H30: 3
A31: Архангельская область без автономного округа | C31: 30816 | D31: 37728 | E31: 41307 | F31: 49 347 | G31: 55 952 | H31: 15
A32: без автономного округа
A33: Вологодская область | B33: 14 115 | C33: 25002 | D33: 29706 | E33: 31887 | F33: 37178 | G33: 42708 | H33: 41
A34: Калининградская область | B34: 16 040 | C34: 25476 | D34: 29536 | E34: 31934 | F34: 38327 | G34: 43543 | H34: 36
A35: Ленинградская область | B35: 14 798 | C35: 25008 | D35: 31884 | E35: 35199 | F35: 40790 | G35: 45989 | H35: 28
A36: Мурманская область | B36: 24 047 | C36: 38001 | D36: 50139 | E36: 55506 | F36: 65707 | G36: 75786 | H36: 8
A37: Новгородская область | B37: 15 599 | C37: 25712 | D37: 26606 | E37: 29517 | F37: 34201 | G37: 38903 | H37: 61
A38: Псковская область | B38: 12 798 | C38: 21762 | D38: 27069 | E38: 30127 | F38: 35031 | G38: 39898 | H38: 54
A39: г. Санкт-Петербург | B39: 24 824 | C39: 36757 | D39: 47664 | E39: 55679 | F39: 65395 | G39: 72037 | H39: 10
A40: Южный | B40: 15 114 | C40: 25157 | D40: 30413 | E40: 34431 | F40: 40 219 | G40: 45 063 | H40: 5
A41: федеральный округ
A42: Республика Адыгея | B42: 12 279 | C42: 22417 | D42: 28716 | E42: 32882 | F42: 36627 | G42: 42684 | H42: 43
A43: Республика Калмыкия | B43: 7 774 | C43: 15325 | D43: 19892 | E43: 21415 | F43: 23771 | G43: 28635 | H43: 83
A44: Республика Крым | C44: 15641 | D44: 22698 | E44: 25937 | F44: 29817 | G44: 32875 | H44: 79
A45: Краснодарский край | B45: 16 892 | C45: 30970 | D45: 36547 | E45: 42228 | F45: 48684 | G45: 54627 | H45: 16
A46: Астраханская область | B46: 14 697 | C46: 24149 | D46: 25912 | E46: 27675 | F46: 33137 | G46: 36593 | H46: 66
A47: Волгоградская область | B47: 13 775 | C47: 21953 | D47: 24627 | E47: 27226 | F47: 32673 | G47: 35575 | H47: 71
A48: Ростовская область | B48: 14 647 | C48: 25730 | D48: 31270 | E48: 34743 | F48: 41377 | G48: 46840 | H48: 26
A49: г. Севастополь | C49: 17324 | D49: 27267 | E49: 31603 | F49: 35679 | G49: 39968 | H49: 52
A50: Северо-Кавказский | B50: 13 253 | C50: 22368 | D50: 24143 | E50: 26323 | F50: 32 330 | G50: 35 426 | H50: 8
A51: федеральный округ
A52: Республика Дагестан | B52: 15 678 | C52: 26625 | D52: 27395 | E52: 29952 | F52: 37606 | G52: 39686 | H52: 56
A53: Республика Ингушетия | B53: 9 630 | C53: 15358 | D53: 17247 | E53: 18573 | F53: 23047 | G53: 24414 | H53: 85
A54: Кабардино-Балкарская Республика | B54: 11 290 | C54: 18670 | D54: 21276 | E54: 24991 | F54: 34759 | G54: 38948 | H54: 59
A55: Карачаево-Черкесская Республика | B55: 10 878 | C55: 17754 | D55: 18903 | E55: 20256 | F55: 23035 | G55: 25619 | H55: 84
A56: Республика Северная Осетия | B56: 13 193 | C56: 21816 | D56: 24035 | E56: 25980 | F56: 30774 | G56: 35276 | H56: 72
A57: Чеченская Республика | B57: 11 982 | C57: 22703 | D57: 24645 | E57: 26425 | F57: 30751 | G57: 35920 | H57: 69
A58: Ставропольский край | B58: 13 016 | C58: 20871 | D58: 23305 | E58: 25133 | F58: 30100 | G58: 32930 | H58: 78
A59: Приволжский | B59: 15 840 | C59: 26097 | D59: 28604 | E59: 31285 | F59: 37173 | G59: 41 765 | H59: 7
A60: федеральный округ
A61: Республика Башкортостан | B61: 17 499 | C61: 27065 | D61: 29827 | E61: 31935 | F61: 36 463 | G61: 40022 | H61: 51
A62: Республика Марий Эл | B62: 10 336 | C62: 18496 | D62: 21138 | E62: 23024 | F62: 27276 | G62: 31013 | H62: 80
A63: Республика Мордовия | B63: 11 294 | C63: 17494 | D63: 20394 | E63: 22607 | F63: 27439 | G63: 30647 | H63: 81
A64: Республика Татарстан | B64: 18 424 | C64: 32031 | D64: 34815 | E64: 38601 | F64: 45932 | G64: 52524 | H64: 21
A65: Удмуртская Республика | B65: 12 984 | C65: 24493 | D65: 25997 | E65: 28346 | F65: 33820 | G65: 38939 | H65: 60
A66: Чувашская Республика | B66: 11 066 | C66: 18244 | D66: 21384 | E66: 23926 | F66: 28702 | G66: 34129 | H66: 76
A67: Пермский край | B67: 19 834 | C67: 31754 | D67: 30550 | E67: 33139 | F67: 39767 | G67: 45639 | H67: 29
A68: Кировская область | B68: 13 331 | C68: 22194 | D68: 25804 | E68: 28519 | F68: 35178 | G68: 38277 | H68: 64
A69: Нижегородская область | B69: 16 477 | C69: 30139 | D69: 34140 | E69: 37929 | F69: 45573 | G69: 50601 | H69: 22
A70: Оренбургская область | B70: 13 557 | C70: 23301 | D70: 25530 | E70: 27454 | F70: 32972 | G70: 36756 | H70: 65
A71: Пензенская область | B71: 12 920 | C71: 21540 | D71: 24352 | E71: 26676 | F71: 32072 | G71: 36429 | H71: 68
A72: Самарская область | B72: 20 223 | C72: 27799 | D72: 29708 | E72: 32343 | F72: 38444 | G72: 42701 | H72: 42
A73: Саратовская область | B73: 12 147 | C73: 19887 | D73: 23515 | E73: 25517 | F73: 30290 | G73: 33348 | H73: 77
... A75: Уральский | B75: 21 832 | C75: 32741 | D75: 37379 | E75: 40251 | F75: 47466 | G75: 53489 | H75: 4
A76: федеральный округ
A77: Курганская область | B77: 13 499 | C77: 20635 | D77: 22654 | E77: 24710 | F77: 29838 | G77: 34812 | H77: 75
A78: Свердловская область | B78: 22 194 | C78: 34116 | D78: 37452 | E78: 40281 | F78: 47109 | G78: 53413 | H78: 19
A79: Тюменская область | B79: 28 757 | C79: 41810 | D79: 50206 | E79: 53105 | F79: 62161 | G79: 69341
A80: в том числе:
A81: Ханты-Мансийский автономный округ | B81: 32 385 | C81: 46088 | D81: 54264 | E81: 56644 | F81: 66517 | G81: 72634 | H81: 9
A82: автономный округ – Югра
A83: Ямало-Ненецкий автономный округ | B83: 43 367 | C83: 69942 | D83: 96553 | E83: 104323 | F83: 120010 | G83: 139651 | H83: 2
A84: Тюменская область без автономных округов | C84: 27068 | D84: 30971 | E84: 32956 | F84: 39047 | G84: 43350 | H84: 38
A85: Челябинская область | B85: 16 821 | C85: 24646 | D85: 26628 | E85: 29474 | F85: 35347 | G85: 39703 | H85: 55
A86: Сибирский | B86: 15 007 | C86: 23687 | D86: 28187 | E86: 31007 | F86: 37881 | G86: 42991 | H86: 6
A87: федеральный округ2)
A88: Республика Алтай | B88: 13 536 | C88: 18257 | D88: 22642 | E88: 24958 | F88: 29564 | G88: 34817 | H88: 74
A89: Республика Тыва | B89: 10 160 | C89: 15500 | D89: 18803 | E89: 20435 | F89: 24460 | G89: 28934 | H89: 82
A90: Республика Хакасия | B90: 12 806 | C90: 19053 | D90: 23659 | E90: 25849 | F90: 31056 | G90: 34999 | H90: 73
A91: Алтайский край | B91: 11 029 | C91: 21277 | D91: 24981 | E91: 27305 | F91: 32901 | G91: 36431 | H91: 67
A92: Красноярский край | B92: 18 262 | C92: 27026 | D92: 32801 | E92: 36004 | F92: 43183 | G92: 50380 | H92: 23
A93: Иркутская область | B93: 15 110 | C93: 21730 | D93: 27514 | E93: 30270 | F93: 37484 | G93: 42483 | H93: 44
A94: Кемеровская область | B94: 15 341 | C94: 21921 | D94: 25544 | E94: 28174 | F94: 33996 | G94: 39408 | H94: 57
A95: Новосибирская область | B95: 16 276 | C95: 25477 | D95: 31440 | E95: 35070 | F95: 44359 | G95: 49936 | H95: 24
A96: Омская область | B96: 15 199 | C96: 25433 | D96: 27729 | E96: 30407 | F96: 36919 | G96: 40804 | H96: 50
A97: Томская область | B97: 15 070 | C97: 26885 | D97: 29001 | E97: 31210 | F97: 37954 | G97: 41600 | H97: 46
A98: Дальневосточный | B98: 20 807 | C98: 32199 | D98: 39612 | E98: 43089 | F98: 52186 | G98: 57941 | H98: 3
A99: федеральный округ2)
A100: Республика Бурятия | B100: 14 271 | C100: 23902 | D100: 26333 | E100: 28446 | F100: 35163 | G100: 38412 | H100: 63
A101: Республика Саха (Якутия) | B101: 23 088 | C101: 36918 | D101: 46108 | E101: 50090 | F101: 59040 | G101: 69031 | H101: 11
A102: Забайкальский край | B102: 14 205 | C102: 22369 | D102: 28021 | E102: 31043 | F102: 38601 | G102: 42758 | H102: 39
A103: Камчатский край | B103: 27 010 | C103: 43985 | D103: 58674 | E103: 64791 | F103: 77505 | G103: 87054 | H103: 7
A104: Приморский край | B104: 17 298 | C104: 31224 | D104: 37728 | E104: 41293 | F104: 49942 | G104: 54494 | H104: 17
A105: Хабаровский край | B105: 22 479 | C105: 35550 | D105: 41931 | E105: 44310 | F105: 52656 | G105: 58092 | H105: 13
A106: Амурская область | B106: 14 323 | C106: 28371 | D106: 35862 | E106: 40067 | F106: 49798 | G106: 54055 | H106: 18
...

Sheet Темп роста
B1: Численность | C1: Реальные | D1: Реальные | E1: Реальная | F1: Валовой | G1: Инвестиции | H1: Промышленное производство2) | I1: Продукция | J1: в том числе | L1: Ввод | M1: Оборот | N1: Производи- | O1: Сальдиро-ванный финансовый
B2: населения | C2: денежные | D2: потреби- | E2: начисленная | F2: региональ- | G2: в основной | I2: сельского | L2: в действие | M2: розничной | N2: тельность труда | O2: результат
B3: на 1 января | C3: доходы | D3: тельские | E3: заработная плата работ- | F3: ный продукт | G3: капитал | I3: хозяйства – | L3: жилых | M3: торговли | N3: в 2022 г.3) | O3: (прибыль минус убы-ток) дея-тельности
B4: 2024 г. | C4: населения | D4: расходы | E4: ников орга- | F4: в 2022 г.1) | I4: всего | L4: домов | O4: организаций
D5: населения | E5: низаций | O5: (в фактичес-ки действо-вавших
J6: растение- | K6: животно- | O6: ценах)4)
J7: водства | K7: водства
A8: Российская Федерация | B8: 99.8 | C8: 106.5 | D8: 108.6 | E8: 108.2 | F8: 100.3 | G8: 109.8 | H8: 104.1 | I8: 100.2 | J8: 99.7 | K8: 100.9 | L8: 107.5 | M8: 108 | N8: 97.2 | O8: 156 | P8: Российская Федерация
A9: Центральный | B9: 99.9 | C9: 107.9 | D9: 107.8 | E9: 106.8 | F9: 98.8 | G9: 103.6 | H9: 116 | I9: 106.6 | J9: 109.2 | K9: 103.2 | L9: 100.3 | M9: 106.7 | O9: 173.6 | P9: Центральный
A10: федеральный округ | P10: федеральный округ
A11: Белгородская область | B11: 99.1 | C11: 105.2 | D11: 101.5 | E11: 107.8 | F11: 99.2 | G11: 99 | H11: 104.7 | I11: 105 | J11: 108.7 | K11: 102.6 | L11: 114.1 | M11: 99.2 | N11: 96.7 | O11: 126.1 | P11: Белгородская область
A12: Брянская область | B12: 99.1 | C12: 101.2 | D12: 98.2 | E12: 110.1 | F12: 99.9 | G12: 93.4 | H12: 115.8 | I12: 115.9 | J12: 118.9 | K12: 112.8 | L12: 117 | M12: 97.6 | N12: 101.9 | O12: 134.3 | P12: Брянская область
A13: Владимирская область | B13: 98.8 | C13: 103.7 | D13: 104 | E13: 109.9 | F13: 93.4 | G13: 91.2 | H13: 109.3 | I13: 105.7 | J13: 109.6 | K13: 103.5 | L13: 96.8 | M13: 103.4 | N13: 90 | O13: 102 | P13: Владимирская область
A14: Воронежская область | B14: 99.5 | C14: 103.3 | D14: 104.4 | E14: 109.3 | F14: 97.6 | G14: 100.5 | H14: 109.9 | I14: 103.3 | J14: 105.3 | K14: 100 | L14: 104.8 | M14: 104.6 | N14: 94.6 | O14: 109.9 | P14: Воронежская область
A15: Ивановская область | B15: 99 | C15: 105.9 | D15: 102.4 | E15: 109.5 | F15: 100 | G15: 97.8 | H15: 110 | I15: 108.5 | J15: 114.9 | K15: 104.1 | L15: 130.5 | M15: 102 | N15: 99.5 | O15: 142.2 | P15: Ивановская область
A16: Калужская область | B16: 99.8 | C16: 105.6 | D16: 104.5 | E16: 106.9 | F16: 88.5 | G16: 79.6 | H16: 111 | I16: 106.3 | J16: 106 | K16: 106.6 | L16: 122.1 | M16: 103.6 | N16: 89.4 | O16: 14.6 | P16: Калужская область
A17: Костромская область | B17: 99 | C17: 107.8 | D17: 102.9 | E17: 108 | F17: 98.3 | G17: 114.4 | H17: 108.7 | I17: 105.6 | J17: 111.1 | K17: 102.9 | L17: 106.8 | M17: 100.6 | N17: 97.1 | O17: – | P17: Костромская область
A18: Курская область | B18: 99.4 | C18: 103.5 | D18: 102 | E18: 109.4 | F18: 94.6 | G18: 102.9 | H18: 111.3 | I18: 105 | J18: 105.2 | K18: 104.5 | L18: 111.9 | M18: 101.4 | N18: 92.8 | O18: 89.9 | P18: Курская область
A19: Липецкая область | B19: 99.1 | C19: 103.3 | D19: 101.1 | E19: 109.4 | F19: 92 | G19: 104.1 | H19: 108.9 | I19: 103.5 | J19: 105.6 | K19: 98.6 | L19: 102.1 | M19: 100.4 | N19: 93.3 | O19: 129.8 | P19: Липецкая область
A20: Московская область | B20: 100.7 | C20: 108.8 | D20: 107.5 | E20: 109.3 | F20: 95 | G20: 106.2 | H20: 116.2 | I20: 103.1 | J20: 107.3 | K20: 96.9 | L20: 88.6 | M20: 109.6 | N20: 96.5 | O20: 158.5 | P20: Московская область
A21: Орловская область | B21: 98.9 | C21: 113.8 | D21: 103.3 | E21: 109.9 | F21: 97.1 | G21: 88.3 | H21: 103.6 | I21: 114.3 | J21: 117.1 | K21: 107.3 | L21: 100.1 | M21: 102.6 | N21: 96.2 | O21: 138.8 | P21: Орловская область
A22: Рязанская область | B22: 99.4 | C22: 102.8 | D22: 105.4 | E22: 110.1 | F22: 101.7 | G22: 102.1 | H22: 108.6 | I22: 105.5 | J22: 104.1 | K22: 107.6 | L22: 97.8 | M22: 105.6 | N22: 101.1 | O22: 118.5 | P22: Рязанская область
A23: Смоленская область | B23: 99 | C23: 113.6 | D23: 106.1 | E23: 113.2 | F23: 100.1 | G23: 128.9 | H23: 111.1 | I23: 100.7 | J23: 100.3 | K23: 101 | L23: 100.4 | M23: 107.3 | N23: 96.8 | O23: 131.5 | P23: Смоленская область
A24: Тамбовская область | B24: 99 | C24: 105 | D24: 100.9 | E24: 109.5 | F24: 98.1 | G24: 104.6 | H24: 112.3 | I24: 111.1 | J24: 120.5 | K24: 95.2 | L24: 119.3 | M24: 100.8 | N24: 96.3 | O24: 117.4 | P24: Тамбовская область
A25: Тверская область | B25: 99.1 | C25: 107.3 | D25: 106.7 | E25: 112 | F25: 96.9 | G25: 145.4 | H25: 115.4 | I25: 116.5 | J25: 118 | K25: 115.9 | L25: 107.5 | M25: 107.6 | N25: 97 | O25: 133.3 | P25: Тверская область
A26: Тульская область | B26: 99.3 | C26: 107 | D26: 111.5 | E26: 111.7 | F26: 104.1 | G26: 101.6 | H26: 117.1 | I26: 107.1 | J26: 107.9 | K26: 105.6 | L26: 120.9 | M26: 111 | N26: 104.2 | O26: 113 | P26: Тульская область
A27: Ярославская область | B27: 99.4 | C27: 108.4 | D27: 103.8 | E27: 111.5 | F27: 97 | G27: 106.1 | H27: 106.9 | I27: 105.1 | J27: 105.6 | K27: 104.9 | L27: 119.8 | M27: 105.2 | N27: 98.5 | O27: 120.9 | P27: Ярославская область
A28: г. Москва | B28: 100.3 | C28: 109 | D28: 110.4 | E28: 104.4 | F28: 100.6 | G28: 103.8 | H28: 118.7 | I28: 70.8 | J28: 70.2 | K28: 81.2 | L28: 108 | M28: 107.5 | N28: 101.3 | O28: 190.4 | P28: г. Москва
A29: Северо-Западный | B29: 99.8 | C29: 105.4 | D29: 111.7 | E29: 106.1 | F29: 97.5 | G29: 104.3 | H29: 104.9 | I29: 100.8 | J29: 99.4 | K29: 101.4 | L29: 101.7 | M29: 113.1 | O29: 120.7 | P29: Северо-Западный
A30: федеральный округ | P30: федеральный округ
A31: Республика Карелия | B31: 99.2 | C31: 107.9 | D31: 110 | E31: 108.2 | F31: 91 | G31: 95.7 | H31: 100.2 | I31: 99.9 | J31: 99.4 | K31: 100.3 | L31: 100.8 | M31: 112.2 | N31: 90.6 | O31: 60.8 | P31: Республика Карелия
A32: Республика Коми | B32: 99.2 | C32: 103.4 | D32: 102.6 | E32: 106.6 | F32: 99.9 | G32: 98.5 | H32: 100.5 | I32: 94.6 | J32: 101.4 | K32: 91.6 | L32: 107.1 | M32: 105.8 | N32: 102.1 | O32: 63.8 | P32: Республика Коми
A33: Архангельская область | B33: 99.2 | C33: 105.9 | D33: 103.9 | E33: 106.2 | F33: 102.5 | G33: 98.7 | H33: 95.9 | I33: 101.6 | J33: 99 | K33: 103.9 | L33: 100 | M33: 102.9 | N33: 102.1 | O33: 69.9 | P33: Архангельская область
A34: в том числе: | P34: в том числе:
A35: Ненецкий автономный округ | B35: 102 | C35: 105 | D35: 102.5 | E35: 104.4 | F35: 112.3 | G35: 94.4 | H35: 93.7 | I35: 102.8 | J35: 100.1 | K35: 103.2 | L35: 60.8 | M35: 103.7 | N35: 107.9 | O35: 34 | P35: Ненецкий автономный округ
A36: Архангельская область | B36: 99.1 | C36: 105.9 | D36: 104 | E36: 106.2 | F36: 96.5 | G36: 100.8 | H36: 99.2 | I36: 101.5 | J36: 99 | K36: 104 | L36: 103.3 | M36: 102.8 | N36: 96 | O36: 87.1 | P36: Архангельская область
A37: без автономного округа | P37: без автономного округа
A38: Вологодская область | B38: 99.3 | C38: 107.4 | D38: 103.9 | E38: 103.7 | F38: 95.2 | G38: 86.7 | H38: 106.2 | I38: 101.7 | J38: 102.8 | K38: 101.2 | L38: 115.1 | M38: 102.6 | N38: 95.1 | O38: 62.8 | P38: Вологодская область
A39: Калининградская область | B39: 100.2 | C39: 106.9 | D39: 107.9 | E39: 108.6 | F39: 95.5 | G39: 142.7 | H39: 96.8 | I39: 103.2 | J39: 103.5 | K39: 102.9 | L39: 92.3 | M39: 107.5 | N39: 91.5 | O39: в 2,3 р. | P39: Калининградская область
A40: Ленинградская область | B40: 100.6 | C40: 107.3 | D40: 113.1 | E40: 107.2 | F40: 100.1 | G40: 113.2 | H40: 107.9 | I40: 101.1 | J40: 97.1 | K40: 102.5 | L40: 105.5 | M40: 114.4 | N40: 93.8 | O40: 109.4 | P40: Ленинградская область
A41: Мурманская область | B41: 99.7 | C41: 107.3 | D41: 103.3 | E41: 106 | F41: 92.6 | G41: 91 | H41: 97.5 | I41: 106.1 | J41: 83 | K41: 122.7 | L41: 33.7 | M41: 101.1 | N41: 97.1 | O41: 91 | P41: Мурманская область
A42: Новгородская область | B42: 99.2 | C42: 106.5 | D42: 102.5 | E42: 111 | F42: 98.6 | G42: 116.9 | H42: 102.7 | I42: 99.6 | J42: 101.7 | K42: 98.3 | L42: 109.6 | M42: 102.9 | N42: 98.1 | O42: 60.2 | P42: Новгородская область
A43: Псковская область | B43: 98.9 | C43: 106.8 | D43: 102.8 | E43: 109.3 | F43: 99.1 | G43: 100.5 | H43: 118.4 | I43: 98.7 | J43: 87 | K43: 101.5 | L43: 111.6 | M43: 102.3 | N43: 99.9 | O43: 162.3 | P43: Псковская область
A44: г. Санкт-Петербург | B44: 99.96 | C44: 104.2 | D44: 117.2 | E44: 105.2 | F44: 97.6 | G44: 103.4 | H44: 111.5 | I44: – | J44: – | K44: – | L44: 100.2 | M44: 119.2 | N44: 97.2 | O44: 143.6 | P44: г. Санкт-Петербург
A45: Южный федеральный округ | B45: 99.9 | C45: 105.2 | D45: 110.7 | E45: 108.9 | F45: 104.9 | G45: 108.2 | H45: 103.5 | I45: 100.4 | J45: 100.6 | K45: 99.7 | L45: 106 | M45: 112.4 | O45: 151.3 | P45: Южный федеральный округ
A46: Республика Адыгея | B46: 100.5 | C46: 111.4 | D46: 114.3 | E46: 110.1 | F46: 104.2 | G46: 122.4 | H46: 107.2 | I46: 101.6 | J46: 96.4 | K46: 110.2 | L46: 120.5 | M46: 111.6 | N46: 104.7 | O46: 130.3 | P46: Республика Адыгея
A47: Республика Калмыкия | B47: 100.9 | C47: 115.6 | D47: 160.3 | E47: 111.3 | F47: 108.8 | G47: 80 | H47: 102 | I47: 104.8 | J47: 116.2 | K47: 98.1 | L47: 115.4 | M47: 187.1 | N47: 104.1 | O47: – | P47: Республика Калмыкия
A48: Республика Крым | B48: 99.6 | C48: 102.6 | D48: 103.1 | E48: 105.5 | F48: 98 | G48: 117 | H48: 98.3 | I48: 95.9 | J48: 95.7 | K48: 96.4 | L48: 131.5 | M48: 103.9 | N48: 97 | O48: 19.3 | P48: Республика Крым
A49: Краснодарский край | B49: 100.2 | C49: 105.5 | D49: 111.4 | E49: 109 | F49: 108.1 | G49: 102.4 | H49: 106 | I49: 95.7 | J49: 93.8 | K49: 101.4 | L49: 100.6 | M49: 115.6 | N49: 102.6 | O49: 163.1 | P49: Краснодарский край
A50: Астраханская область | B50: 99.6 | C50: 103.7 | D50: 105.7 | E50: 106.6 | F50: 100.7 | G50: 90.1 | H50: 100.6 | I50: 103 | J50: 105.9 | K50: 98.8 | L50: 107 | M50: 101.3 | N50: 97.6 | O50: 86.8 | P50: Астраханская область
A51: Волгоградская область | B51: 99.3 | C51: 102.4 | D51: 110.4 | E51: 111.2 | F51: 104.3 | G51: 121.1 | H51: 102.5 | I51: 100.1 | J51: 101.3 | K51: 96.4 | L51: 119.1 | M51: 110.2 | N51: 103.1 | O51: 150 | P51: Волгоградская область
A52: Ростовская область | B52: 99.7 | C52: 106 | D52: 111.4 | E52: 109.5 | F52: 103.1 | G52: 123.3 | H52: 103.5 | I52: 106.9 | J52: 109.5 | K52: 99.1 | L52: 109.6 | M52: 109.9 | N52: 101.5 | O52: в 2,2 р. | P52: Ростовская область
A53: г. Севастополь | B53: 100.6 | C53: 106.4 | D53: 106.4 | E53: 103.7 | F53: 109.4 | G53: 49.2 | H53: 116.4 | I53: 97.3 | J53: 100 | K53: 73.1 | L53: 86.2 | M53: 101.3 | N53: 98.8 | O53: 59.4 | P53: г. Севастополь
A54: Северо-Кавказский | B54: 100.4 | C54: 103.4 | D54: 108.1 | E54: 105.9 | F54: 102.5 | G54: 108 | H54: 110.2 | I54: 104.5 | J54: 105.8 | K54: 102.6 | L54: 123.3 | M54: 107.6 | O54: 133.1 | P54: Северо-Кавказский
A55: федеральный округ | P55: федеральный округ
A56: Республика Дагестан | B56: 100.7 | C56: 100.5 | D56: 103.6 | E56: 105.2 | F56: 101.9 | G56: 107.2 | H56: 123.8 | I56: 105.9 | J56: 111.8 | K56: 100.2 | L56: 160.9 | M56: 101.8 | N56: 93.7 | O56: – | P56: Республика Дагестан
A57: Республика Ингушетия | B57: 101.6 | C57: 99.9 | D57: 119.2 | E57: 101.4 | F57: 103.8 | G57: 105.5 | H57: 117.8 | I57: 100.8 | J57: 90.5 | K57: 108 | L57: 120.6 | M57: 121.3 | N57: 96.9 | O57: – | P57: Республика Ингушетия
A58: Кабардино-Балкарская Республика | B58: 100.2 | C58: 105.3 | D58: 110.5 | E58: 106.5 | F58: 107 | G58: 108.5 | H58: 102.7 | I58: 110.1 | J58: 112.3 | K58: 106.9 | L58: 107 | M58: 109.4 | N58: 103.8 | O58: – | P58: Кабардино-Балкарская Республика
A59: Карачаево-Черкесская Республика | B59: 99.97 | C59: 104.8 | D59: 111.9 | E59: 107.5 | F59: 104.4 | G59: 77.9 | H59: 114.3 | I59: 102.7 | J59: 104.1 | K59: 101.5 | L59: 135.9 | M59: 106.8 | N59: 97.3 | O59: – | P59: Карачаево-Черкесская Республика
A60: Республика Северная | B60: 99.7 | C60: 107.8 | D60: 105 | E60: 106.7 | F60: 100.5 | G60: 92.5 | H60: 126.6 | I60: 106.8 | J60: 111.9 | K60: 103.4 | L60: 140.9 | M60: 107.1 | N60: 98.3 | O60: – | P60: Республика Северная
A61: Осетия – Алания | P61: Осетия – Алания
A62: Чеченская Республика | B62: 101.3 | C62: 111.9 | D62: 108.5 | E62: 105.4 | F62: 104.7 | G62: 129.2 | H62: 104.5 | I62: 110.9 | J62: 123.4 | K62: 101.2 | L62: 115.6 | M62: 103.7 | N62: 98.2 | O62: – | P62: Чеченская Республика
A63: Ставропольский край | B63: 99.8 | C63: 101.7 | D63: 112.4 | E63: 106 | F63: 101.5 | G63: 106.2 | H63: 106.4 | I63: 100.8 | J63: 99.8 | K63: 103.4 | L63: 109.2 | M63: 114.3 | N63: 101.1 | O63: 136.4 | P63: Ставропольский край
A64: Приволжский | B64: 99.5 | C64: 106 | D64: 108.6 | E64: 111.8 | F64: 101.7 | G64: 116.1 | H64: 107.9 | I64: 97.5 | J64: 94.6 | K64: 101.2 | L64: 108.7 | M64: 109.4 | O64: 156 | P64: Приволжский
A65: федеральный округ | P65: федеральный округ
A66: Республика Башкортостан | B66: 99.7 | C66: 104.9 | D66: 109.5 | E66: 110.5 | F66: 101 | G66: 107.6 | H66: 108 | I66: 88.8 | J66: 80.3 | K66: 96.8 | L66: 108.3 | M66: 111.3 | N66: 97.9 | O66: 114.1 | P66: Республика Башкортостан
A67: Республика Марий Эл | B67: 99.6 | C67: 105.6 | D67: 106.5 | E67: 112.3 | F67: 99.7 | G67: 114.1 | H67: 115.7 | I67: 100.2 | J67: 91.9 | K67: 104.1 | L67: 123.1 | M67: 108.8 | N67: 100.9 | O67: 186.4 | P67: Республика Марий Эл
A68: Республика Мордовия | B68: 99.3 | C68: 105.5 | D68: 126.1 | E68: 112 | F68: 98.9 | G68: 112.4 | H68: 109.5 | I68: 107.2 | J68: 113.4 | K68: 103 | L68: 105.2 | M68: 131.8 | N68: 98.4 | O68: 159 | P68: Республика Мордовия
A69: Республика Татарстан | B69: 100 | C69: 109 | D69: 111.2 | E69: 112.8 | F69: 105.4 | G69: 122 | H69: 103 | I69: 91.8 | J69: 81.8 | K69: 101.2 | L69: 111.1 | M69: 111.3 | N69: 103.9 | O69: в 2,0 р. | P69: Республика Татарстан
A70: Удмуртская Республика | B70: 99.5 | C70: 107.8 | D70: 105.5 | E70: 110.3 | F70: 101.4 | G70: 106 | H70: 113.6 | I70: 99 | J70: 88.9 | K70: 103.2 | L70: 118.2 | M70: 104.6 | N70: 101.8 | O70: 125.3 | P70: Удмуртская Республика
A71: Чувашская Республика | B71: 99.5 | C71: 112.1 | D71: 110.8 | E71: 114.8 | F71: 103.7 | G71: 113.2 | H71: 130.7 | I71: 100.5 | J71: 100.2 | K71: 100.8 | L71: 91.8 | M71: 112.1 | N71: 104.9 | O71: 191.5 | P71: Чувашская Республика
A72: Пермский край | B72: 99.5 | C72: 107.9 | D72: 104.3 | E72: 110.8 | F72: 98.7 | G72: 115.8 | H72: 105.9 | I72: 91.5 | J72: 75.4 | K72: 99.8 | L72: 97 | M72: 102.1 | N72: 99.6 | O72: 75.5 | P72: Пермский край
A73: Кировская область | B73: 99.3 | C73: 101.4 | D73: 104.8 | E73: 111.1 | F73: 100.7 | G73: 106.5 | H73: 110.5 | I73: 97.5 | J73: 88.8 | K73: 101.8 | L73: 112.3 | M73: 104.1 | N73: 102 | O73: 105.7 | P73: Кировская область
A74: Нижегородская область | B74: 99.3 | C74: 104.7 | D74: 108.3 | E74: 111 | F74: 102.5 | G74: 136.6 | H74: 111.7 | I74: 111.1 | J74: 114.2 | K74: 107.9 | L74: 109.3 | M74: 108.3 | N74: 102.4 | O74: 156.9 | P74: Нижегородская область
A75: Оренбургская область | B75: 99.3 | C75: 105.4 | D75: 106.1 | E75: 116.2 | F75: 101.3 | G75: 110.9 | H75: 103.7 | I75: 95.7 | J75: 93.6 | K75: 99.6 | L75: 118.9 | M75: 107.4 | N75: 102.8 | O75: 100.3 | P75: Оренбургская область
A76: Пензенская область | B76: 99.2 | C76: 107.1 | D76: 106.6 | E76: 111 | F76: 101.5 | G76: 106.2 | H76: 112.4 | I76: 107.7 | J76: 108.1 | K76: 107.3 | L76: 113.3 | M76: 105.8 | N76: 102 | O76: 152 | P76: Пензенская область
A77: Самарская область | B77: 99.5 | C77: 103.8 | D77: 111.1 | E77: 111.7 | F77: 97.8 | G77: 104.9 | H77: 111.4 | I77: 94.5 | J77: 91.9 | K77: 101.9 | L77: 103 | M77: 112.9 | N77: 98.8 | O77: в 3,7 р. | P77: Самарская область
A78: Саратовская область | B78: 99.2 | C78: 103.5 | D78: 107.4 | E78: 110.6 | F78: 105.3 | G78: 124 | H78: 104.9 | I78: 100.6 | J78: 102.1 | K78: 96.4 | L78: 114 | M78: 108 | N78: 100.6 | O78: 149.3 | P78: Саратовская область
A79: Ульяновская область | B79: 99.3 | C79: 105 | D79: 105.2 | E79: 110.3 | F79: 99 | G79: 102.3 | H79: 115.1 | I79: 93.7 | J79: 93.6 | K79: 93.9 | L79: 115.6 | M79: 104.5 | N79: 95.5 | O79: в 5,4 р. | P79: Ульяновская область
A80: Уральский | B80: 100 | C80: 107.7 | D80: 109.1 | E80: 109.5 | F80: 101.1 | G80: 103.3 | H80: 101.9 | I80: 91.5 | J80: 85.6 | K80: 97.3 | L80: 111.5 | M80: 110 | O80: 137 | P80: Уральский
A81: федеральный округ | P81: федеральный округ
A82: Курганская область | B82: 98.9 | C82: 109.6 | D82: 109.2 | E82: 115.9 | F82: 107.7 | G82: 115 | H82: 117.1 | I82: 79.7 | J82: 73.6 | K82: 97.9 | L82: 105.5 | M82: 107.4 | N82: 107.1 | O82: 171.9 | P82: Курганская область
A83: Свердловская область | B83: 99.6 | C83: 106.6 | D83: 106.5 | E83: 111.1 | F83: 99.6 | G83: 116.1 | H83: 111.8 | I83: 95.7 | J83: 90.2 | K83: 99.3 | L83: 110.9 | M83: 104.6 | N83: 100.1 | O83: в 2,7 р. | P83: Свердловская область
A84: Тюменская область | B84: 101 | C84: 109.7 | D84: 111.4 | E84: 108.9 | F84: 101.5 | G84: 99.9 | H84: 99.2 | I84: 93.5 | J84: 85 | K84: 102 | L84: 112.6 | M84: 114 | N84: 101.9 | O84: 123.5 | P84: Тюменская область
A85: в том числе: | P85: в том числе:
A86: Ханты-Мансийский автономный округ | B86: 101.7 | C86: 108.1 | D86: 107.6 | E86: 108.4 | F86: 102.6 | G86: 107.5 | H86: 98.5 | I86: 98.4 | J86: 99.9 | K86: 96 | L86: 108.8 | M86: 109.4 | N86: 103.5 | O86: в 5,3 р. | P86: Ханты-Мансийский автономный
A87: округ – Югра | P87: округ – Югра
A88: Ямало-Ненецкий автономный округ | B88: 100.7 | C88: 113 | D88: 114.5 | E88: 106.6 | F88: 100.2 | G88: 97.1 | H88: 97.1 | I88: 80.7 | J88: 97 | K88: 80.2 | L88: 152.6 | M88: 115.3 | N88: 100.8 | O88: 49.7 | P88: Ямало-Ненецкий автономный округ
A89: Тюменская область без автономных | B89: 100.4 | C89: 109.1 | D89: 114.7 | E89: 112.5 | F89: 101.2 | G89: 85 | H89: 109.2 | I89: 93.5 | J89: 83.5 | K89: 103.6 | L89: 110.7 | M89: 118.5 | N89: 100.6 | O89: 87.3 | P89: Тюменская область без автономных
A90: округов | P90: округов
A91: Челябинская область | B91: 99.7 | C91: 105.9 | D91: 109.6 | E91: 110.4 | F91: 100.3 | G91: 107.8 | H91: 110.9 | I91: 92.3 | J91: 92.8 | K91: 92 | L91: 111.8 | M91: 113.1 | N91: 101.1 | O91: 155.3 | P91: Челябинская область
A92: Сибирский | B92: 99.5 | C92: 106.7 | D92: 109.4 | E92: 109.8 | F92: 102.4 | G92: 103 | H92: 99.4 | I92: 92.4 | J92: 88.3 | K92: 97.4 | L92: 120.7 | M92: 109.4 | O92: 109.9 | P92: Сибирский
A93: федеральный округ | P93: федеральный округ
A94: Республика Алтай | B94: 99.99 | C94: 111.2 | D94: 108.2 | E94: 112.7 | F94: 109.4 | G94: 129.2 | H94: 109.4 | I94: 95.4 | J94: 84.5 | K94: 98.5 | L94: 115.6 | M94: 107.1 | N94: 108.8 | O94: 136.2 | P94: Республика Алтай
A95: Республика Тыва | B95: 100.1 | C95: 110.7 | D95: 113.6 | E95: 104.2 | F95: 108.9 | G95: 103.7 | H95: 97.4 | I95: 96.9 | J95: 96 | K95: 97.1 | L95: 123.7 | M95: 118 | N95: 102.8 | O95: 53.6 | P95: Республика Тыва
A96: Республика Хакасия | B96: 99.6 | C96: 106.5 | D96: 113.7 | E96: 108 | F96: 97.7 | G96: 103 | H96: 105.2 | I96: 100.6 | J96: 113.4 | K96: 94 | L96: 116.1 | M96: 113.5 | N96: 96.2 | O96: 46.8 | P96: Республика Хакасия
A97: Алтайский край | B97: 99.3 | C97: 103.3 | D97: 103.5 | E97: 110.6 | F97: 102.2 | G97: 109.6 | H97: 107.2 | I97: 93.1 | J97: 90.6 | K97: 98.7 | L97: 102.4 | M97: 103 | N97: 96.7 | O97: 112.5 | P97: Алтайский край
A98: Красноярский край | B98: 100 | C98: 110 | D98: 109 | E98: 106.7 | F98: 102.5 | G98: 109.6 | H98: 94.2 | I98: 96.1 | J98: 95.2 | K98: 97.3 | L98: 116.8 | M98: 108.4 | N98: 104.9 | O98: 151.2 | P98: Красноярский край
A99: Иркутская область | B99: 99.4 | C99: 105.3 | D99: 111.2 | E99: 107.6 | F99: 104.3 | G99: 97.6 | H99: 98 | I99: 97.6 | J99: 93.2 | K99: 100.4 | L99: 119.1 | M99: 111.2 | N99: 101.7 | O99: 133.1 | P99: Иркутская область
A100: Кемеровская область | B100: 99.2 | C100: 108.8 | D100: 109.9 | E100: 110.4 | F100: 99.4 | G100: 98 | H100: 98.7 | I100: 86.2 | J100: 75.9 | K100: 99.5 | L100: 114.4 | M100: 110.7 | N100: 99.2 | O100: 50.3 | P100: Кемеровская область
...

Sheet Основные
B1: Площадь | C1: Численность | D1: Средне- | E1: Средне- | F1: Потреби- | G1: Средне- | H1: Валовой | J1: Инвестиции | K1: Основные | L1: Объем отгруженных товаров собственного производства, выполненных работ и услуг собственными силами по видам экономической деятельности, | P1: Продукция | Q1: в том числе | S1: Ввод | T1: Оборот | U1: Сальдированный финансовый результат (прибыль минус убыток) деятельности организа-
B2: территории1), | C2: населения | D2: годовая численность | E2: душевые денежные доходы | F2: тельские расходы | G2: месячная | H2: региональ- | J2: в основной | K2: фонды | L2: млрд руб. | P2: сельского | S2: в действие | T2: розничной | U2: ций4),
B3: тыс. км2 | C3: на 1 января | D3: занятых, | E3: (в месяц), руб. | F3: в среднем | G3: номиналь- | H3: ный | J3: капитал2), | K3: в экономике | P3: хозяйства - | S3: жилых домов, | T3: торговли, | U3: млрд руб.
C4: 2024 г., | D4: тыс. человек | F4: на душу населения | G4: ная начис- | H4: продукт | J4: млрд руб. | K4: (по полной учетной стоимости; | P4: всего, | S4: тыс. м2 | T4: млрд руб.
C5: тыс. человек | F5: (в месяц), руб. | G5: ленная | H5: в 2022 г. , | K5: на конец года)3), | P5: млрд руб. | S5: общей
G6: заработная плата работников организаций, руб. | H6: млрд руб. | K6: млрд руб. | S6: площади
S7: жилых
L8: добыча | M8: обрабаты- | N8: обеспечение электрической энергией, газом | O8: водоснабжение; водоотведение, организация сбора и утилизации отходов, деятельность по ликвидации загрязнений | Q8: растение- | R8: животно- | S8: помещений
L9: полезных | M9: вающие производства | N9: и паром; кондиционирование воздуха | Q9: водства | R9: водства
L10: ископаемых
A11: Российская Федерация | B11: 17234 | C11: 146150.8 | D11: 72911.8 | E11: 53579 | F11: 41231 | G11: 74854 | H11: 140669 | I11: =H11/C11*1000*1000 -> 962492.17 | J11: 34 036,35) | K11: 460370 | L11: 28085.8 | M11: 74573.8 | N11: 7506.2 | O11: 2078.5 | P11: 8493.6 | Q11: 4709.4 | R11: 3784.2 | S11: 110438.5 | T11: 48155.7 | U11: 35378535 | V11: Российская Федерация
A12: Центральный | B12: 650.2 | C12: 40198.7 | D12: 21537.9 | E12: 71 914 | F12: 51422 | G12: 94239 | H12: 47367 | I12: =H12/C12*1000*1000 -> 1178321.7 | J12: 10731.3 | K12: 161573 | L12: 693.6 | M12: 26707.1 | N12: 2268.8 | O12: 687.9 | P12: 2356.1 | Q12: 1311 | R12: 1045.1 | S12: 32964.1 | T12: 15842.3 | U12: 14885140 | V12: Центральный
A13: федеральный округ | I13: =H13/C13*1000*1000 -> #DIV/0! | V13: федеральный округ
A14: Белгородская область | B14: 27.1 | C14: 1500.7 | D14: 765.3 | E14: 47257 | F14: 35281 | G14: 54495 | H14: 1311 | I14: =H14/C14*1000*1000 -> 873592.32 | J14: 212.2 | K14: 3473 | L14: 229.9 | M14: 1101.9 | N14: 32.7 | O14: 14.9 | P14: 350.3 | Q14: 133.4 | R14: 216.9 | S14: 959.2 | T14: 455.8 | U14: 343530 | V14: Белгородская область
A15: Брянская область | B15: 34.9 | C15: 1142.4 | D15: 504.5 | E15: 40927 | F15: 32470 | G15: 48080 | H15: 549 | I15: =H15/C15*1000*1000 -> 480567.23 | J15: 94.1 | K15: 2025 | L15: 0.2 | M15: 454.1 | N15: 22.9 | O15: 12.3 | P15: 148.1 | Q15: 74.7 | R15: 73.4 | S15: 568.6 | T15: 341.6 | U15: 69640 | V15: Брянская область
A16: Владимирская область | B16: 29.1 | C16: 1309.9 | D16: 639 | E16: 38649 | F16: 29346 | G16: 53286 | H16: 781 | I16: =H16/C16*1000*1000 -> 596228.72 | J16: 181.7 | K16: 2261 | L16: 11.1 | M16: 859.1 | N16: 47.3 | O16: 16.5 | P16: 46 | Q16: 17.4 | R16: 28.6 | S16: 1145.4 | T16: 331.1 | U16: 115169 | V16: Владимирская область
A17: Воронежская область | B17: 52.2 | C17: 2273.4 | D17: 1151.6 | E17: 45087 | F17: 37678 | G17: 53332 | H17: 1378 | I17: =H17/C17*1000*1000 -> 606140.58 | J17: 374.1 | K17: 5141 | L17: 12.7 | M17: 870.8 | N17: 147.6 | O17: 25.7 | P17: 356.5 | Q17: 224 | R17: 132.5 | S17: 2014.5 | T17: 792.1 | U17: 151186 | V17: Воронежская область
A18: Ивановская область | B18: 21.4 | C18: 905.9 | D18: 422.2 | E18: 41108 | F18: 31683 | G18: 41929 | H18: 364 | I18: =H18/C18*1000*1000 -> 401810.35 | J18: 67.5 | K18: 1250 | L18: 1.8 | M18: 324.1 | N18: 28.3 | O18: 9.6 | P18: 27.2 | Q18: 11.2 | R18: 16 | S18: 511.9 | T18: 258.8 | U18: 28573 | V18: Ивановская область
A19: Калужская область | B19: 29.8 | C19: 1068.4 | D19: 536.9 | E19: 44564 | F19: 31984 | G19: 61588 | H19: 694 | I19: =H19/C19*1000*1000 -> 649569.45 | J19: 125.7 | K19: 2812 | L19: 5.1 | M19: 924.2 | N19: 31.3 | O19: 14.6 | P19: 83.4 | Q19: 37.7 | R19: 45.7 | S19: 1118.7 | T19: 280.8 | U19: 4990 | V19: Калужская область
A20: Костромская область | B20: 60.2 | C20: 566.3 | D20: 257.3 | E20: 43668 | F20: 33526 | G20: 46730 | H20: 276 | I20: =H20/C20*1000*1000 -> 487374.18 | J20: 47.9 | K20: 1061 | L20: 1 | M20: 237.6 | N20: 48.4 | O20: 4.7 | P20: 24.6 | Q20: 8.1 | R20: 16.5 | S20: 360.4 | T20: 167.7 | U20: 18604 | V20: Костромская область
A21: Курская область | B21: 30 | C21: 1060.9 | D21: 502.6 | E21: 43719 | F21: 31887 | G21: 53624 | H21: 666 | I21: =H21/C21*1000*1000 -> 627768.88 | J21: 231.2 | K21: 2415 | L21: 102.4 | M21: 457.1 | N21: 67.5 | O21: 9.4 | P21: 240 | Q21: 148.3 | R21: 91.7 | S21: 619.5 | T21: 304.5 | U21: 108944 | V21: Курская область
A22: Липецкая область | B22: 24 | C22: 1116.3 | D22: 565.7 | E22: 45458 | F22: 35308 | G22: 54044 | H22: 793 | I22: =H22/C22*1000*1000 -> 710382.51 | J22: 187.2 | K22: 2585 | L22: 7.5 | M22: 1233.7 | N22: 31.8 | O22: 21.7 | P22: 199.1 | Q22: 138.3 | R22: 60.8 | S22: 770.9 | T22: 350.1 | U22: 358586 | V22: Липецкая область
A23: Московская область | B23: 44.3 | C23: 8651.3 | D23: 3991.8 | E23: 64870 | F23: 50139 | G23: 83195 | H23: 7721 | I23: =H23/C23*1000*1000 -> 892467.03 | J23: 1593.5 | K23: 34218 | L23: 23.3 | M23: 5275.2 | N23: 402.6 | O23: 194.5 | P23: 158 | Q23: 92 | R23: 66 | S23: 12485.7 | T23: 3824 | U23: 1707059 | V23: Московская область
A24: Орловская область | B24: 24.7 | C24: 692.5 | D24: 301.5 | E24: 43730 | F24: 30887 | G24: 47382 | H24: 370 | I24: =H24/C24*1000*1000 -> 534296.03 | J24: 58.4 | K24: 1229 | L24: 0.4 | M24: 227.2 | N24: 17.5 | O24: 7.4 | P24: 138.7 | Q24: 96.2 | R24: 42.5 | S24: 374.4 | T24: 190.4 | U24: 58286 | V24: Орловская область
A25: Рязанская область | B25: 39.6 | C25: 1082.2 | D25: 499.7 | E25: 39905 | F25: 30904 | G25: 53270 | H25: 619 | I25: =H25/C25*1000*1000 -> 571983 | J25: 101.3 | K25: 2725 | L25: 2.2 | M25: 564.5 | N25: 58.7 | O25: 14.3 | P25: 110.6 | Q25: 62.4 | R25: 48.2 | S25: 787.6 | T25: 294.4 | U25: 78787 | V25: Рязанская область
... A31: г. Москва | B31: 2.6 | C31: 13149.8 | D31: 8617.1 | E31: 117103 | F31: 78051 | G31: 138882 | H31: 28507 | I31: =H31/C31*1000*1000 -> 2167865.7 | J31: 6757.2 | K31: 87411 | L31: 271.3 | M31: 10810.2 | N31: 1000.6 | O31: 275.8 | P31: 4.3 | Q31: 4.1 | R31: 0.2 | S31: 7342.5 | T31: 6617.4 | U31: 11348045 | V31: г. Москва
A32: Северо-Западный | B32: 1687 | C32: 13840.4 | D32: 7221.2 | E32: 58 669 | F32: 47100 | G32: 81442 | H32: 18929 | I32: =H32/C32*1000*1000 -> 1367662.8 | J32: 3074.2 | K32: 58713 | L32: 2078.4 | M32: 10925.8 | N32: 886.1 | O32: 228.9 | P32: 371.9 | Q32: 119.5 | R32: 252.4 | S32: 11440.3 | T32: 5155.1 | U32: 5455390 | V32: Северо-Западный
A33: федеральный округ | I33: =H33/C33*1000*1000 -> #DIV/0! | V33: федеральный округ
A34: Республика Карелия | B34: 180.5 | C34: 523.9 | D34: 235.1 | E34: 53068 | F34: 43443 | G34: 64779 | H34: 391 | I34: =H34/C34*1000*1000 -> 746325.63 | J34: 103.6 | K34: 1400 | L34: 103.9 | M34: 149.3 | N34: 35.4 | O34: 5.9 | P34: 6.5 | Q34: 3.2 | R34: 3.3 | S34: 312.4 | T34: 185.3 | U34: 35405 | V34: Республика Карелия
A35: Республика Коми | B35: 416.8 | C35: 720.6 | D35: 335.6 | E35: 56152 | F35: 39531 | G35: 77601 | H35: 976 | I35: =H35/C35*1000*1000 -> 1354426.9 | J35: 128.6 | K35: 4726 | L35: 639.1 | M35: 202.5 | N35: 51.1 | O35: 11.4 | P35: 12.9 | Q35: 4.7 | R35: 8.2 | S35: 217.1 | T35: 208.3 | U35: 51572 | V35: Республика Коми
A36: Архангельская область | B36: 589.9 | C36: 998.1 | D36: 460.5 | E36: 58967 | F36: 43146 | G36: 76368 | H36: 1188 | I36: =H36/C36*1000*1000 -> 1190261.5 | J36: 206 | K36: 4133 | L36: 603.9 | M36: 405.8 | N36: 50.9 | O36: 10.1 | P36: 14.4 | Q36: 6.2 | R36: 8.2 | S36: 462.3 | T36: 361.7 | U36: 60634 | V36: Архангельская область
A37: в том числе: | I37: =H37/C37*1000*1000 -> #DIV/0! | V37: в том числе:
A38: Ненецкий автономный округ | B38: 176.8 | C38: 42.2 | D38: 30.7 | E38: 128204 | F38: 42804 | G38: 119386 | H38: 488 | I38: =H38/C38*1000*1000 -> 11563981 | J38: 86.3 | K38: 1235 | L38: 556.1 | M38: 2.7 | N38: 5.8 | O38: 0.8 | P38: 1.3 | Q38: 0.1 | R38: 1.2 | S38: 21.7 | T38: 12.8 | U38: 9514 | V38: Ненецкий автономный
A39: округ | I39: =H39/C39*1000*1000 -> #DIV/0! | V39: округ
A40: Архангельская область без автономного округа | B40: 413.1 | C40: 955.9 | D40: 429.8 | E40: 55 952 | F40: 43161 | G40: 72540 | H40: 700 | I40: =H40/C40*1000*1000 -> 732294.17 | J40: 119.7 | K40: 2898 | L40: 47.7 | M40: 403.1 | N40: 45.1 | O40: 9.4 | P40: 13.1 | Q40: 6.1 | R40: 7 | S40: 440.6 | T40: 348.9 | U40: 51120 | V40: Архангельская область
A41: без автономного округа | I41: =H41/C41*1000*1000 -> #DIV/0! | V41: без автономного округа
A42: Вологодская область | B42: 144.5 | C42: 1121.4 | D42: 503.2 | E42: 42708 | F42: 31167 | G42: 58939 | H42: 1024 | I42: =H42/C42*1000*1000 -> 913144.28 | J42: 168.8 | K42: 3592 | L42: 0.8 | M42: 1195 | N42: 45.1 | O42: 14.7 | P42: 47.8 | Q42: 13.2 | R42: 34.6 | S42: 746 | T42: 274.5 | U42: 622017 | V42: Вологодская область
A43: Калининградская область | B43: 15.1 | C43: 1033.9 | D43: 519.3 | E43: 43543 | F43: 36496 | G43: 54739 | H43: 738 | I43: =H43/C43*1000*1000 -> 713802.11 | J43: 196 | K43: 2740 | L43: 19.8 | M43: 502.5 | N43: 64.2 | O43: 8.7 | P43: 63.1 | Q43: 35.3 | R43: 27.8 | S43: 1216.7 | T43: 283.8 | U43: 944071 | V43: Калининградская область
A44: Ленинградская область | B44: 83.9 | C44: 2035.8 | D44: 901.5 | E44: 45989 | F44: 38583 | G44: 68105 | H44: 1658 | I44: =H44/C44*1000*1000 -> 814421.85 | J44: 685.6 | K44: 10121 | L44: 43.7 | M44: 1767 | N44: 196.5 | O44: 31.9 | P44: 130.5 | Q44: 35.3 | R44: 95.2 | S44: 4186.4 | T44: 738.2 | U44: 460864 | V44: Ленинградская область
A45: Мурманская область | B45: 144.9 | C45: 656.4 | D45: 313.2 | E45: 75786 | F45: 51217 | G45: 98818 | H45: 1149 | I45: =H45/C45*1000*1000 -> 1750457 | J45: 266.9 | K45: 3570 | L45: 213.6 | M45: 845.4 | N45: 74.9 | O45: 11.2 | P45: 2.7 | Q45: 0.4 | R45: 2.3 | S45: 60.7 | T45: 235.3 | U45: 297051 | V45: Мурманская область
A46: Новгородская область | B46: 54.5 | C46: 571.4 | D46: 273.8 | E46: 38903 | F46: 32064 | G46: 53188 | H46: 381 | I46: =H46/C46*1000*1000 -> 666783.34 | J46: 75.5 | K46: 1545 | L46: 1.8 | M46: 331.7 | N46: 23.2 | O46: 5.1 | P46: 35.7 | Q46: 12.3 | R46: 23.4 | S46: 377 | T46: 164.5 | U46: 65900 | V46: Новгородская область
A47: Псковская область | B47: 55.4 | C47: 581.1 | D47: 285.2 | E47: 39898 | F47: 32386 | G47: 44853 | H47: 258 | I47: =H47/C47*1000*1000 -> 443985.54 | J47: 47.6 | K47: 952 | L47: 2.2 | M47: 186.1 | N47: 14.7 | O47: 9.1 | P47: 58.4 | Q47: 8.9 | R47: 49.5 | S47: 379 | T47: 173.7 | U47: 29718 | V47: Псковская область
A48: г. Санкт-Петербург | B48: 1.4 | C48: 5597.8 | D48: 3393.9 | E48: 72037 | F48: 59969 | G48: 96232 | H48: 11166 | I48: =H48/C48*1000*1000 -> 1994712.2 | J48: 1195.6 | K48: 25934 | L48: 449.6 | M48: 5340.6 | N48: 330.1 | O48: 120.8 | P48: – | Q48: – | R48: – | S48: 3482.7 | T48: 2529.8 | U48: 2888158 | V48: г. Санкт-Петербург
A49: Южный | B49: 447.8 | C49: 16624.1 | D49: 8057.6 | E49: 45 063 | F49: 41457 | G49: 53432 | H49: 9815 | I49: =H49/C49*1000*1000 -> 590407.9 | J49: 2284 | K49: 37708 | L49: 574.7 | M49: 4297.2 | N49: 580.6 | O49: 143.6 | P49: 1498.2 | Q49: 1063 | R49: 435.2 | S49: 14592.9 | T49: 5621.7 | U49: 1579603 | V49: Южный
A50: федеральный округ | I50: =H50/C50*1000*1000 -> #DIV/0! | V50: федеральный округ
A51: Республика Адыгея | B51: 7.8 | C51: 500.6 | D51: 156.7 | E51: 42684 | F51: 36734 | G51: 46431 | H51: 197 | I51: =H51/C51*1000*1000 -> 393527.77 | J51: 61.6 | K51: 610 | L51: 2.7 | M51: 88.1 | N51: 12.2 | O51: 2.9 | P51: 35.5 | Q51: 20.5 | R51: 15 | S51: 564 | T51: 165.4 | U51: 7640 | V51: Республика Адыгея
A52: Республика Калмыкия | B52: 74.7 | C52: 266.8 | D52: 111.9 | E52: 28635 | F52: 26174 | G52: 42151 | H52: 119 | I52: =H52/C52*1000*1000 -> 446026.99 | J52: 13.8 | K52: 355 | L52: …6) | M52: 1.2 | N52: 15.9 | O52: …6) | P52: 29.1 | Q52: 11.2 | R52: 17.9 | S52: 142 | T52: 59.8 | U52: 2073 | V52: Республика Калмыкия
A53: Республика Крым | B53: 26.1 | C53: 1909.5 | D53: 890.6 | E53: 32875 | F53: 27509 | G53: 47325 | H53: 656 | I53: =H53/C53*1000*1000 -> 343545.43 | J53: 271.3 | K53: 4360 | L53: 6 | M53: 145.7 | N53: 49.9 | O53: 9.9 | P53: 81.7 | Q53: 53.9 | R53: 27.8 | S53: 1219.6 | T53: 408.9 | U53: 2784 | V53: Республика Крым
A54: Краснодарский край | B54: 75.5 | C54: 5833 | D54: 2908 | E54: 54627 | F54: 54117 | G54: 58256 | H54: 4304 | I54: =H54/C54*1000*1000 -> 737870.74 | J54: 860.6 | K54: 16105 | L54: 48.3 | M54: 1607.4 | N54: 145.9 | O54: 50.8 | P54: 584.8 | Q54: 431.6 | R54: 153.2 | S54: 7640.4 | T54: 2537.5 | U54: 936138 | V54: Краснодарский край
A55: Астраханская область | B55: 49 | C55: 946.4 | D55: 466.8 | E55: 36593 | F55: 29728 | G55: 53964 | H55: 765 | I55: =H55/C55*1000*1000 -> 808326.29 | J55: 87.5 | K55: 2434 | L55: 423.2 | M55: 117 | N55: 48.4 | O55: 7.9 | P55: 71.5 | Q55: 44.2 | R55: 27.3 | S55: 632.1 | T55: 221.1 | U55: 189243 | V55: Астраханская область
A56: Волгоградская область | B56: 112.9 | C56: 2453.9 | D56: 1180.1 | E56: 35575 | F56: 31067 | G56: 51833 | H56: 1218 | I56: =H56/C56*1000*1000 -> 496352.74 | J56: 291.4 | K56: 4619 | L56: 39.9 | M56: 815.8 | N56: 87.2 | O56: 23.4 | P56: 237.5 | Q56: 177.6 | R56: 59.9 | S56: 951.1 | T56: 619.6 | U56: 129372 | V56: Волгоградская область
A57: Ростовская область | B57: 101 | C57: 4152.5 | D57: 2092.1 | E57: 46840 | F57: 41526 | G57: 52100 | H57: 2326 | I57: =H57/C57*1000*1000 -> 560144.49 | J57: 643.7 | K57: 8281 | L57: 50.2 | M57: 1494.6 | N57: 207.4 | O57: 43.3 | P57: 453.9 | Q57: 320 | R57: 133.9 | S57: 2963.4 | T57: 1506 | U57: 311222 | V57: Ростовская область
A58: г. Севастополь | B58: 0.9 | C58: 561.4 | D58: 251.4 | E58: 39968 | F58: 33896 | G58: 47638 | H58: 230 | I58: =H58/C58*1000*1000 -> 409690.06 | J58: 54 | K58: 944 | L58: …6) | M58: 27.5 | N58: 13.8 | O58: …6) | P58: 4.2 | Q58: 3.9 | R58: 0.3 | S58: 480.3 | T58: 103.3 | U58: 1131 | V58: г. Севастополь
A59: Северо-Кавказский | B59: 170.4 | C59: 10251.1 | D59: 4190.5 | E59: 35 426 | F59: 28816 | G59: 42091 | H59: 3111 | I59: =H59/C59*1000*1000 -> 303479.63 | J59: 1012.7 | K59: 8744 | L59: 47.5 | M59: 726.8 | N59: 208.2 | O59: 35 | P59: 786 | Q59: 451.6 | R59: 334.4 | S59: 7364.1 | T59: 2405.9 | U59: 116293 | V59: Северо-Кавказский
A60: федеральный округ | I60: =H60/C60*1000*1000 -> #DIV/0! | V60: федеральный округ
A61: Республика Дагестан | B61: 50.3 | C61: 3232.2 | D61: 1230.2 | E61: 39686 | F61: 32046 | G61: 39054 | H61: 913 | I61: =H61/C61*1000*1000 -> 282470.14 | J61: 350.6 | K61: 1853 | L61: 4.8 | M61: 56.9 | N61: 20.4 | O61: 2.8 | P61: 222.9 | Q61: 106.4 | R61: 116.5 | S61: 1617.4 | T61: 827.2 | U61: -11989 | V61: Республика Дагестан
A62: Республика Ингушетия | B62: 3.1 | C62: 527.2 | D62: 198.6 | E62: 24414 | F62: 14491 | G62: 35825 | H62: 82 | I62: =H62/C62*1000*1000 -> 155538.69 | J62: 23.2 | K62: 281 | L62: 1.7 | M62: 6.3 | N62: 0.6 | O62: 0.7 | P62: 22.1 | Q62: 8.1 | R62: 14 | S62: 162.6 | T62: 48.6 | U62: -1889 | V62: Республика Ингушетия
A63: Кабардино-Балкарская Республика | B63: 12.5 | C63: 905.5 | D63: 386 | E63: 38948 | F63: 33021 | G63: 39988 | H63: 259 | I63: =H63/C63*1000*1000 -> 286029.82 | J63: 68.3 | K63: 666 | L63: 0.5 | M63: 43.9 | N63: 14 | O63: 2.6 | P63: 96 | Q63: 55.5 | R63: 40.5 | S63: 559.3 | T63: 283.3 | U63: -2044 | V63: Кабардино-Балкарская
A64: Республика | I64: =H64/C64*1000*1000 -> #DIV/0! | V64: Республика
A65: Карачаево-Черкесская Республика | B65: 14.3 | C65: 468.3 | D65: 188 | E65: 25619 | F65: 17547 | G65: 40388 | H65: 126 | I65: =H65/C65*1000*1000 -> 269058.3 | J65: 28.9 | K65: 550 | L65: 4.6 | M65: 48.5 | N65: 14.1 | O65: 2.5 | P65: 43.6 | Q65: 18.2 | R65: 25.4 | S65: 419.9 | T65: 53.1 | U65: -6383 | V65: Карачаево-Черкесская
A66: Республика | I66: =H66/C66*1000*1000 -> #DIV/0! | V66: Республика
A67: Республика Северная Осетия | B67: 8 | C67: 678.9 | D67: 274.2 | E67: 35276 | F67: 26999 | G67: 41059 | H67: 216 | I67: =H67/C67*1000*1000 -> 318161.73 | J67: 43.5 | K67: 462 | L67: 2.2 | M67: 41.5 | N67: 18.1 | O67: 3.5 | P67: 56.7 | Q67: 32 | R67: 24.7 | S67: 481.5 | T67: 167.3 | U67: -94 | V67: Республика Северная
A68: Осетия - Алания | I68: =H68/C68*1000*1000 -> #DIV/0! | V68: Осетия - Алания
A69: Чеченская Республика | B69: 16.2 | C69: 1552.9 | D69: 569.2 | E69: 35920 | F69: 25262 | G69: 37589 | H69: 315 | I69: =H69/C69*1000*1000 -> 202846.29 | J69: 163.4 | K69: 1074 | L69: 5 | M69: 23.7 | N69: 37.6 | O69: 2.8 | P69: 56.7 | Q69: 23.9 | R69: 32.8 | S69: 2331.5 | T69: 283.9 | U69: -28848 | V69: Чеченская Республика
A70: Ставропольский край | B70: 66.2 | C70: 2886.1 | D70: 1344.4 | E70: 32930 | F70: 30648 | G70: 47054 | H70: 1200 | I70: =H70/C70*1000*1000 -> 415786.01 | J70: 334.7 | K70: 3858 | L70: 28.8 | M70: 505.9 | N70: 103.2 | O70: 20 | P70: 287.9 | Q70: 207.4 | R70: 80.5 | S70: 1791.9 | T70: 742.6 | U70: 167540 | V70: Ставропольский край
A71: Приволжский | B71: 1037 | C71: 28540.8 | D71: 13695.9 | E71: 41 765 | F71: 33869 | G71: 55724 | H71: 19665 | I71: =H71/C71*1000*1000 -> 689013.62 | J71: 4830.2 | K71: 63014 | L71: 4134.3 | M71: 14288.6 | N71: 1232.4 | O71: 379.2 | P71: 1937.2 | Q71: 1003 | R71: 934.2 | S71: 20158.3 | T71: 8287.9 | U71: 3763171 | V71: Приволжский
A72: федеральный округ | I72: =H72/C72*1000*1000 -> #DIV/0! | V72: федеральный округ
A73: Республика Башкортостан | B73: 142.9 | C73: 4064.3 | D73: 1730 | E73: 40022 | F73: 35226 | G73: 56974 | H73: 2243 | I73: =H73/C73*1000*1000 -> 551878.55 | J73: 620 | K73: 8198 | L73: 442.4 | M73: 1748.9 | N73: 181.5 | O73: 31.2 | P73: 227.5 | Q73: 99.1 | R73: 128.4 | S73: 3315.5 | T73: 1278.4 | U73: 425856 | V73: Республика Башкортостан
A74: Республика Марий Эл | B74: 23.4 | C74: 669.8 | D74: 280.7 | E74: 31013 | F74: 23518 | G74: 48997 | H74: 262 | I74: =H74/C74*1000*1000 -> 391161.54 | J74: 52.2 | K74: 1038 | L74: 0.7 | M74: 248.3 | N74: 14.6 | O74: 6 | P74: 57.9 | Q74: 17 | R74: 40.9 | S74: 536.5 | T74: 134.6 | U74: 38808 | V74: Республика Марий Эл
A75: Республика Мордовия | B75: 26.1 | C75: 765.9 | D75: 369.3 | E75: 30647 | F75: 26730 | G75: 46406 | H75: 343 | I75: =H75/C75*1000*1000 -> 447839.14 | J75: 74.1 | K75: 1267 | L75: 0.3 | M75: 371.3 | N75: 14.1 | O75: 4.4 | P75: 117.8 | Q75: 47.4 | R75: 70.4 | S75: 360.3 | T75: 185.4 | U75: 58994 | V75: Республика Мордовия
A76: Республика Татарстан | B76: 67.8 | C76: 4003 | D76: 2036.5 | E76: 52524 | F76: 42009 | G76: 61894 | H76: 4179 | I76: =H76/C76*1000*1000 -> 1043967 | J76: 1180.4 | K76: 11075 | L76: 1159.7 | M76: 3509.7 | N76: 175.6 | O76: 62.3 | P76: 289.7 | Q76: 127.2 | R76: 162.5 | S76: 3436.5 | T76: 1400.3 | U76: 1320174 | V76: Республика Татарстан
A77: Удмуртская Республика | B77: 42.1 | C77: 1434.6 | D77: 681.5 | E77: 38939 | F77: 29170 | G77: 53721 | H77: 966 | I77: =H77/C77*1000*1000 -> 673358.43 | J77: 166.3 | K77: 2893 | L77: 353.5 | M77: 592.2 | N77: 49.6 | O77: 15.3 | P77: 88.7 | Q77: 24.4 | R77: 64.3 | S77: 1389.6 | T77: 338.6 | U77: 89894 | V77: Удмуртская Республика
A78: Чувашская Республика | B78: 18.3 | C78: 1167.1 | D78: 508.7 | E78: 34129 | F78: 25976 | G78: 50263 | H78: 501 | I78: =H78/C78*1000*1000 -> 429269.13 | J78: 123.4 | K78: 1741 | L78: 1 | M78: 402.9 | N78: 30.6 | O78: 8.3 | P78: 63.4 | Q78: 36.2 | R78: 27.2 | S78: 780.7 | T78: 258.3 | U78: 68639 | V78: Чувашская Республика
A79: Пермский край | B79: 160.2 | C79: 2495.3 | D79: 1145.6 | E79: 45639 | F79: 35068 | G79: 62393 | H79: 2003 | I79: =H79/C79*1000*1000 -> 802709.09 | J79: 481.4 | K79: 7527 | L79: 633.3 | M79: 1385.9 | N79: 145.4 | O79: 39.8 | P79: 62.7 | Q79: 20.3 | R79: 42.4 | S79: 1927.7 | T79: 702.7 | U79: 320610 | V79: Пермский край
A80: Кировская область | B80: 120.4 | C80: 1129.9 | D80: 530 | E80: 38277 | F80: 30119 | G80: 48258 | H80: 555 | I80: =H80/C80*1000*1000 -> 491193.91 | J80: 106.2 | K80: 1790 | L80: 1.6 | M80: 410 | N80: 47.2 | O80: 10.9 | P80: 62.4 | Q80: 17.3 | R80: 45.1 | S80: 595.7 | T80: 282.9 | U80: 37338 | V80: Кировская область
A81: Нижегородская область | B81: 76.6 | C81: 3060.3 | D81: 1660.5 | E81: 50601 | F81: 40630 | G81: 56526 | H81: 2288 | I81: =H81/C81*1000*1000 -> 747639.12 | J81: 686.9 | K81: 7783 | L81: 6 | M81: 1935.5 | N81: 133.9 | O81: 57.7 | P81: 126.1 | Q81: 61.9 | R81: 64.2 | S81: 1859.4 | T81: 1093.8 | U81: 557444 | V81: Нижегородская область
A82: Оренбургская область | B82: 123.7 | C82: 1828.7 | D82: 848.3 | E82: 36756 | F82: 28738 | G82: 53119 | H82: 1571 | I82: =H82/C82*1000*1000 -> 859080.22 | J82: 293.4 | K82: 4052 | L82: 859.1 | M82: 546.9 | N82: 93.6 | O82: 28.1 | P82: 178.3 | Q82: 107.4 | R82: 70.9 | S82: 1129.8 | T82: 464.9 | U82: 156714 | V82: Оренбургская область
A83: Пензенская область | B83: 43.4 | C83: 1236.1 | D83: 580.5 | E83: 36429 | F83: 29428 | G83: 48167 | H83: 593 | I83: =H83/C83*1000*1000 -> 479734.65 | J83: 121.8 | K83: 2318 | L83: 3.5 | M83: 398.1 | N83: 26.3 | O83: 8.9 | P83: 162.4 | Q83: 86.1 | R83: 76.3 | S83: 938.7 | T83: 314.1 | U83: 59520 | V83: Пензенская область
A84: Самарская область | B84: 53.6 | C84: 3127.8 | D84: 1646.3 | E84: 42701 | F84: 36303 | G84: 58063 | H84: 2378 | I84: =H84/C84*1000*1000 -> 760278.79 | J84: 516.6 | K84: 7869 | L84: 588.3 | M84: 1572.4 | N84: 142 | O84: 75.4 | P84: 159.2 | Q84: 107.7 | R84: 51.5 | S84: 1938.2 | T84: 990.6 | U84: 505525 | V84: Самарская область
... A87: Уральский | B87: 1818.5 | C87: 12262.3 | D87: 6448.6 | E87: 53489 | F87: 39323 | G87: 77889 | H87: 20073 | I87: =H87/C87*1000*1000 -> 1636968.6 | J87: 4594.2 | K87: 66104 | L87: 12746.2 | M87: 9433.8 | N87: 896.3 | O87: 279.8 | P87: 410.1 | Q87: 179.5 | R87: 230.6 | S87: 9435.7 | T87: 3814.3 | U87: 4850097 | V87: Уральский
A88: федеральный округ | I88: =H88/C88*1000*1000 -> #DIV/0! | V88: федеральный округ
A89: Курганская область | B89: 71.5 | C89: 753 | D89: 308.6 | E89: 34812 | F89: 26094 | G89: 50938 | H89: 340 | I89: =H89/C89*1000*1000 -> 451527.22 | J89: 71.2 | K89: 1353 | L89: 4.6 | M89: 254.9 | N89: 24.4 | O89: 7.3 | P89: 50.4 | Q89: 32.1 | R89: 18.3 | S89: 351.6 | T89: 165.4 | U89: 31728 | V89: Курганская область
A90: Свердловская область | B90: 194.2 | C90: 4222.7 | D90: 2095.2 | E90: 53413 | F90: 42728 | G90: 64997 | H90: 3469 | I90: =H90/C90*1000*1000 -> 821512.3 | J90: 720.4 | K90: 12468 | L90: 137.4 | M90: 3392 | N90: 306.5 | O90: 135 | P90: 114.3 | Q90: 40.7 | R90: 73.6 | S90: 3262.1 | T90: 1426.1 | U90: 686831 | V90: Свердловская область
A91: Тюменская область | B91: 1464.2 | C91: 3890.8 | D91: 2258.6 | E91: 69341 | F91: 44894 | G91: 105981 | H91: 13964 | I91: =H91/C91*1000*1000 -> 3588979.1 | J91: 3356.6 | K91: 45296 | L91: 12358.1 | M91: 3318.6 | N91: 404.2 | O91: 79.7 | P91: 115.6 | Q91: 49.8 | R91: 65.8 | S91: 3730.8 | T91: 1329.1 | U91: 3682667 | V91: Тюменская область
A92: в том числе: | I92: =H92/C92*1000*1000 -> #DIV/0! | V92: в том числе:
A93: Ханты-Мансийский автономный округ | B93: 534.8 | C93: 1759.4 | D93: 1101.9 | E93: 72 634 | F93: 43555 | G93: 108148 | H93: 6895 | I93: =H93/C93*1000*1000 -> 3918949.6 | J93: 1552.8 | K93: 20175 | L93: 7641.2 | M93: 1016.5 | N93: 262.5 | O93: 35.5 | P93: 9.9 | Q93: 5.8 | R93: 4.1 | S93: 955.3 | T93: 557.6 | U93: 2269961 | V93: Ханты-Мансийский
A94: автономный округ – Югра | I94: =H94/C94*1000*1000 -> #DIV/0! | V94: автономный округ – Югра
A95: Ямало-Ненецкий автономный округ | B95: 769.3 | C95: 516 | D95: 409.2 | E95: 139651 | F95: 56231 | G95: 145050 | H95: 5350 | I95: =H95/C95*1000*1000 -> 10368217 | J95: 1474.2 | K95: 20021 | L95: 4430.6 | M95: 949.1 | N95: 66.2 | O95: 13.7 | P95: 3.1 | Q95: 0.1 | R95: 3 | S95: 290 | T95: 205.3 | U95: 1077517 | V95: Ямало-Ненецкий
A96: автономный округ | I96: =H96/C96*1000*1000 -> #DIV/0! | V96: автономный округ
A97: Тюменская область без автономных округов | B97: 160.1 | C97: 1615.4 | D97: 747.4 | E97: 43350 | F97: 42728 | G97: 71184 | H97: 1720 | I97: =H97/C97*1000*1000 -> 1064751.8 | J97: 329.5 | K97: 5100 | L97: 286.3 | M97: 1353 | N97: 75.5 | O97: 30.6 | Q97: 43.9 | R97: 58.7 | S97: 2485.5 | T97: 566.1 | U97: 335189 | V97: Тюменская область
A98: без автономных округов | I98: =H98/C98*1000*1000 -> #DIV/0! | V98: без автономных округов
A99: Челябинская область | B99: 88.6 | C99: 3395.8 | D99: 1786.3 | E99: 39703 | F99: 31694 | G99: 58424 | H99: 2300 | I99: =H99/C99*1000*1000 -> 677307.26 | J99: 446.1 | K99: 6987 | L99: 246.1 | M99: 2468.3 | N99: 161.2 | O99: 57.8 | P99: 129.8 | Q99: 56.9 | R99: 72.9 | S99: 2091.2 | T99: 893.9 | U99: 448871 | V99: Челябинская область
A100: Сибирский | B100: 4361.7 | C100: 16567.1 | D100: 7795.2 | E100: 42991 | F100: 32798 | G100: 66423 | H100: 13054 | I100: =H100/C100*1000*1000 -> 787947.2 | J100: 3302.6 | K100: 34778 | L100: 4115.1 | M100: 6271.2 | N100: 899.6 | O100: 247.9 | P100: 831.4 | Q100: 413 | R100: 418.4 | S100: 10001.4 | T100: 4370.2 | U100: 2641156 | V100: Сибирский
A101: федеральный округ | I101: =H101/C101*1000*1000 -> #DIV/0! | V101: федеральный округ
A102: Республика Алтай | B102: 92.9 | C102: 210.8 | D102: 80.5 | E102: 34817 | F102: 26868 | G102: 52450 | H102: 92 | I102: =H102/C102*1000*1000 -> 436432.64 | J102: 48.7 | K102: 272 | L102: 1.7 | M102: 6.7 | N102: 7.5 | O102: 0.7 | P102: 13.5 | Q102: 3 | R102: 10.5 | S102: 190.4 | T102: 47.8 | U102: 64928 | V102: Республика Алтай
A103: Республика Тыва | B103: 168.6 | C103: 337.5 | D103: 112.3 | E103: 28934 | F103: 22219 | G103: 57793 | H103: 108 | I103: =H103/C103*1000*1000 -> 320000 | J103: 25.4 | K103: 263 | L103: 27.3 | M103: 2.3 | N103: 4.8 | O103: 0.5 | P103: 9.7 | Q103: 1.3 | R103: 8.4 | S103: 172.7 | T103: 43 | U103: 6091 | V103: Республика Тыва
A104: Республика Хакасия | B104: 61.6 | C104: 528.2 | D104: 248.2 | E104: 34999 | F104: 30215 | G104: 62015 | H104: 349 | I104: =H104/C104*1000*1000 -> 660734.57 | J104: 59.9 | K104: 1012 | L104: 139.3 | M104: 168.3 | N104: 66.6 | O104: 3 | P104: 20.4 | Q104: 7.7 | R104: 12.7 | S104: 372.8 | T104: 129.3 | U104: 28730 | V104: Республика Хакасия
A105: Алтайский край | B105: 168 | C105: 2115.3 | D105: 1057.8 | E105: 36431 | F105: 28083 | G105: 46137 | H105: 945 | I105: =H105/C105*1000*1000 -> 446745.14 | J105: 179.9 | K105: 2739 | L105: 12 | M105: 597.7 | N105: 49.3 | O105: 17.2 | P105: 221.1 | Q105: 140.2 | R105: 80.9 | S105: 945.8 | T105: 505.9 | U105: 103906 | V105: Алтайский край
A106: Красноярский край | B106: 2366.8 | C106: 2846.1 | D106: 1409.4 | E106: 50380 | F106: 36883 | G106: 81056 | H106: 3319 | I106: =H106/C106*1000*1000 -> 1166157.2 | J106: 926.4 | K106: 8085 | L106: 1166.1 | M106: 1896.1 | N106: 249.2 | O106: 48.4 | P106: 118.4 | Q106: 61.7 | R106: 56.7 | S106: 1630.7 | T106: 782.7 | U106: 1147040 | V106: Красноярский край
A107: Иркутская область | B107: 774.8 | C107: 2330.5 | D107: 1093.7 | E107: 42483 | F107: 32201 | G107: 74257 | H107: 2357 | I107: =H107/C107*1000*1000 -> 1011371 | J107: 910.2 | K107: 5702 | L107: 992.6 | M107: 793.8 | N107: 191.2 | O107: 29.5 | P107: 80.7 | Q107: 29 | R107: 51.7 | S107: 1490.7 | T107: 616.8 | U107: 431697 | V107: Иркутская область
...

Sheet Культурные факторы
A1: Регион | B1: Численность зрителей театров, человек | C1: Стадионы с трибунами на 1500 мест и более | D1: Библиотечный фонд на 1 000 человек населения (на конец года; экземпляров) | E1: ВЫПУСК ГАЗЕТ на 1 000 человек населения | F1: Численность детей, отдохнувших в них за лето, тыс. человек
A2: Белгородская область | B2: =VLOOKUP($A2,'театры, музеи'!$A$2:$H$112,7,FALSE) -> 152 | C2: =VLOOKUP($A2,'спортивные сооружния'!A4:G112,7,FALSE) -> 23 | D2: =VLOOKUP($A2,библиотеки!A4:H116,7,FALSE) -> 6001 | E2: =VLOOKUP($A2,Газеты!$A$3:$G$111,7,FALSE) -> 852 | F2: =VLOOKUP($A2,Лагеря!$A$3:$F$113,6,FALSE) -> 59.5
A3: Брянская область | B3: =VLOOKUP($A3,'театры, музеи'!$A$2:$H$112,7,FALSE) -> 173 | C3: =VLOOKUP($A3,'спортивные сооружния'!A5:G113,7,FALSE) -> 18 | D3: =VLOOKUP($A3,библиотеки!A5:H117,7,FALSE) -> 6792 | E3: =VLOOKUP($A3,Газеты!$A$3:$G$111,7,FALSE) -> 234 | F3: =VLOOKUP($A3,Лагеря!$A$3:$F$113,6,FALSE) -> 33.1
A4: Владимирская область | B4: =VLOOKUP($A4,'театры, музеи'!$A$2:$H$112,7,FALSE) -> 78 | C4: =VLOOKUP($A4,'спортивные сооружния'!A6:G114,7,FALSE) -> 28 | D4: =VLOOKUP($A4,библиотеки!A6:H118,7,FALSE) -> 6592 | E4: =VLOOKUP($A4,Газеты!$A$3:$G$111,7,FALSE) -> 552 | F4: =VLOOKUP($A4,Лагеря!$A$3:$F$113,6,FALSE) -> 46.3
A5: Воронежская область | B5: =VLOOKUP($A5,'театры, музеи'!$A$2:$H$112,7,FALSE) -> 228 | C5: =VLOOKUP($A5,'спортивные сооружния'!A7:G115,7,FALSE) -> 10 | D5: =VLOOKUP($A5,библиотеки!A7:H119,7,FALSE) -> 5899 | E5: =VLOOKUP($A5,Газеты!$A$3:$G$111,7,FALSE) -> 480 | F5: =VLOOKUP($A5,Лагеря!$A$3:$F$113,6,FALSE) -> 69.4
A6: Ивановская область | B6: =VLOOKUP($A6,'театры, музеи'!$A$2:$H$112,7,FALSE) -> 350 | C6: =VLOOKUP($A6,'спортивные сооружния'!A8:G116,7,FALSE) -> 14 | D6: =VLOOKUP($A6,библиотеки!A8:H120,7,FALSE) -> 8511 | E6: =VLOOKUP($A6,Газеты!$A$3:$G$111,7,FALSE) -> 321 | F6: =VLOOKUP($A6,Лагеря!$A$3:$F$113,6,FALSE) -> 25.4
A7: Калужская область | B7: =VLOOKUP($A7,'театры, музеи'!$A$2:$H$112,7,FALSE) -> 205 | C7: =VLOOKUP($A7,'спортивные сооружния'!A9:G117,7,FALSE) -> 15 | D7: =VLOOKUP($A7,библиотеки!A9:H121,7,FALSE) -> 6642 | E7: =VLOOKUP($A7,Газеты!$A$3:$G$111,7,FALSE) -> 622 | F7: =VLOOKUP($A7,Лагеря!$A$3:$F$113,6,FALSE) -> 27
A8: Костромская область | B8: =VLOOKUP($A8,'театры, музеи'!$A$2:$H$112,7,FALSE) -> 257 | C8: =VLOOKUP($A8,'спортивные сооружния'!A10:G118,7,FALSE) -> 6 | D8: =VLOOKUP($A8,библиотеки!A10:H122,7,FALSE) -> 10260 | E8: =VLOOKUP($A8,Газеты!$A$3:$G$111,7,FALSE) -> 386 | F8: =VLOOKUP($A8,Лагеря!$A$3:$F$113,6,FALSE) -> 25.1
A9: Курская область | B9: =VLOOKUP($A9,'театры, музеи'!$A$2:$H$112,7,FALSE) -> 234 | C9: =VLOOKUP($A9,'спортивные сооружния'!A11:G119,7,FALSE) -> 9 | D9: =VLOOKUP($A9,библиотеки!A11:H123,7,FALSE) -> 8072 | E9: =VLOOKUP($A9,Газеты!$A$3:$G$111,7,FALSE) -> 394 | F9: =VLOOKUP($A9,Лагеря!$A$3:$F$113,6,FALSE) -> 29
A10: Липецкая область | B10: =VLOOKUP($A10,'театры, музеи'!$A$2:$H$112,7,FALSE) -> 200 | C10: =VLOOKUP($A10,'спортивные сооружния'!A12:G120,7,FALSE) -> 22 | D10: =VLOOKUP($A10,библиотеки!A12:H124,7,FALSE) -> 6891 | E10: =VLOOKUP($A10,Газеты!$A$3:$G$111,7,FALSE) -> 132 | F10: =VLOOKUP($A10,Лагеря!$A$3:$F$113,6,FALSE) -> 43.8
A11: Московская область | B11: =VLOOKUP($A11,'театры, музеи'!$A$2:$H$112,7,FALSE) -> 104 | C11: =VLOOKUP($A11,'спортивные сооружния'!A13:G121,7,FALSE) -> 118 | D11: =VLOOKUP($A11,библиотеки!A13:H125,7,FALSE) -> 1831 | E11: =VLOOKUP($A11,Газеты!$A$3:$G$111,7,FALSE) -> 198 | F11: =VLOOKUP($A11,Лагеря!$A$3:$F$113,6,FALSE) -> 104.8
A12: Орловская область | B12: =VLOOKUP($A12,'театры, музеи'!$A$2:$H$112,7,FALSE) -> 327 | C12: =VLOOKUP($A12,'спортивные сооружния'!A14:G122,7,FALSE) -> 3 | D12: =VLOOKUP($A12,библиотеки!A14:H126,7,FALSE) -> 6796 | E12: =VLOOKUP($A12,Газеты!$A$3:$G$111,7,FALSE) -> 188 | F12: =VLOOKUP($A12,Лагеря!$A$3:$F$113,6,FALSE) -> 23.7
A13: Рязанская область | B13: =VLOOKUP($A13,'театры, музеи'!$A$2:$H$112,7,FALSE) -> 264 | C13: =VLOOKUP($A13,'спортивные сооружния'!A15:G123,7,FALSE) -> 13 | D13: =VLOOKUP($A13,библиотеки!A15:H127,7,FALSE) -> 5850 | E13: =VLOOKUP($A13,Газеты!$A$3:$G$111,7,FALSE) -> 408 | F13: =VLOOKUP($A13,Лагеря!$A$3:$F$113,6,FALSE) -> 20.7
... A22: Архангельская область | B22: =VLOOKUP($A22,'театры, музеи'!$A$2:$H$112,7,FALSE) -> 256 | C22: =VLOOKUP($A22,'спортивные сооружния'!A24:G132,7,FALSE) -> 7 | D22: =VLOOKUP($A22,библиотеки!A24:H136,7,FALSE) -> 7313 | E22: =VLOOKUP($A22,Газеты!$A$3:$G$111,7,FALSE) -> 1250 | F22: =VLOOKUP($A22,Лагеря!$A$3:$F$113,6,FALSE) -> 31.7
A23: Архангельская область без автономного округа | B23: =VLOOKUP($A23,'театры, музеи'!$A$2:$H$112,7,FALSE) -> 267 | C23: =VLOOKUP($A23,'спортивные сооружния'!A26:G134,7,FALSE) -> 7 | D23: =VLOOKUP($A23,библиотеки!A26:H138,7,FALSE) -> 7243 | E23: =VLOOKUP($A23,Газеты!$A$3:$G$111,7,FALSE) -> 1250 | F23: =VLOOKUP($A23,Лагеря!$A$3:$F$113,6,FALSE) -> 29.9
A24: Вологодская область | B24: =VLOOKUP($A24,'театры, музеи'!$A$2:$H$112,7,FALSE) -> 264 | C24: =VLOOKUP($A24,'спортивные сооружния'!A27:G135,7,FALSE) -> 11 | D24: =VLOOKUP($A24,библиотеки!A27:H139,7,FALSE) -> 6058 | E24: =VLOOKUP($A24,Газеты!$A$3:$G$111,7,FALSE) -> 1061 | F24: =VLOOKUP($A24,Лагеря!$A$3:$F$113,6,FALSE) -> 33.1
A25: Калинингpадская область | B25: =VLOOKUP($A25,'театры, музеи'!$A$2:$H$112,7,FALSE) -> 211 | C25: =VLOOKUP($A25,'спортивные сооружния'!A28:G136,7,FALSE) -> 6 | D25: =VLOOKUP($A25,библиотеки!A28:H140,7,FALSE) -> 4206 | E25: =VLOOKUP($A25,Газеты!$A$3:$G$111,7,FALSE) -> 319 | F25: =VLOOKUP($A25,Лагеря!$A$3:$F$113,6,FALSE) -> 46.1
A26: Ленинградская область | B26: =VLOOKUP($A26,'театры, музеи'!$A$2:$H$112,7,FALSE) -> 126 | C26: =VLOOKUP($A26,'спортивные сооружния'!A29:G137,7,FALSE) -> 20 | D26: =VLOOKUP($A26,библиотеки!A29:H141,7,FALSE) -> 3229 | E26: =VLOOKUP($A26,Газеты!$A$3:$G$111,7,FALSE) -> 130 | F26: =VLOOKUP($A26,Лагеря!$A$3:$F$113,6,FALSE) -> 60.5
A27: Мурманская область | B27: =VLOOKUP($A27,'театры, музеи'!$A$2:$H$112,7,FALSE) -> 214 | C27: =VLOOKUP($A27,'спортивные сооружния'!A30:G138,7,FALSE) -> 6 | D27: =VLOOKUP($A27,библиотеки!A30:H142,7,FALSE) -> 7443 | E27: =VLOOKUP($A27,Газеты!$A$3:$G$111,7,FALSE) -> 837 | F27: =VLOOKUP($A27,Лагеря!$A$3:$F$113,6,FALSE) -> 7.3
A28: Новгородская область | B28: =VLOOKUP($A28,'театры, музеи'!$A$2:$H$112,7,FALSE) -> 115 | C28: =VLOOKUP($A28,'спортивные сооружния'!A31:G139,7,FALSE) -> 2 | D28: =VLOOKUP($A28,библиотеки!A31:H143,7,FALSE) -> 7900 | E28: =VLOOKUP($A28,Газеты!$A$3:$G$111,7,FALSE) -> 717 | F28: =VLOOKUP($A28,Лагеря!$A$3:$F$113,6,FALSE) -> 16.4
A29: Псковская область | B29: =VLOOKUP($A29,'театры, музеи'!$A$2:$H$112,7,FALSE) -> 204 | C29: =VLOOKUP($A29,'спортивные сооружния'!A32:G140,7,FALSE) -> 7 | D29: =VLOOKUP($A29,библиотеки!A32:H144,7,FALSE) -> 10512 | E29: =VLOOKUP($A29,Газеты!$A$3:$G$111,7,FALSE) -> 353 | F29: =VLOOKUP($A29,Лагеря!$A$3:$F$113,6,FALSE) -> 12
A30: г. Санкт-Петербург | B30: =VLOOKUP($A30,'театры, музеи'!$A$2:$H$112,7,FALSE) -> 822 | C30: =VLOOKUP($A30,'спортивные сооружния'!A33:G141,7,FALSE) -> 9 | D30: =VLOOKUP($A30,библиотеки!A33:H145,7,FALSE) -> 9919 | E30: =VLOOKUP($A30,Газеты!$A$3:$G$111,7,FALSE) -> 1313 | F30: =VLOOKUP($A30,Лагеря!$A$3:$F$113,6,FALSE) -> 35.2
A31: Республика Адыгея | B31: =VLOOKUP($A31,'театры, музеи'!$A$2:$H$112,7,FALSE) -> 181 | C31: =VLOOKUP($A31,'спортивные сооружния'!A34:G143,7,FALSE) -> 3 | D31: =VLOOKUP($A31,библиотеки!A35:H147,7,FALSE) -> 4936 | E31: =VLOOKUP($A31,Газеты!$A$3:$G$111,7,FALSE) -> 186 | F31: =VLOOKUP($A31,Лагеря!$A$3:$F$113,6,FALSE) -> 4.9
A32: Республика Крым | B32: =VLOOKUP($A32,'театры, музеи'!$A$2:$H$112,7,FALSE) -> 228 | C32: =VLOOKUP($A32,'спортивные сооружния'!A36:G145,7,FALSE) -> 30 | D32: =VLOOKUP($A32,библиотеки!A37:H149,7,FALSE) -> 5223 | E32: =VLOOKUP($A32,Газеты!$A$3:$G$111,7,FALSE) -> 136 | F32: =VLOOKUP($A32,Лагеря!$A$3:$F$113,6,FALSE) -> 67.7
A33: Краснодарский край | B33: =VLOOKUP($A33,'театры, музеи'!$A$2:$H$112,7,FALSE) -> 103 | C33: =VLOOKUP($A33,'спортивные сооружния'!A37:G146,7,FALSE) -> 82 | D33: =VLOOKUP($A33,библиотеки!A38:H150,7,FALSE) -> 3875 | E33: =VLOOKUP($A33,Газеты!$A$3:$G$111,7,FALSE) -> 230 | F33: =VLOOKUP($A33,Лагеря!$A$3:$F$113,6,FALSE) -> 191.4
A34: Астраханская область | B34: =VLOOKUP($A34,'театры, музеи'!$A$2:$H$112,7,FALSE) -> 283 | C34: =VLOOKUP($A34,'спортивные сооружния'!A38:G147,7,FALSE) -> 8 | D34: =VLOOKUP($A34,библиотеки!A38:H151,7,FALSE) -> 6029 | E34: =VLOOKUP($A34,Газеты!$A$3:$G$111,7,FALSE) -> 104 | F34: =VLOOKUP($A34,Лагеря!$A$3:$F$113,6,FALSE) -> 14
A35: Волгоградская область | B35: =VLOOKUP($A35,'театры, музеи'!$A$2:$H$112,7,FALSE) -> 214 | C35: =VLOOKUP($A35,'спортивные сооружния'!A39:G148,7,FALSE) -> 35 | D35: =VLOOKUP($A35,библиотеки!A39:H152,7,FALSE) -> 5061 | E35: =VLOOKUP($A35,Газеты!$A$3:$G$111,7,FALSE) -> 156 | F35: =VLOOKUP($A35,Лагеря!$A$3:$F$113,6,FALSE) -> 78.3
A36: Ростовская область | B36: =VLOOKUP($A36,'театры, музеи'!$A$2:$H$112,7,FALSE) -> 204 | C36: =VLOOKUP($A36,'спортивные сооружния'!A40:G149,7,FALSE) -> 56 | D36: =VLOOKUP($A36,библиотеки!A40:H153,7,FALSE) -> 5036 | E36: =VLOOKUP($A36,Газеты!$A$3:$G$111,7,FALSE) -> 310 | F36: =VLOOKUP($A36,Лагеря!$A$3:$F$113,6,FALSE) -> 59.3
A37: г. Севастополь | B37: =VLOOKUP($A37,'театры, музеи'!$A$2:$H$112,7,FALSE) -> 358 | C37: =VLOOKUP($A37,'спортивные сооружния'!A41:G150,7,FALSE) -> 3 | D37: =VLOOKUP($A37,библиотеки!A41:H154,7,FALSE) -> 2693 | E37: =VLOOKUP($A37,Газеты!$A$3:$G$111,7,FALSE) -> 195 | F37: =VLOOKUP($A37,Лагеря!$A$3:$F$113,6,FALSE) -> 4.8
A38: Республика Дагестан | B38: =VLOOKUP($A38,'театры, музеи'!$A$2:$H$112,7,FALSE) -> 122 | C38: =VLOOKUP($A38,'спортивные сооружния'!A43:G152,7,FALSE) -> 13 | D38: =VLOOKUP($A38,библиотеки!A43:H156,7,FALSE) -> 2339 | E38: =VLOOKUP($A38,Газеты!$A$3:$G$111,7,FALSE) -> 56 | F38: =VLOOKUP($A38,Лагеря!$A$3:$F$113,6,FALSE) -> 26.4
A39: Кабардино-Балкарская Республика | B39: =VLOOKUP($A39,'театры, музеи'!$A$2:$H$112,7,FALSE) -> 210 | C39: =VLOOKUP($A39,'спортивные сооружния'!A45:G154,7,FALSE) -> 11 | D39: =VLOOKUP($A39,библиотеки!A45:H158,7,FALSE) -> 5527 | E39: =VLOOKUP($A39,Газеты!$A$3:$G$111,7,FALSE) -> 49 | F39: =VLOOKUP($A39,Лагеря!$A$3:$F$113,6,FALSE) -> 2.6
A40: Карачаево-Черкесская Республика | B40: =VLOOKUP($A40,'театры, музеи'!$A$2:$H$112,7,FALSE) -> 99 | C40: =VLOOKUP($A40,'спортивные сооружния'!A46:G155,7,FALSE) -> 4 | D40: =VLOOKUP($A40,библиотеки!A46:H159,7,FALSE) -> 5343 | E40: =VLOOKUP($A40,Газеты!$A$3:$G$111,7,FALSE) -> 95 | F40: =VLOOKUP($A40,Лагеря!$A$3:$F$113,6,FALSE) -> 6.6
A41: Республика Северная Осетия | B41: =VLOOKUP($A41,'театры, музеи'!$A$2:$H$112,7,FALSE) -> 317 | C41: =VLOOKUP($A41,'спортивные сооружния'!A47:G156,7,FALSE) -> 12 | D41: =VLOOKUP($A41,библиотеки!A47:H160,7,FALSE) -> 4936 | E41: =VLOOKUP($A41,Газеты!$A$3:$G$111,7,FALSE) -> 85 | F41: =VLOOKUP($A41,Лагеря!$A$3:$F$113,6,FALSE) -> 16.5
A42: Чеченская Республика | B42: =VLOOKUP($A42,'театры, музеи'!$A$2:$H$112,7,FALSE) -> 154 | C42: =VLOOKUP($A42,'спортивные сооружния'!A48:G157,7,FALSE) -> 13 | D42: =VLOOKUP($A42,библиотеки!A48:H161,7,FALSE) -> 1483 | E42: =VLOOKUP($A42,Газеты!$A$3:$G$111,7,FALSE) -> 28 | F42: =VLOOKUP($A42,Лагеря!$A$3:$F$113,6,FALSE) -> 9
A43: Ставропольский край | B43: =VLOOKUP($A43,'театры, музеи'!$A$2:$H$112,7,FALSE) -> 117 | C43: =VLOOKUP($A43,'спортивные сооружния'!A49:G158,7,FALSE) -> 40 | D43: =VLOOKUP($A43,библиотеки!A49:H162,7,FALSE) -> 5289 | E43: =VLOOKUP($A43,Газеты!$A$3:$G$111,7,FALSE) -> 173 | F43: =VLOOKUP($A43,Лагеря!$A$3:$F$113,6,FALSE) -> 78.1
A44: Республика Башкортостан | B44: =VLOOKUP($A44,'театры, музеи'!$A$2:$H$112,7,FALSE) -> 257 | C44: =VLOOKUP($A44,'спортивные сооружния'!A51:G160,7,FALSE) -> 25 | D44: =VLOOKUP($A44,библиотеки!A51:H164,7,FALSE) -> 6490 | E44: =VLOOKUP($A44,Газеты!$A$3:$G$111,7,FALSE) -> 278 | F44: =VLOOKUP($A44,Лагеря!$A$3:$F$113,6,FALSE) -> 174.7
A45: Республика Марий Эл | B45: =VLOOKUP($A45,'театры, музеи'!$A$2:$H$112,7,FALSE) -> 561 | C45: =VLOOKUP($A45,'спортивные сооружния'!A52:G161,7,FALSE) -> 8 | D45: =VLOOKUP($A45,библиотеки!A52:H165,7,FALSE) -> 6956 | E45: =VLOOKUP($A45,Газеты!$A$3:$G$111,7,FALSE) -> 1618 | F45: =VLOOKUP($A45,Лагеря!$A$3:$F$113,6,FALSE) -> 22.1
A46: Республика Мордовия | B46: =VLOOKUP($A46,'театры, музеи'!$A$2:$H$112,7,FALSE) -> 324 | C46: =VLOOKUP($A46,'спортивные сооружния'!A53:G162,7,FALSE) -> 6 | D46: =VLOOKUP($A46,библиотеки!A53:H166,7,FALSE) -> 7886 | E46: =VLOOKUP($A46,Газеты!$A$3:$G$111,7,FALSE) -> 225 | F46: =VLOOKUP($A46,Лагеря!$A$3:$F$113,6,FALSE) -> 23.6
A47: Республика Татарстан | B47: =VLOOKUP($A47,'театры, музеи'!$A$2:$H$112,7,FALSE) -> 341 | C47: =VLOOKUP($A47,'спортивные сооружния'!A54:G163,7,FALSE) -> 46 | D47: =VLOOKUP($A47,библиотеки!A54:H167,7,FALSE) -> 5868 | E47: =VLOOKUP($A47,Газеты!$A$3:$G$111,7,FALSE) -> 349 | F47: =VLOOKUP($A47,Лагеря!$A$3:$F$113,6,FALSE) -> 147
A48: Удмуртская Республика | B48: =VLOOKUP($A48,'театры, музеи'!$A$2:$H$112,7,FALSE) -> 312 | C48: =VLOOKUP($A48,'спортивные сооружния'!A55:G164,7,FALSE) -> 25 | D48: =VLOOKUP($A48,библиотеки!A55:H168,7,FALSE) -> 3663 | E48: =VLOOKUP($A48,Газеты!$A$3:$G$111,7,FALSE) -> 520 | F48: =VLOOKUP($A48,Лагеря!$A$3:$F$113,6,FALSE) -> 55.9
A49: Чувашская Республика | B49: =VLOOKUP($A49,'театры, музеи'!$A$2:$H$112,7,FALSE) -> 388 | C49: =VLOOKUP($A49,'спортивные сооружния'!A56:G165,7,FALSE) -> 12 | D49: =VLOOKUP($A49,библиотеки!A56:H169,7,FALSE) -> 7548 | E49: =VLOOKUP($A49,Газеты!$A$3:$G$111,7,FALSE) -> 509 | F49: =VLOOKUP($A49,Лагеря!$A$3:$F$113,6,FALSE) -> 31.9
A50: Пермский край | B50: =VLOOKUP($A50,'театры, музеи'!$A$2:$H$112,7,FALSE) -> 349 | C50: =VLOOKUP($A50,'спортивные сооружния'!A56:G166,7,FALSE) -> 25 | D50: =VLOOKUP($A50,библиотеки!A57:H170,7,FALSE) -> 4738 | E50: =VLOOKUP($A50,Газеты!$A$3:$G$111,7,FALSE) -> 370 | F50: =VLOOKUP($A50,Лагеря!$A$3:$F$113,6,FALSE) -> 97.6
A51: Кировская область | B51: =VLOOKUP($A51,'театры, музеи'!$A$2:$H$112,7,FALSE) -> 236 | C51: =VLOOKUP($A51,'спортивные сооружния'!A57:G167,7,FALSE) -> 24 | D51: =VLOOKUP($A51,библиотеки!A58:H171,7,FALSE) -> 10482 | E51: =VLOOKUP($A51,Газеты!$A$3:$G$111,7,FALSE) -> 605 | F51: =VLOOKUP($A51,Лагеря!$A$3:$F$113,6,FALSE) -> 51.1
A52: Нижегородская область | B52: =VLOOKUP($A52,'театры, музеи'!$A$2:$H$112,7,FALSE) -> 317 | C52: =VLOOKUP($A52,'спортивные сооружния'!A57:G168,7,FALSE) -> 42 | D52: =VLOOKUP($A52,библиотеки!A59:H172,7,FALSE) -> 5806 | E52: =VLOOKUP($A52,Газеты!$A$3:$G$111,7,FALSE) -> 1201 | F52: =VLOOKUP($A52,Лагеря!$A$3:$F$113,6,FALSE) -> 97.5
A53: Оренбургская область | B53: =VLOOKUP($A53,'театры, музеи'!$A$2:$H$112,7,FALSE) -> 220 | C53: =VLOOKUP($A53,'спортивные сооружния'!A58:G169,7,FALSE) -> 35 | D53: =VLOOKUP($A53,библиотеки!A60:H173,7,FALSE) -> 6593 | E53: =VLOOKUP($A53,Газеты!$A$3:$G$111,7,FALSE) -> 291 | F53: =VLOOKUP($A53,Лагеря!$A$3:$F$113,6,FALSE) -> 61.5
A54: Пензенская область | B54: =VLOOKUP($A54,'театры, музеи'!$A$2:$H$112,7,FALSE) -> 175 | C54: =VLOOKUP($A54,'спортивные сооружния'!A58:G170,7,FALSE) -> 25 | D54: =VLOOKUP($A54,библиотеки!A61:H174,7,FALSE) -> 6641 | E54: =VLOOKUP($A54,Газеты!$A$3:$G$111,7,FALSE) -> 455 | F54: =VLOOKUP($A54,Лагеря!$A$3:$F$113,6,FALSE) -> 38.5
A55: Самарская область | B55: =VLOOKUP($A55,'театры, музеи'!$A$2:$H$112,7,FALSE) -> 277 | C55: =VLOOKUP($A55,'спортивные сооружния'!A59:G171,7,FALSE) -> 39 | D55: =VLOOKUP($A55,библиотеки!A62:H175,7,FALSE) -> 5198 | E55: =VLOOKUP($A55,Газеты!$A$3:$G$111,7,FALSE) -> 285 | F55: =VLOOKUP($A55,Лагеря!$A$3:$F$113,6,FALSE) -> 93.5
A56: Саратовская область | B56: =VLOOKUP($A56,'театры, музеи'!$A$2:$H$112,7,FALSE) -> 266 | C56: =VLOOKUP($A56,'спортивные сооружния'!A60:G172,7,FALSE) -> 24 | D56: =VLOOKUP($A56,библиотеки!A62:H176,7,FALSE) -> 5728 | E56: =VLOOKUP($A56,Газеты!$A$3:$G$111,7,FALSE) -> 405 | F56: =VLOOKUP($A56,Лагеря!$A$3:$F$113,6,FALSE) -> 50.8
A57: Ульяновская область | B57: =VLOOKUP($A57,'театры, музеи'!$A$2:$H$112,7,FALSE) -> 189 | C57: =VLOOKUP($A57,'спортивные сооружния'!A61:G173,7,FALSE) -> 17 | D57: =VLOOKUP($A57,библиотеки!A63:H177,7,FALSE) -> 6888 | E57: =VLOOKUP($A57,Газеты!$A$3:$G$111,7,FALSE) -> 1143 | F57: =VLOOKUP($A57,Лагеря!$A$3:$F$113,6,FALSE) -> 40.7
A58: Свердловская область | B58: =VLOOKUP($A58,'театры, музеи'!$A$2:$H$112,7,FALSE) -> 325 | C58: =VLOOKUP($A58,'спортивные сооружния'!A64:G176,7,FALSE) -> 45 | D58: =VLOOKUP($A58,библиотеки!A66:H180,7,FALSE) -> 3656 | E58: =VLOOKUP($A58,Газеты!$A$3:$G$111,7,FALSE) -> 375 | F58: =VLOOKUP($A58,Лагеря!$A$3:$F$113,6,FALSE) -> 36.6
A59: Тюменская область | B59: =VLOOKUP($A59,'театры, музеи'!$A$2:$H$112,7,FALSE) -> 200 | C59: =VLOOKUP($A59,'спортивные сооружния'!A65:G177,7,FALSE) -> 22 | D59: =VLOOKUP($A59,библиотеки!A67:H181,7,FALSE) -> 4066 | E59: =VLOOKUP($A59,Газеты!$A$3:$G$111,7,FALSE) -> 204 | F59: =VLOOKUP($A59,Лагеря!$A$3:$F$113,6,FALSE) -> 180.2
A60: Ханты-Мансийский автономный округ | B60: =VLOOKUP($A60,'театры, музеи'!$A$2:$H$112,7,FALSE) -> 162 | C60: =VLOOKUP($A60,'спортивные сооружния'!A66:G178,7,FALSE) -> 4 | D60: =VLOOKUP($A60,библиотеки!A68:H182,7,FALSE) -> 3069 | E60: =VLOOKUP($A60,Газеты!$A$3:$G$111,7,FALSE) -> 222 | F60: =VLOOKUP($A60,Лагеря!$A$3:$F$113,6,FALSE) -> 49
A61: Тюменская область без автономных округов | B61: =VLOOKUP($A61,'театры, музеи'!$A$2:$H$112,7,FALSE) -> 304 | C61: =VLOOKUP($A61,'спортивные сооружния'!A68:G180,7,FALSE) -> 18 | D61: =VLOOKUP($A61,библиотеки!A70:H184,7,FALSE) -> 5600 | E61: =VLOOKUP($A61,Газеты!$A$3:$G$111,7,FALSE) -> 193 | F61: =VLOOKUP($A61,Лагеря!$A$3:$F$113,6,FALSE) -> 100.9
A62: Челябинская область | B62: =VLOOKUP($A62,'театры, музеи'!$A$2:$H$112,7,FALSE) -> 225 | C62: =VLOOKUP($A62,'спортивные сооружния'!A69:G181,7,FALSE) -> 37 | D62: =VLOOKUP($A62,библиотеки!A71:H185,7,FALSE) -> 4393 | E62: =VLOOKUP($A62,Газеты!$A$3:$G$111,7,FALSE) -> 450 | F62: =VLOOKUP($A62,Лагеря!$A$3:$F$113,6,FALSE) -> 140.1
A63: Республика Алтай | B63: =VLOOKUP($A63,'театры, музеи'!$A$2:$H$112,7,FALSE) -> 135 | C63: =VLOOKUP($A63,'спортивные сооружния'!A71:G183,7,FALSE) -> 8 | D63: =VLOOKUP($A63,библиотеки!A73:H187,7,FALSE) -> 6933 | E63: =VLOOKUP($A63,Газеты!$A$3:$G$111,7,FALSE) -> 318 | F63: =VLOOKUP($A63,Лагеря!$A$3:$F$113,6,FALSE) -> 10
A64: Республика Тыва | B64: =VLOOKUP($A64,'театры, музеи'!$A$2:$H$112,7,FALSE) -> 420 | C64: =VLOOKUP($A64,'спортивные сооружния'!A72:G184,7,FALSE) -> 10 | D64: =VLOOKUP($A64,библиотеки!A74:H188,7,FALSE) -> 8732 | E64: =VLOOKUP($A64,Газеты!$A$3:$G$111,7,FALSE) -> 73 | F64: =VLOOKUP($A64,Лагеря!$A$3:$F$113,6,FALSE) -> 16.7
A65: Республика Хакасия | B65: =VLOOKUP($A65,'театры, музеи'!$A$2:$H$112,7,FALSE) -> 258 | C65: =VLOOKUP($A65,'спортивные сооружния'!A73:G185,7,FALSE) -> 21 | D65: =VLOOKUP($A65,библиотеки!A75:H189,7,FALSE) -> 5661 | E65: =VLOOKUP($A65,Газеты!$A$3:$G$111,7,FALSE) -> 788 | F65: =VLOOKUP($A65,Лагеря!$A$3:$F$113,6,FALSE) -> 21.9
A66: Алтайский край | B66: =VLOOKUP($A66,'театры, музеи'!$A$2:$H$112,7,FALSE) -> 234 | C66: =VLOOKUP($A66,'спортивные сооружния'!A74:G186,7,FALSE) -> 49 | D66: =VLOOKUP($A66,библиотеки!A76:H190,7,FALSE) -> 6028 | E66: =VLOOKUP($A66,Газеты!$A$3:$G$111,7,FALSE) -> 294 | F66: =VLOOKUP($A66,Лагеря!$A$3:$F$113,6,FALSE) -> 97.8
A67: Красноярский край | B67: =VLOOKUP($A67,'театры, музеи'!$A$2:$H$112,7,FALSE) -> 385 | C67: =VLOOKUP($A67,'спортивные сооружния'!A75:G187,7,FALSE) -> 16 | D67: =VLOOKUP($A67,библиотеки!A77:H191,7,FALSE) -> 6333 | E67: =VLOOKUP($A67,Газеты!$A$3:$G$111,7,FALSE) -> 314 | F67: =VLOOKUP($A67,Лагеря!$A$3:$F$113,6,FALSE) -> 107.4
A68: Иркутская область | B68: =VLOOKUP($A68,'театры, музеи'!$A$2:$H$112,7,FALSE) -> 251 | C68: =VLOOKUP($A68,'спортивные сооружния'!A76:G188,7,FALSE) -> 24 | D68: =VLOOKUP($A68,библиотеки!A78:H192,7,FALSE) -> 4597 | E68: =VLOOKUP($A68,Газеты!$A$3:$G$111,7,FALSE) -> 354 | F68: =VLOOKUP($A68,Лагеря!$A$3:$F$113,6,FALSE) -> 79.9
A69: Кемеровская область | B69: =VLOOKUP($A69,'театры, музеи'!$A$2:$H$112,7,FALSE) -> 178 | C69: =VLOOKUP($A69,'спортивные сооружния'!A77:G189,7,FALSE) -> 26 | D69: =VLOOKUP($A69,библиотеки!A79:H193,7,FALSE) -> 4961 | E69: =VLOOKUP($A69,Газеты!$A$3:$G$111,7,FALSE) -> 122 | F69: =VLOOKUP($A69,Лагеря!$A$3:$F$113,6,FALSE) -> 103.9
A70: Новосибирская область | B70: =VLOOKUP($A70,'театры, музеи'!$A$2:$H$112,7,FALSE) -> 394 | C70: =VLOOKUP($A70,'спортивные сооружния'!A78:G190,7,FALSE) -> 24 | D70: =VLOOKUP($A70,библиотеки!A80:H194,7,FALSE) -> 3889 | E70: =VLOOKUP($A70,Газеты!$A$3:$G$111,7,FALSE) -> 363 | F70: =VLOOKUP($A70,Лагеря!$A$3:$F$113,6,FALSE) -> 107.1
A71: Омская область | B71: =VLOOKUP($A71,'театры, музеи'!$A$2:$H$112,7,FALSE) -> 342 | C71: =VLOOKUP($A71,'спортивные сооружния'!A79:G191,7,FALSE) -> 39 | D71: =VLOOKUP($A71,библиотеки!A81:H195,7,FALSE) -> 7002 | E71: =VLOOKUP($A71,Газеты!$A$3:$G$111,7,FALSE) -> 266 | F71: =VLOOKUP($A71,Лагеря!$A$3:$F$113,6,FALSE) -> 67.2
A72: Томская область | B72: =VLOOKUP($A72,'театры, музеи'!$A$2:$H$112,7,FALSE) -> 278 | C72: =VLOOKUP($A72,'спортивные сооружния'!A80:G192,7,FALSE) -> 14 | D72: =VLOOKUP($A72,библиотеки!A82:H196,7,FALSE) -> 4694 | E72: =VLOOKUP($A72,Газеты!$A$3:$G$111,7,FALSE) -> 416 | F72: =VLOOKUP($A72,Лагеря!$A$3:$F$113,6,FALSE) -> 42.8
A73: Республика Бурятия | B73: =VLOOKUP($A73,'театры, музеи'!$A$2:$H$112,7,FALSE) -> 263 | C73: =VLOOKUP($A73,'спортивные сооружния'!A82:G194,7,FALSE) -> 19 | D73: =VLOOKUP($A73,библиотеки!A84:H198,7,FALSE) -> 5587 | E73: =VLOOKUP($A73,Газеты!$A$3:$G$111,7,FALSE) -> 342 | F73: =VLOOKUP($A73,Лагеря!$A$3:$F$113,6,FALSE) -> 31.8
A74: Республика Саха (Якутия) | B74: =VLOOKUP($A74,'театры, музеи'!$A$2:$H$112,7,FALSE) -> 242 | C74: =VLOOKUP($A74,'спортивные сооружния'!A83:G195,7,FALSE) -> 24 | D74: =VLOOKUP($A74,библиотеки!A85:H199,7,FALSE) -> 8837 | E74: =VLOOKUP($A74,Газеты!$A$3:$G$111,7,FALSE) -> 135 | F74: =VLOOKUP($A74,Лагеря!$A$3:$F$113,6,FALSE) -> 34.5
A75: Забайкальский край | B75: =VLOOKUP($A75,'театры, музеи'!$A$2:$H$112,7,FALSE) -> 276 | C75: =VLOOKUP($A75,'спортивные сооружния'!A83:G196,7,FALSE) -> 12 | D75: =VLOOKUP($A75,библиотеки!A86:H200,7,FALSE) -> 6518 | E75: =VLOOKUP($A75,Газеты!$A$3:$G$111,7,FALSE) -> 163 | F75: =VLOOKUP($A75,Лагеря!$A$3:$F$113,6,FALSE) -> 37.2
A76: Камчатский край | B76: =VLOOKUP($A76,'театры, музеи'!$A$2:$H$112,7,FALSE) -> 271 | C76: =VLOOKUP($A76,'спортивные сооружния'!A84:G197,7,FALSE) -> 1 | D76: =VLOOKUP($A76,библиотеки!A87:H201,7,FALSE) -> 7520 | E76: =VLOOKUP($A76,Газеты!$A$3:$G$111,7,FALSE) -> 487 | F76: =VLOOKUP($A76,Лагеря!$A$3:$F$113,6,FALSE) -> 12.9
A77: Приморский край | B77: =VLOOKUP($A77,'театры, музеи'!$A$2:$H$112,7,FALSE) -> 318 | C77: =VLOOKUP($A77,'спортивные сооружния'!A85:G198,7,FALSE) -> 24 | D77: =VLOOKUP($A77,библиотеки!A88:H202,7,FALSE) -> 3577 | E77: =VLOOKUP($A77,Газеты!$A$3:$G$111,7,FALSE) -> 150 | F77: =VLOOKUP($A77,Лагеря!$A$3:$F$113,6,FALSE) -> 92.2
A78: Хабаровский край | B78: =VLOOKUP($A78,'театры, музеи'!$A$2:$H$112,7,FALSE) -> 246 | C78: =VLOOKUP($A78,'спортивные сооружния'!A85:G199,7,FALSE) -> 16 | D78: =VLOOKUP($A78,библиотеки!A88:H203,7,FALSE) -> 7103 | E78: =VLOOKUP($A78,Газеты!$A$3:$G$111,7,FALSE) -> 193 | F78: =VLOOKUP($A78,Лагеря!$A$3:$F$113,6,FALSE) -> 40.3
A79: Амурская область | B79: =VLOOKUP($A79,'театры, музеи'!$A$2:$H$112,7,FALSE) -> 172 | C79: =VLOOKUP($A79,'спортивные сооружния'!A86:G200,7,FALSE) -> 26 | D79: =VLOOKUP($A79,библиотеки!A89:H204,7,FALSE) -> 4829 | E79: =VLOOKUP($A79,Газеты!$A$3:$G$111,7,FALSE) -> 208 | F79: =VLOOKUP($A79,Лагеря!$A$3:$F$113,6,FALSE) -> 19.7
A80: Магаданская область | B80: =VLOOKUP($A80,'театры, музеи'!$A$2:$H$112,7,FALSE) -> 350 | C80: =VLOOKUP($A80,'спортивные сооружния'!A87:G201,7,FALSE) -> 1 | D80: =VLOOKUP($A80,библиотеки!A89:H205,7,FALSE) -> 10550 | E80: =VLOOKUP($A80,Газеты!$A$3:$G$111,7,FALSE) -> 280 | F80: =VLOOKUP($A80,Лагеря!$A$3:$F$113,6,FALSE) -> 7.3
A81: Сахалинская область | B81: =VLOOKUP($A81,'театры, музеи'!$A$2:$H$112,7,FALSE) -> 246 | C81: =VLOOKUP($A81,'спортивные сооружния'!A88:G202,7,FALSE) -> 3 | D81: =VLOOKUP($A81,библиотеки!A90:H206,7,FALSE) -> 6276 | E81: =VLOOKUP($A81,Газеты!$A$3:$G$111,7,FALSE) -> 160 | F81: =VLOOKUP($A81,Лагеря!$A$3:$F$113,6,FALSE) -> 27.3
A82: Еврейская автономная область | B82: =VLOOKUP($A82,'театры, музеи'!$A$2:$H$112,7,FALSE) -> 138 | C82: =VLOOKUP($A82,'спортивные сооружния'!A89:G203,7,FALSE) -> 2 | D82: =VLOOKUP($A82,библиотеки!A91:H207,7,FALSE) -> 8834 | E82: =VLOOKUP($A82,Газеты!$A$3:$G$111,7,FALSE) -> 173 | F82: =VLOOKUP($A82,Лагеря!$A$3:$F$113,6,FALSE) -> 8.2
A83: Чукотский автономный округ | B83: 0 | C83: 0 | D83: =VLOOKUP($A83,библиотеки!A92:H208,7,FALSE) -> 14479 | E83: =VLOOKUP($A83,Газеты!$A$3:$G$111,7,FALSE) -> 108 | F83: =VLOOKUP($A83,Лагеря!$A$3:$F$113,6,FALSE) -> 4.2

Sheet Экономические факторы
A1: Регион | B1: СРЕДНЕГОДОВАЯ ЧИСЛЕННОСТЬ ЗАНЯТЫХ | C1: РЕАЛЬНЫЕ ДЕНЕЖНЫЕ ДОХОДЫ НАСЕЛЕНИЯ | D1: ВРП на душу | E1: Плотность населения чел/км2 | F1: Инвестиции основной капитал млрд руб | G1: Численность населения тыс. чел.
A2: Белгородская область | B2: =VLOOKUP($A2,занятые!$A$2:$G$108,7,FALSE) -> 765.3 | C2: =VLOOKUP($A2,Доход!$A$2:$G$108,7,FALSE) -> 47257 | D2: =VLOOKUP($A2,Основные!$A$2:$I$126,9,FALSE) -> 873592.32 | E2: =VLOOKUP($A2,Основные!$A$2:$I$126,3,FALSE)/VLOOKUP($A2,Основные!$A$2:$I$126,2,FALSE) -> 55.376384 | F2: =VLOOKUP($A2,Основные!$A$2:$K$126,10,FALSE) -> 212.2 | G2: 1500.7
A3: Брянская область | B3: =VLOOKUP($A3,занятые!$A$2:$G$108,7,FALSE) -> 504.5 | C3: =VLOOKUP($A3,Доход!$A$2:$G$108,7,FALSE) -> 40927 | D3: =VLOOKUP($A3,Основные!$A$2:$I$126,9,FALSE) -> 480567.23 | E3: =VLOOKUP($A3,Основные!$A$2:$I$126,3,FALSE)/VLOOKUP($A3,Основные!$A$2:$I$126,2,FALSE) -> 32.733524 | F3: =VLOOKUP($A3,Основные!$A$2:$K$126,10,FALSE) -> 94.1 | G3: 1142.4
A4: Владимирская область | B4: =VLOOKUP($A4,занятые!$A$2:$G$108,7,FALSE) -> 639 | C4: =VLOOKUP($A4,Доход!$A$2:$G$108,7,FALSE) -> 38649 | D4: =VLOOKUP($A4,Основные!$A$2:$I$126,9,FALSE) -> 596228.72 | E4: =VLOOKUP($A4,Основные!$A$2:$I$126,3,FALSE)/VLOOKUP($A4,Основные!$A$2:$I$126,2,FALSE) -> 45.013746 | F4: =VLOOKUP($A4,Основные!$A$2:$K$126,10,FALSE) -> 181.7 | G4: 1309.9
A5: Воронежская область | B5: =VLOOKUP($A5,занятые!$A$2:$G$108,7,FALSE) -> 1151.6 | C5: =VLOOKUP($A5,Доход!$A$2:$G$108,7,FALSE) -> 45087 | D5: =VLOOKUP($A5,Основные!$A$2:$I$126,9,FALSE) -> 606140.58 | E5: =VLOOKUP($A5,Основные!$A$2:$I$126,3,FALSE)/VLOOKUP($A5,Основные!$A$2:$I$126,2,FALSE) -> 43.551724 | F5: =VLOOKUP($A5,Основные!$A$2:$K$126,10,FALSE) -> 374.1 | G5: 2273.4
A6: Ивановская область | B6: =VLOOKUP($A6,занятые!$A$2:$G$108,7,FALSE) -> 422.2 | C6: =VLOOKUP($A6,Доход!$A$2:$G$108,7,FALSE) -> 41108 | D6: =VLOOKUP($A6,Основные!$A$2:$I$126,9,FALSE) -> 401810.35 | E6: =VLOOKUP($A6,Основные!$A$2:$I$126,3,FALSE)/VLOOKUP($A6,Основные!$A$2:$I$126,2,FALSE) -> 42.331776 | F6: =VLOOKUP($A6,Основные!$A$2:$K$126,10,FALSE) -> 67.5 | G6: 905.9
A7: Калужская область | B7: =VLOOKUP($A7,занятые!$A$2:$G$108,7,FALSE) -> 536.9 | C7: =VLOOKUP($A7,Доход!$A$2:$G$108,7,FALSE) -> 44564 | D7: =VLOOKUP($A7,Основные!$A$2:$I$126,9,FALSE) -> 649569.45 | E7: =VLOOKUP($A7,Основные!$A$2:$I$126,3,FALSE)/VLOOKUP($A7,Основные!$A$2:$I$126,2,FALSE) -> 35.852349 | F7: =VLOOKUP($A7,Основные!$A$2:$K$126,10,FALSE) -> 125.7 | G7: 1068.4
A8: Костромская область | B8: =VLOOKUP($A8,занятые!$A$2:$G$108,7,FALSE) -> 257.3 | C8: =VLOOKUP($A8,Доход!$A$2:$G$108,7,FALSE) -> 43668 | D8: =VLOOKUP($A8,Основные!$A$2:$I$126,9,FALSE) -> 487374.18 | E8: =VLOOKUP($A8,Основные!$A$2:$I$126,3,FALSE)/VLOOKUP($A8,Основные!$A$2:$I$126,2,FALSE) -> 9.4069767 | F8: =VLOOKUP($A8,Основные!$A$2:$K$126,10,FALSE) -> 47.9 | G8: 566.3
A9: Курская область | B9: =VLOOKUP($A9,занятые!$A$2:$G$108,7,FALSE) -> 502.6 | C9: =VLOOKUP($A9,Доход!$A$2:$G$108,7,FALSE) -> 43719 | D9: =VLOOKUP($A9,Основные!$A$2:$I$126,9,FALSE) -> 627768.88 | E9: =VLOOKUP($A9,Основные!$A$2:$I$126,3,FALSE)/VLOOKUP($A9,Основные!$A$2:$I$126,2,FALSE) -> 35.363333 | F9: =VLOOKUP($A9,Основные!$A$2:$K$126,10,FALSE) -> 231.2 | G9: 1060.9
A10: Липецкая область | B10: =VLOOKUP($A10,занятые!$A$2:$G$108,7,FALSE) -> 565.7 | C10: =VLOOKUP($A10,Доход!$A$2:$G$108,7,FALSE) -> 45458 | D10: =VLOOKUP($A10,Основные!$A$2:$I$126,9,FALSE) -> 710382.51 | E10: =VLOOKUP($A10,Основные!$A$2:$I$126,3,FALSE)/VLOOKUP($A10,Основные!$A$2:$I$126,2,FALSE) -> 46.5125 | F10: =VLOOKUP($A10,Основные!$A$2:$K$126,10,FALSE) -> 187.2 | G10: 1116.3
A11: Московская область | B11: =VLOOKUP($A11,занятые!$A$2:$G$108,7,FALSE) -> 3991.8 | C11: =VLOOKUP($A11,Доход!$A$2:$G$108,7,FALSE) -> 64870 | D11: =VLOOKUP($A11,Основные!$A$2:$I$126,9,FALSE) -> 892467.03 | E11: =VLOOKUP($A11,Основные!$A$2:$I$126,3,FALSE)/VLOOKUP($A11,Основные!$A$2:$I$126,2,FALSE) -> 195.28894 | F11: =VLOOKUP($A11,Основные!$A$2:$K$126,10,FALSE) -> 1593.5 | G11: 8651.3
A12: Орловская область | B12: =VLOOKUP($A12,занятые!$A$2:$G$108,7,FALSE) -> 301.5 | C12: =VLOOKUP($A12,Доход!$A$2:$G$108,7,FALSE) -> 43730 | D12: =VLOOKUP($A12,Основные!$A$2:$I$126,9,FALSE) -> 534296.03 | E12: =VLOOKUP($A12,Основные!$A$2:$I$126,3,FALSE)/VLOOKUP($A12,Основные!$A$2:$I$126,2,FALSE) -> 28.036437 | F12: =VLOOKUP($A12,Основные!$A$2:$K$126,10,FALSE) -> 58.4 | G12: 692.5
A13: Рязанская область | B13: =VLOOKUP($A13,занятые!$A$2:$G$108,7,FALSE) -> 499.7 | C13: =VLOOKUP($A13,Доход!$A$2:$G$108,7,FALSE) -> 39905 | D13: =VLOOKUP($A13,Основные!$A$2:$I$126,9,FALSE) -> 571983 | E13: =VLOOKUP($A13,Основные!$A$2:$I$126,3,FALSE)/VLOOKUP($A13,Основные!$A$2:$I$126,2,FALSE) -> 27.328283 | F13: =VLOOKUP($A13,Основные!$A$2:$K$126,10,FALSE) -> 101.3 | G13: 1082.2
... A81: Сахалинская область | B81: =VLOOKUP($A81,занятые!$A$2:$G$108,7,FALSE) -> 280.1 | C81: =VLOOKUP($A81,Доход!$A$2:$G$108,7,FALSE) -> 87902 | D81: =VLOOKUP($A81,Основные!$A$2:$I$126,9,FALSE) -> 3343531.5 | E81: =VLOOKUP($A81,Основные!$A$2:$I$126,3,FALSE)/VLOOKUP($A81,Основные!$A$2:$I$126,2,FALSE) -> 5.2537313 | F81: =VLOOKUP($A81,Основные!$A$2:$K$126,10,FALSE) -> 305.4 | G81: 457.6
A82: Еврейская автономная область | B82: =VLOOKUP($A82,занятые!$A$2:$G$108,7,FALSE) -> 60.2 | C82: =VLOOKUP($A82,Доход!$A$2:$G$110,7,FALSE) -> 43479 | D82: =VLOOKUP($A82,Основные!$A$2:$I$126,9,FALSE) -> 555555.56 | E82: =VLOOKUP($A82,Основные!$A$2:$I$126,3,FALSE)/VLOOKUP($A82,Основные!$A$2:$I$126,2,FALSE) -> 4.0165289 | F82: =VLOOKUP($A82,Основные!$A$2:$K$126,10,FALSE) -> 29.3 | G82: 145.8
A83: Чукотский автономный округ | B83: =VLOOKUP($A83,занятые!$A$2:$G$108,7,FALSE) -> 32 | C83: =VLOOKUP($A83,Доход!$A$2:$G$110,7,FALSE) -> 156988 | D83: =VLOOKUP($A83,Основные!$A$2:$I$126,9,FALSE) -> 2937500 | E83: =VLOOKUP($A83,Основные!$A$2:$I$126,3,FALSE)/VLOOKUP($A83,Основные!$A$2:$I$126,2,FALSE) -> 0.066528067 | F83: =VLOOKUP($A83,Основные!$A$2:$K$126,10,FALSE) -> 88.2 | G83: 48

Sheet Данные
A1: Регион | B1: Численность зрителей театров, на тыс чел | C1: Стадионы с трибунами на 1500 мест и более на 100 чел | D1: Численность пользователей библиотек на 1000 чел | E1: ВЫПУСК ГАЗЕТ на 1 000 человек населения | F1: Численность детей, отдохнувших в них за лето на 1000 человек | G1: СРЕДНЕГОДОВАЯ ЧИСЛЕННОСТЬ ЗАНЯТЫХ на 100 чел | H1: РЕАЛЬНЫЕ ДЕНЕЖНЫЕ ДОХОДЫ НАСЕЛЕНИЯ | I1: ВРП на душу | J1: Инвестиции основной капитал | K1: Плотность населения чел/км2 | M1: Место занимаемое в России | N1: Численность зрителей театров, на тыс. чел | O1: Стадионы с трибунами на 1500 мест и более | P1: Численность пользователей библиотек на тыс. чел | Q1: ВЫПУСК ГАЗЕТ на 1 000 человек населения | R1: Численность детей, отдохнувших в них за лето на 1000 человек | S1: СРЕДНЕГОДОВАЯ ЧИСЛЕННОСТЬ ЗАНЯТЫХ на 100 чел | T1: РЕАЛЬНЫЕ ДЕНЕЖНЫЕ ДОХОДЫ НАСЕЛЕНИЯ | U1: ВРП на душу | V1: Численность населения | W1: Инвестиции основной капитал
A2: Белгородская область | B2: 152 | C2: =IFERROR(VLOOKUP($A2,'спортивные сооружния'!A4:G112,7,FALSE)/'Экономические факторы'!G2*100,0) -> 1.5326181 | D2: =VLOOKUP($A2,библиотеки!A4:N116,14,FALSE)/'Экономические факторы'!G2*1000 -> 497.10135 | E2: =VLOOKUP($A2,Газеты!$A$3:$G$111,7,FALSE) -> 852 | F2: ='Культурные факторы'!F2/'Экономические факторы'!G2*1000 -> 39.648164 | G2: ='Экономические факторы'!B2/'Экономические факторы'!G2*100 -> 50.996202 | H2: 47257 | I2: 873592.32 | J2: ='Экономические факторы'!F2/'Экономические факторы'!G2*1000 -> 141.40068 | K2: 55.376384 | M2: 1 | N2: {=INDEX($A$2:$A$83,_xlfn.XMATCH(LARGE(B$2:B$83,ROW(N1)),B$2:B$83,0,1))} -> г. Санкт-Петербург | O2: {=INDEX($A$2:$A$83,_xlfn.XMATCH(LARGE(C$2:C$83,ROW(O1)),C$2:C$83,0,1))} -> Республика Хакасия | P2: {=INDEX($A$2:$A$83,_xlfn.XMATCH(LARGE(D$2:D$83,ROW(P1)),D$2:D$83,0,1))} -> Костромская область | Q2: {=INDEX($A$2:$A$83,_xlfn.XMATCH(LARGE(E$2:E$83,ROW(Q1)),E$2:E$83,0,1))} -> Смоленская область | R2: {=INDEX($A$2:$A$83,_xlfn.XMATCH(LARGE(F$2:F$83,ROW(R1)),F$2:F$83,0,1))} -> Чукотский автономный округ | S2: {=INDEX($A$2:$A$83,_xlfn.XMATCH(LARGE(G$2:G$83,ROW(S1)),G$2:G$83,0,1))} -> Чукотский автономный округ | T2: {=INDEX($A$2:$A$83,_xlfn.XMATCH(LARGE(H$2:H$83,ROW(T1)),H$2:H$83,0,1))} -> Чукотский автономный округ | U2: {=INDEX($A$2:$A$83,_xlfn.XMATCH(LARGE(I$2:I$83,ROW(U1)),I$2:I$83,0,1))} -> Ханты-Мансийский автономный округ | V2: {=INDEX($A$2:$A$83,_xlfn.XMATCH(LARGE(K$2:K$83,ROW(V1)),K$2:K$83,0,1))} -> г. Москва | W2: {=INDEX($A$2:$A$83,_xlfn.XMATCH(LARGE(J$2:J$83,ROW(W1)),J$2:J$83,0,1))} -> Чукотский автономный округ
A3: Брянская область | B3: 173 | C3: =IFERROR(VLOOKUP($A3,'спортивные сооружния'!A5:G113,7,FALSE)/'Экономические факторы'!G3*100,0) -> 1.5756303 | D3: =VLOOKUP($A3,библиотеки!A5:N117,14,FALSE)/'Экономические факторы'!G3*1000 -> 426.29552 | E3: =VLOOKUP($A3,Газеты!$A$3:$G$111,7,FALSE) -> 234 | F3: ='Культурные факторы'!F3/'Экономические факторы'!G3*1000 -> 28.97409 | G3: ='Экономические факторы'!B3/'Экономические факторы'!G3*100 -> 44.161415 | H3: 40927 | I3: 480567.23 | J3: ='Экономические факторы'!F3/'Экономические факторы'!G3*1000 -> 82.370448 | K3: 32.733524 | M3: 2 | N3: {=INDEX($A$2:$A$83,_xlfn.XMATCH(LARGE(B$2:B$83,ROW(N2)),B$2:B$83,0,1))} -> Республика Марий Эл | O3: {=INDEX($A$2:$A$83,_xlfn.XMATCH(LARGE(C$2:C$83,ROW(O2)),C$2:C$83,0,1))} -> Республика Алтай | P3: {=INDEX($A$2:$A$83,_xlfn.XMATCH(LARGE(D$2:D$83,ROW(P2)),D$2:D$83,0,1))} -> Кировская область | Q3: {=INDEX($A$2:$A$83,_xlfn.XMATCH(LARGE(E$2:E$83,ROW(Q2)),E$2:E$83,0,1))} -> г. Москва | R3: {=INDEX($A$2:$A$83,_xlfn.XMATCH(LARGE(F$2:F$83,ROW(R2)),F$2:F$83,0,1))} -> Тюменская область без автономных округов | S3: {=INDEX($A$2:$A$83,_xlfn.XMATCH(LARGE(G$2:G$83,ROW(S2)),G$2:G$83,0,1))} -> г. Москва | T3: {=INDEX($A$2:$A$83,_xlfn.XMATCH(LARGE(H$2:H$83,ROW(T2)),H$2:H$83,0,1))} -> г. Москва | U3: {=INDEX($A$2:$A$83,_xlfn.XMATCH(LARGE(I$2:I$83,ROW(U2)),I$2:I$83,0,1))} -> Тюменская область | V3: {=INDEX($A$2:$A$83,_xlfn.XMATCH(LARGE(K$2:K$83,ROW(V2)),K$2:K$83,0,1))} -> г. Санкт-Петербург | W3: {=INDEX($A$2:$A$83,_xlfn.XMATCH(LARGE(J$2:J$83,ROW(W2)),J$2:J$83,0,1))} -> Амурская область
